USB_PHY/nrzi_decoder.v
module nrzi_decoder(
	input wire clk,
	input wire dp,
	input wire dm,
	input wire reset,
	output reg bit
);
	reg dpp,dmp;
	
	initial begin
		dpp = 1'b0;
		bit = 1'b0;
		dmp = 1'b0;
	end
	
	always@(posedge clk or posedge reset)begin
		if(reset) begin
			dpp <= 1'b0;
			dmp <= 1'b0;
			bit <= 1'b0;
		end
		else begin
			dpp <= dp;
			dmp <= dm;
			if(dp==~dpp && dm==~dmp) begin
				bit <= 1'b0;
			end
			else begin
				bit <= 1'b1;
			end
		end
	end
endmodule

USB_PHY/oversampler.v
module oversampler(
	input clk_8x,
	input d_plus_device,
	input d_minus_device,
	input reset,
	output reg dp,
	output reg dm
);
	reg [2:0]counter;
	reg counter_en;
	reg dp_pa,dm_pa;
	
	initial begin
		counter = 3'd0;
		counter_en = 1'b0;
		dp = 1'b0;
		dm = 1'b0;
	end
	
	always@(posedge clk_8x or posedge reset) begin
		if(reset) begin
			counter<=3'd0;
			counter_en <= 1'b0;
			dp <= 1'b0;
			dm <= 1'b0;
			dp_pa <= 1'b0;
			dm_pa <= 1'b0;
		end
		else begin
			if(dp_pa != d_plus_device || dm_pa != d_minus_device) begin
				counter_en <= 1'b1;
				counter <= 3'd1;
			end
		end
		dp_pa <= d_plus_device;
		dm_pa <= d_minus_device;
		if(counter_en) begin
			counter <= (counter==3'd7)?3'd0:counter+1;
			if(counter == 3'd4) begin
				dp <= d_plus_device;
				dm <= d_minus_device;
			end
		end
	end
endmodule

USB_PHY/test.v
`timescale 1ps / 1ps;
module test;
reg clk;
reg dpl;
reg dmi;
reg reset;
reg clk_8x;
//wire dp,dm;
wire bit,dptmp,dmtmp;
wire dp_prev=test.u_nd.dpp;
wire dm_prev=test.u_nd.dmp;
oversampler u_os(
	.clk_8x(clk_8x),
	.d_plus_device(dpl),
	.d_minus_device(dmi),
	.reset(reset),
	.dp(dptmp),
	.dm(dmtmp)
	
);
nrzi_decoder u_nd(
	.clk(clk),
	.dp(dptmp),
	.dm(dmtmp),
	.reset(reset),
	.bit(bit)
);
initial begin
	$dumpfile("test.vcd");
	$dumpvars(0,test);
	$display("time | clk | clk_8x | dplus | dminus | dplus_samp | dminus_samp | reset |counter|bit|");
end

always@ (posedge clk_8x) begin
	$display(" %3t | %3t |  %3t   |   %b   |   %b    |     %b      |      %b      |   %b   |  %3d  | %b |",$time/125,clk,clk_8x,dpl,dmi,dptmp,dmtmp,reset,test.u_os.counter,bit);
end



initial begin
	clk = 0;
	clk_8x = 0;
	reset = 0;
	dpl = 0;
	dmi =0;
end
always begin
	# 125 clk_8x = ~clk_8x;
end
always begin
	#1000 clk = ~clk;
end

	initial begin
		#0 {dpl,dmi} = 2'b00;
		#500;
		#2000 {dpl,dmi} = 2'b10;
		#2000 {dpl,dmi} = 2'b01;
		#2000 {dpl,dmi} = 2'b10;
		#2000 {dpl,dmi} = 2'b01;
		#2000 {dpl,dmi} = 2'b10;
		#2000 {dpl,dmi} = 2'b01;
		#2000 {dpl,dmi} = 2'b10;
		#10000; 
		 $finish;
	end
endmodule

USB_PHY/test.vcd
$date
	Thu Oct  2 20:01:02 2025
$end
$version
	Icarus Verilog
$end
$timescale
	1ps
$end
$scope module test $end
$var wire 1 ! dm_prev $end
$var wire 1 " dp_prev $end
$var wire 1 # dptmp $end
$var wire 1 $ dmtmp $end
$var wire 1 % bit $end
$var reg 1 & clk $end
$var reg 1 ' clk_8x $end
$var reg 1 ( dmi $end
$var reg 1 ) dpl $end
$var reg 1 * reset $end
$scope module u_nd $end
$var wire 1 & clk $end
$var wire 1 * reset $end
$var wire 1 # dp $end
$var wire 1 $ dm $end
$var reg 1 % bit $end
$var reg 1 + dmp $end
$var reg 1 , dpp $end
$upscope $end
$scope module u_os $end
$var wire 1 ' clk_8x $end
$var wire 1 ( d_minus_device $end
$var wire 1 ) d_plus_device $end
$var wire 1 * reset $end
$var reg 3 - counter [2:0] $end
$var reg 1 . counter_en $end
$var reg 1 $ dm $end
$var reg 1 / dm_pa $end
$var reg 1 # dp $end
$var reg 1 0 dp_pa $end
$upscope $end
$upscope $end
$enddefinitions $end
$comment Show the parameter values. $end
$dumpall
$end
#0
$dumpvars
x0
x/
0.
b0 -
0,
0+
0*
0)
0(
0'
0&
0%
0$
0#
0"
0!
$end
#125
0/
00
1'
#250
0'
#375
1'
#500
0'
#625
1'
#750
0'
#875
1'
#1000
1%
0'
1&
#1125
1'
#1250
0'
#1375
1'
#1500
0'
#1625
1'
#1750
0'
#1875
1'
#2000
0'
0&
#2125
1'
#2250
0'
#2375
1'
#2500
0'
1)
#2625
10
b1 -
1.
1'
#2750
0'
#2875
b10 -
1'
#3000
0'
1&
#3125
b11 -
1'
#3250
0'
#3375
b100 -
1'
#3500
0'
#3625
1#
b101 -
1'
#3750
0'
#3875
b110 -
1'
#4000
0'
0&
#4125
b111 -
1'
#4250
0'
#4375
b0 -
1'
#4500
0'
0)
1(
#4625
1/
00
b1 -
1'
#4750
0'
#4875
b10 -
1'
#5000
1"
1,
0'
1&
#5125
b11 -
1'
#5250
0'
#5375
b100 -
1'
#5500
0'
#5625
1$
0#
b101 -
1'
#5750
0'
#5875
b110 -
1'
#6000
0'
0&
#6125
b111 -
1'
#6250
0'
#6375
b0 -
1'
#6500
0'
1)
0(
#6625
0/
10
b1 -
1'
#6750
0'
#6875
b10 -
1'
#7000
0%
1!
1+
0"
0,
0'
1&
#7125
b11 -
1'
#7250
0'
#7375
b100 -
1'
#7500
0'
#7625
0$
1#
b101 -
1'
#7750
0'
#7875
b110 -
1'
#8000
0'
0&
#8125
b111 -
1'
#8250
0'
#8375
b0 -
1'
#8500
0'
0)
1(
#8625
1/
00
b1 -
1'
#8750
0'
#8875
b10 -
1'
#9000
0!
0+
1"
1,
0'
1&
#9125
b11 -
1'
#9250
0'
#9375
b100 -
1'
#9500
0'
#9625
1$
0#
b101 -
1'
#9750
0'
#9875
b110 -
1'
#10000
0'
0&
#10125
b111 -
1'
#10250
0'
#10375
b0 -
1'
#10500
0'
1)
0(
#10625
0/
10
b1 -
1'
#10750
0'
#10875
b10 -
1'
#11000
1!
1+
0"
0,
0'
1&
#11125
b11 -
1'
#11250
0'
#11375
b100 -
1'
#11500
0'
#11625
0$
1#
b101 -
1'
#11750
0'
#11875
b110 -
1'
#12000
0'
0&
#12125
b111 -
1'
#12250
0'
#12375
b0 -
1'
#12500
0'
0)
1(
#12625
1/
00
b1 -
1'
#12750
0'
#12875
b10 -
1'
#13000
0!
0+
1"
1,
0'
1&
#13125
b11 -
1'
#13250
0'
#13375
b100 -
1'
#13500
0'
#13625
1$
0#
b101 -
1'
#13750
0'
#13875
b110 -
1'
#14000
0'
0&
#14125
b111 -
1'
#14250
0'
#14375
b0 -
1'
#14500
0'
1)
0(
#14625
0/
10
b1 -
1'
#14750
0'
#14875
b10 -
1'
#15000
1!
1+
0"
0,
0'
1&
#15125
b11 -
1'
#15250
0'
#15375
b100 -
1'
#15500
0'
#15625
0$
1#
b101 -
1'
#15750
0'
#15875
b110 -
1'
#16000
0'
0&
#16125
b111 -
1'
#16250
0'
#16375
b0 -
1'
#16500
0'
#16625
b1 -
1'
#16750
0'
#16875
b10 -
1'
#17000
0!
0+
1"
1,
0'
1&
#17125
b11 -
1'
#17250
0'
#17375
b100 -
1'
#17500
0'
#17625
b101 -
1'
#17750
0'
#17875
b110 -
1'
#18000
0'
0&
#18125
b111 -
1'
#18250
0'
#18375
b0 -
1'
#18500
0'
#18625
b1 -
1'
#18750
0'
#18875
b10 -
1'
#19000
1%
0'
1&
#19125
b11 -
1'
#19250
0'
#19375
b100 -
1'
#19500
0'
#19625
b101 -
1'
#19750
0'
#19875
b110 -
1'
#20000
0'
0&
#20125
b111 -
1'
#20250
0'
#20375
b0 -
1'
#20500
0'
#20625
b1 -
1'
#20750
0'
#20875
b10 -
1'
#21000
0'
1&
#21125
b11 -
1'
#21250
0'
#21375
b100 -
1'
#21500
0'
#21625
b101 -
1'
#21750
0'
#21875
b110 -
1'
#22000
0'
0&
#22125
b111 -
1'
#22250
0'
#22375
b0 -
1'
#22500
0'
#22625
b1 -
1'
#22750
0'
#22875
b10 -
1'
#23000
0'
1&
#23125
b11 -
1'
#23250
0'
#23375
b100 -
1'
#23500
0'
#23625
b101 -
1'
#23750
0'
#23875
b110 -
1'
#24000
0'
0&
#24125
b111 -
1'
#24250
0'
#24375
b0 -
1'
