USB_PHY/sync_detector.v
module sync_detector(
	input wire b,
	input wire clk,
	input wire reset,
	output reg sync
);
	reg [5:0]count;
	initial begin
	 count = 6'd0;
	 sync =1'b0;
	end
	always@(posedge clk or posedge reset) begin
		if(reset) begin
			sync <= 1'b0;
			count <= 6'd0;
		end
		else begin
			if(b==1'b0) begin
				count <= count+1;
				sync <= 1'b0;
			end
			else if(count>=6'd30 && b==1'b1) begin
				sync <= 1'b1;
				count <= 6'd0;
			end
			else begin
				count <= 6'd0;
				sync <= 1'b0;
			end
		end
	end	
endmodule

USB_PHY/bit_unstuffer.v
module bit_unstuffer(
	input wire clk,
	input reset,
	input wire bit,
	output reg b,
	output reg unstuff
);
	reg [2:0]count;
	
	initial begin
		count = 3'd0;
		b = 1'b0;
		unstuff = 1'b0;
	end
	
	always@(posedge clk or posedge reset) begin
		if(reset) begin
			unstuff <= 1'b0;
			count <= 3'd0;
		end
		else begin
			b <= bit;
			if(bit==1'b1) begin
				count <= count+1;
				unstuff <= 1'b1;
			end
			else begin
				if(count>=3'd5) begin
					unstuff <= 1'b0;
					count <= 3'd0;
				end
				else begin
					count <= 3'd0;
					unstuff <= 1'b1;
				end
			end
		end
	end

endmodule

USB_PHY/nrzi_decoder.v
module nrzi_decoder(
	input wire clk,
	input wire dp,
	input wire dm,
	input wire reset,
	output reg bit
);
	reg dpp,dmp;
	
	initial begin
		dpp = 1'b0;
		bit = 1'b0;
		dmp = 1'b0;
	end
	
	always@(posedge clk or posedge reset)begin
		if(reset) begin
			dpp <= 1'b0;
			dmp <= 1'b0;
			bit <= 1'b0;
		end
		else begin
			dpp <= dp;
			dmp <= dm;
			if(dp==~dpp && dm==~dmp) begin
				bit <= 1'b0;
			end
			else begin
				bit <= 1'b1;
			end
		end
	end
endmodule

USB_PHY/oversampler.v
module oversampler(
	input clk_8x,
	input d_plus_device,
	input d_minus_device,
	input reset,
	output reg dp,
	output reg dm
);
	reg [2:0]counter;
	reg counter_en;
	reg dp_pa,dm_pa;
	
	initial begin
		counter = 3'd0;
		counter_en = 1'b0;
		dp = 1'b0;
		dm = 1'b0;
	end
	
	always@(posedge clk_8x or posedge reset) begin
		if(reset) begin
			counter<=3'd0;
			counter_en <= 1'b0;
			dp <= 1'b0;
			dm <= 1'b0;
			dp_pa <= 1'b0;
			dm_pa <= 1'b0;
		end
		else begin
			if(dp_pa != d_plus_device || dm_pa != d_minus_device) begin
				counter_en <= 1'b1;
				counter <= 3'd1;
			end
		end
		dp_pa <= d_plus_device;
		dm_pa <= d_minus_device;
		if(counter_en) begin
			counter <= (counter==3'd7)?3'd0:counter+1;
			if(counter == 3'd4) begin
				dp <= d_plus_device;
				dm <= d_minus_device;
			end
		end
	end
endmodule

USB_PHY/test.v
`timescale 1ps / 1ps;
module test;
reg clk,clk_8x;
reg dpl,dmi;
reg reset;
wire bit,dp,dm;
wire dp_prev=test.u_nd.dpp;
wire dm_prev=test.u_nd.dmp;
wire b,unstuff;
wire sync;
wire [5:0] sync_count = test.u_sd.count;
oversampler u_os(
	.clk_8x(clk_8x),
	.d_plus_device(dpl),
	.d_minus_device(dmi),
	.reset(reset),
	.dp(dp),
	.dm(dm)
	
);
nrzi_decoder u_nd(
	.clk(clk),
	.dp(dp),
	.dm(dm),
	.reset(reset),
	.bit(bit)
);
bit_unstuffer u_bu(
	.clk(clk),
	.reset(reset),
	.bit(bit),
	.b(b),
	.unstuff(unstuff)
);
sync_detector u_sd(
	.b(b),
	.clk(clk),
	.reset(reset),
	.sync(sync)
);
initial begin
	$dumpfile("test.vcd");
	$dumpvars(0,test);
	$display("time | clk | clk_8x | dplus | dminus | dplus_samp | dminus_samp | reset |counter|bit|");
end

always@ (posedge clk_8x) begin
	$display(" %3t | %3t |  %3t   |   %b   |   %b    |     %b      |      %b      |   %b   |  %3d  | %b |",$time/125,clk,clk_8x,dpl,dmi,dp,dm,reset,test.u_os.counter,bit);
end



initial begin
	clk = 0;
	clk_8x = 0;
	reset = 0;
end
always begin
	# 125 clk_8x = ~clk_8x;
end
always begin
	#1000 clk = ~clk;
end

	initial begin
		#0    {dpl,dmi} = 2'b00;
		#2000 {dpl,dmi} = 2'b10;
		#2000 {dpl,dmi} = 2'b10;
		#2000 {dpl,dmi} = 2'b10;
		#2000 {dpl,dmi} = 2'b10;
		#2000 {dpl,dmi} = 2'b10;
		#2000 {dpl,dmi} = 2'b10;
		#2000 {dpl,dmi} = 2'b10;
		#2000 {dpl,dmi} = 2'b01;
		#2000 {dpl,dmi} = 2'b01;
		#2000 {dpl,dmi} = 2'b10;
		#2000 {dpl,dmi} = 2'b10;
		#2000 {dpl,dmi} = 2'b10;
		for(integer i = 0;i<31;i++) begin
			#2000 {dpl,dmi} = {~dpl,~dmi};
		end
		#2000  {dpl,dmi} = 2'b01;
		#2000  {dpl,dmi} = 2'b01;
		 #8000 $finish;
	end
endmodule

USB_PHY/test.vcd
$date
	Fri Oct  3 22:40:47 2025
$end
$version
	Icarus Verilog
$end
$timescale
	1ps
$end
$scope module test $end
$var wire 1 ! dm_prev $end
$var wire 1 " dp_prev $end
$var wire 6 # sync_count [5:0] $end
$var wire 1 $ unstuff $end
$var wire 1 % sync $end
$var wire 1 & dp $end
$var wire 1 ' dm $end
$var wire 1 ( bit $end
$var wire 1 ) b $end
$var reg 1 * clk $end
$var reg 1 + clk_8x $end
$var reg 1 , dmi $end
$var reg 1 - dpl $end
$var reg 1 . reset $end
$scope module u_bu $end
$var wire 1 * clk $end
$var wire 1 . reset $end
$var wire 1 ( bit $end
$var reg 1 ) b $end
$var reg 3 / count [2:0] $end
$var reg 1 $ unstuff $end
$upscope $end
$scope module u_nd $end
$var wire 1 * clk $end
$var wire 1 . reset $end
$var wire 1 & dp $end
$var wire 1 ' dm $end
$var reg 1 ( bit $end
$var reg 1 0 dmp $end
$var reg 1 1 dpp $end
$upscope $end
$scope module u_os $end
$var wire 1 + clk_8x $end
$var wire 1 , d_minus_device $end
$var wire 1 - d_plus_device $end
$var wire 1 . reset $end
$var reg 3 2 counter [2:0] $end
$var reg 1 3 counter_en $end
$var reg 1 ' dm $end
$var reg 1 4 dm_pa $end
$var reg 1 & dp $end
$var reg 1 5 dp_pa $end
$upscope $end
$scope module u_sd $end
$var wire 1 ) b $end
$var wire 1 * clk $end
$var wire 1 . reset $end
$var reg 6 6 count [5:0] $end
$var reg 1 % sync $end
$upscope $end
$scope begin $ivl_for_loop0 $end
$var integer 32 7 i [31:0] $end
$upscope $end
$upscope $end
$enddefinitions $end
$comment Show the parameter values. $end
$dumpall
$end
#0
$dumpvars
bx 7
b0 6
x5
x4
03
b0 2
01
00
b0 /
0.
0-
0,
0+
0*
0)
0(
0'
0&
0%
0$
b0 #
0"
0!
$end
#125
04
05
1+
#250
0+
#375
1+
#500
0+
#625
1+
#750
0+
#875
1+
#1000
1(
1$
b1 #
b1 6
0+
1*
#1125
1+
#1250
0+
#1375
1+
#1500
0+
#1625
1+
#1750
0+
#1875
1+
#2000
0+
0*
1-
#2125
15
b1 2
13
1+
#2250
0+
#2375
b10 2
1+
#2500
0+
#2625
b11 2
1+
#2750
0+
#2875
b100 2
1+
#3000
b10 #
b10 6
b1 /
1)
0+
1*
#3125
1&
b101 2
1+
#3250
0+
#3375
b110 2
1+
#3500
0+
#3625
b111 2
1+
#3750
0+
#3875
b0 2
1+
#4000
0+
0*
#4125
b1 2
1+
#4250
0+
#4375
b10 2
1+
#4500
0+
#4625
b11 2
1+
#4750
0+
#4875
b100 2
1+
#5000
0(
1"
11
b10 /
b0 #
b0 6
0+
1*
#5125
b101 2
1+
#5250
0+
#5375
b110 2
1+
#5500
0+
#5625
b111 2
1+
#5750
0+
#5875
b0 2
1+
#6000
0+
0*
#6125
b1 2
1+
#6250
0+
#6375
b10 2
1+
#6500
0+
#6625
b11 2
1+
#6750
0+
#6875
b100 2
1+
#7000
b0 /
0)
1(
0+
1*
#7125
b101 2
1+
#7250
0+
#7375
b110 2
1+
#7500
0+
#7625
b111 2
1+
#7750
0+
#7875
b0 2
1+
#8000
0+
0*
#8125
b1 2
1+
#8250
0+
#8375
b10 2
1+
#8500
0+
#8625
b11 2
1+
#8750
0+
#8875
b100 2
1+
#9000
b1 /
1)
b1 #
b1 6
0+
1*
#9125
b101 2
1+
#9250
0+
#9375
b110 2
1+
#9500
0+
#9625
b111 2
1+
#9750
0+
#9875
b0 2
1+
#10000
0+
0*
#10125
b1 2
1+
#10250
0+
#10375
b10 2
1+
#10500
0+
#10625
b11 2
1+
#10750
0+
#10875
b100 2
1+
#11000
b0 #
b0 6
b10 /
0+
1*
#11125
b101 2
1+
#11250
0+
#11375
b110 2
1+
#11500
0+
#11625
b111 2
1+
#11750
0+
#11875
b0 2
1+
#12000
0+
0*
#12125
b1 2
1+
#12250
0+
#12375
b10 2
1+
#12500
0+
#12625
b11 2
1+
#12750
0+
#12875
b100 2
1+
#13000
b11 /
0+
1*
#13125
b101 2
1+
#13250
0+
#13375
b110 2
1+
#13500
0+
#13625
b111 2
1+
#13750
0+
#13875
b0 2
1+
#14000
0+
0*
#14125
b1 2
1+
#14250
0+
#14375
b10 2
1+
#14500
0+
#14625
b11 2
1+
#14750
0+
#14875
b100 2
1+
#15000
b100 /
0+
1*
#15125
b101 2
1+
#15250
0+
#15375
b110 2
1+
#15500
0+
#15625
b111 2
1+
#15750
0+
#15875
b0 2
1+
#16000
0+
0*
0-
1,
#16125
14
05
b1 2
1+
#16250
0+
#16375
b10 2
1+
#16500
0+
#16625
b11 2
1+
#16750
0+
#16875
b100 2
1+
#17000
b101 /
0+
1*
#17125
1'
0&
b101 2
1+
#17250
0+
#17375
b110 2
1+
#17500
0+
#17625
b111 2
1+
#17750
0+
#17875
b0 2
1+
#18000
0+
0*
#18125
b1 2
1+
#18250
0+
#18375
b10 2
1+
#18500
0+
#18625
b11 2
1+
#18750
0+
#18875
b100 2
1+
#19000
b110 /
0(
1!
10
0"
01
0+
1*
#19125
b101 2
1+
#19250
0+
#19375
b110 2
1+
#19500
0+
#19625
b111 2
1+
#19750
0+
#19875
b0 2
1+
#20000
0+
0*
1-
0,
#20125
04
15
b1 2
1+
#20250
0+
#20375
b10 2
1+
#20500
0+
#20625
b11 2
1+
#20750
0+
#20875
b100 2
1+
#21000
1(
b0 /
0$
0)
0+
1*
#21125
0'
1&
b101 2
1+
#21250
0+
#21375
b110 2
1+
#21500
0+
#21625
b111 2
1+
#21750
0+
#21875
b0 2
1+
#22000
0+
0*
#22125
b1 2
1+
#22250
0+
#22375
b10 2
1+
#22500
0+
#22625
b11 2
1+
#22750
0+
#22875
b100 2
1+
#23000
b1 #
b1 6
1$
b1 /
1)
0(
0!
00
1"
11
0+
1*
#23125
b101 2
1+
#23250
0+
#23375
b110 2
1+
#23500
0+
#23625
b111 2
1+
#23750
0+
#23875
b0 2
1+
#24000
0+
0*
b0 7
#24125
b1 2
1+
#24250
0+
#24375
b10 2
1+
#24500
0+
#24625
b11 2
1+
#24750
0+
#24875
b100 2
1+
#25000
1(
b0 /
0)
b0 #
b0 6
0+
1*
#25125
b101 2
1+
#25250
0+
#25375
b110 2
1+
#25500
0+
#25625
b111 2
1+
#25750
0+
#25875
b0 2
1+
#26000
0+
0*
b1 7
0-
1,
#26125
14
05
b1 2
1+
#26250
0+
#26375
b10 2
1+
#26500
0+
#26625
b11 2
1+
#26750
0+
#26875
b100 2
1+
#27000
b1 #
b1 6
b1 /
1)
0+
1*
#27125
1'
0&
b101 2
1+
#27250
0+
#27375
b110 2
1+
#27500
0+
#27625
b111 2
1+
#27750
0+
#27875
b0 2
1+
#28000
0+
0*
b10 7
1-
0,
#28125
04
15
b1 2
1+
#28250
0+
#28375
b10 2
1+
#28500
0+
#28625
b11 2
1+
#28750
0+
#28875
b100 2
1+
#29000
0(
1!
10
0"
01
b10 /
b0 #
b0 6
0+
1*
#29125
0'
1&
b101 2
1+
#29250
0+
#29375
b110 2
1+
#29500
0+
#29625
b111 2
1+
#29750
0+
#29875
b0 2
1+
#30000
0+
0*
b11 7
0-
1,
#30125
14
05
b1 2
1+
#30250
0+
#30375
b10 2
1+
#30500
0+
#30625
b11 2
1+
#30750
0+
#30875
b100 2
1+
#31000
b0 /
0)
0!
00
1"
11
0+
1*
#31125
1'
0&
b101 2
1+
#31250
0+
#31375
b110 2
1+
#31500
0+
#31625
b111 2
1+
#31750
0+
#31875
b0 2
1+
#32000
0+
0*
b100 7
1-
0,
#32125
04
15
b1 2
1+
#32250
0+
#32375
b10 2
1+
#32500
0+
#32625
b11 2
1+
#32750
0+
#32875
b100 2
1+
#33000
1!
10
0"
01
b1 #
b1 6
0+
1*
#33125
0'
1&
b101 2
1+
#33250
0+
#33375
b110 2
1+
#33500
0+
#33625
b111 2
1+
#33750
0+
#33875
b0 2
1+
#34000
0+
0*
b101 7
0-
1,
#34125
14
05
b1 2
1+
#34250
0+
#34375
b10 2
1+
#34500
0+
#34625
b11 2
1+
#34750
0+
#34875
b100 2
1+
#35000
b10 #
b10 6
0!
00
1"
11
0+
1*
#35125
1'
0&
b101 2
1+
#35250
0+
#35375
b110 2
1+
#35500
0+
#35625
b111 2
1+
#35750
0+
#35875
b0 2
1+
#36000
0+
0*
b110 7
1-
0,
#36125
04
15
b1 2
1+
#36250
0+
#36375
b10 2
1+
#36500
0+
#36625
b11 2
1+
#36750
0+
#36875
b100 2
1+
#37000
1!
10
0"
01
b11 #
b11 6
0+
1*
#37125
0'
1&
b101 2
1+
#37250
0+
#37375
b110 2
1+
#37500
0+
#37625
b111 2
1+
#37750
0+
#37875
b0 2
1+
#38000
0+
0*
b111 7
0-
1,
#38125
14
05
b1 2
1+
#38250
0+
#38375
b10 2
1+
#38500
0+
#38625
b11 2
1+
#38750
0+
#38875
b100 2
1+
#39000
b100 #
b100 6
0!
00
1"
11
0+
1*
#39125
1'
0&
b101 2
1+
#39250
0+
#39375
b110 2
1+
#39500
0+
#39625
b111 2
1+
#39750
0+
#39875
b0 2
1+
#40000
0+
0*
b1000 7
1-
0,
#40125
04
15
b1 2
1+
#40250
0+
#40375
b10 2
1+
#40500
0+
#40625
b11 2
1+
#40750
0+
#40875
b100 2
1+
#41000
1!
10
0"
01
b101 #
b101 6
0+
1*
#41125
0'
1&
b101 2
1+
#41250
0+
#41375
b110 2
1+
#41500
0+
#41625
b111 2
1+
#41750
0+
#41875
b0 2
1+
#42000
0+
0*
b1001 7
0-
1,
#42125
14
05
b1 2
1+
#42250
0+
#42375
b10 2
1+
#42500
0+
#42625
b11 2
1+
#42750
0+
#42875
b100 2
1+
#43000
b110 #
b110 6
0!
00
1"
11
0+
1*
#43125
1'
0&
b101 2
1+
#43250
0+
#43375
b110 2
1+
#43500
0+
#43625
b111 2
1+
#43750
0+
#43875
b0 2
1+
#44000
0+
0*
b1010 7
1-
0,
#44125
04
15
b1 2
1+
#44250
0+
#44375
b10 2
1+
#44500
0+
#44625
b11 2
1+
#44750
0+
#44875
b100 2
1+
#45000
1!
10
0"
01
b111 #
b111 6
0+
1*
#45125
0'
1&
b101 2
1+
#45250
0+
#45375
b110 2
1+
#45500
0+
#45625
b111 2
1+
#45750
0+
#45875
b0 2
1+
#46000
0+
0*
b1011 7
0-
1,
#46125
14
05
b1 2
1+
#46250
0+
#46375
b10 2
1+
#46500
0+
#46625
b11 2
1+
#46750
0+
#46875
b100 2
1+
#47000
b1000 #
b1000 6
0!
00
1"
11
0+
1*
#47125
1'
0&
b101 2
1+
#47250
0+
#47375
b110 2
1+
#47500
0+
#47625
b111 2
1+
#47750
0+
#47875
b0 2
1+
#48000
0+
0*
b1100 7
1-
0,
#48125
04
15
b1 2
1+
#48250
0+
#48375
b10 2
1+
#48500
0+
#48625
b11 2
1+
#48750
0+
#48875
b100 2
1+
#49000
1!
10
0"
01
b1001 #
b1001 6
0+
1*
#49125
0'
1&
b101 2
1+
#49250
0+
#49375
b110 2
1+
#49500
0+
#49625
b111 2
1+
#49750
0+
#49875
b0 2
1+
#50000
0+
0*
b1101 7
0-
1,
#50125
14
05
b1 2
1+
#50250
0+
#50375
b10 2
1+
#50500
0+
#50625
b11 2
1+
#50750
0+
#50875
b100 2
1+
#51000
b1010 #
b1010 6
0!
00
1"
11
0+
1*
#51125
1'
0&
b101 2
1+
#51250
0+
#51375
b110 2
1+
#51500
0+
#51625
b111 2
1+
#51750
0+
#51875
b0 2
1+
#52000
0+
0*
b1110 7
1-
0,
#52125
04
15
b1 2
1+
#52250
0+
#52375
b10 2
1+
#52500
0+
#52625
b11 2
1+
#52750
0+
#52875
b100 2
1+
#53000
1!
10
0"
01
b1011 #
b1011 6
0+
1*
#53125
0'
1&
b101 2
1+
#53250
0+
#53375
b110 2
1+
#53500
0+
#53625
b111 2
1+
#53750
0+
#53875
b0 2
1+
#54000
0+
0*
b1111 7
0-
1,
#54125
14
05
b1 2
1+
#54250
0+
#54375
b10 2
1+
#54500
0+
#54625
b11 2
1+
#54750
0+
#54875
b100 2
1+
#55000
b1100 #
b1100 6
0!
00
1"
11
0+
1*
#55125
1'
0&
b101 2
1+
#55250
0+
#55375
b110 2
1+
#55500
0+
#55625
b111 2
1+
#55750
0+
#55875
b0 2
1+
#56000
0+
0*
b10000 7
1-
0,
#56125
04
15
b1 2
1+
#56250
0+
#56375
b10 2
1+
#56500
0+
#56625
b11 2
1+
#56750
0+
#56875
b100 2
1+
#57000
1!
10
0"
01
b1101 #
b1101 6
0+
1*
#57125
0'
1&
b101 2
1+
#57250
0+
#57375
b110 2
1+
#57500
0+
#57625
b111 2
1+
#57750
0+
#57875
b0 2
1+
#58000
0+
0*
b10001 7
0-
1,
#58125
14
05
b1 2
1+
#58250
0+
#58375
b10 2
1+
#58500
0+
#58625
b11 2
1+
#58750
0+
#58875
b100 2
1+
#59000
b1110 #
b1110 6
0!
00
1"
11
0+
1*
#59125
1'
0&
b101 2
1+
#59250
0+
#59375
b110 2
1+
#59500
0+
#59625
b111 2
1+
#59750
0+
#59875
b0 2
1+
#60000
0+
0*
b10010 7
1-
0,
#60125
04
15
b1 2
1+
#60250
0+
#60375
b10 2
1+
#60500
0+
#60625
b11 2
1+
#60750
0+
#60875
b100 2
1+
#61000
1!
10
0"
01
b1111 #
b1111 6
0+
1*
#61125
0'
1&
b101 2
1+
#61250
0+
#61375
b110 2
1+
#61500
0+
#61625
b111 2
1+
#61750
0+
#61875
b0 2
1+
#62000
0+
0*
b10011 7
0-
1,
#62125
14
05
b1 2
1+
#62250
0+
#62375
b10 2
1+
#62500
0+
#62625
b11 2
1+
#62750
0+
#62875
b100 2
1+
#63000
b10000 #
b10000 6
0!
00
1"
11
0+
1*
#63125
1'
0&
b101 2
1+
#63250
0+
#63375
b110 2
1+
#63500
0+
#63625
b111 2
1+
#63750
0+
#63875
b0 2
1+
#64000
0+
0*
b10100 7
1-
0,
#64125
04
15
b1 2
1+
#64250
0+
#64375
b10 2
1+
#64500
0+
#64625
b11 2
1+
#64750
0+
#64875
b100 2
1+
#65000
1!
10
0"
01
b10001 #
b10001 6
0+
1*
#65125
0'
1&
b101 2
1+
#65250
0+
#65375
b110 2
1+
#65500
0+
#65625
b111 2
1+
#65750
0+
#65875
b0 2
1+
#66000
0+
0*
b10101 7
0-
1,
#66125
14
05
b1 2
1+
#66250
0+
#66375
b10 2
1+
#66500
0+
#66625
b11 2
1+
#66750
0+
#66875
b100 2
1+
#67000
b10010 #
b10010 6
0!
00
1"
11
0+
1*
#67125
1'
0&
b101 2
1+
#67250
0+
#67375
b110 2
1+
#67500
0+
#67625
b111 2
1+
#67750
0+
#67875
b0 2
1+
#68000
0+
0*
b10110 7
1-
0,
#68125
04
15
b1 2
1+
#68250
0+
#68375
b10 2
1+
#68500
0+
#68625
b11 2
1+
#68750
0+
#68875
b100 2
1+
#69000
1!
10
0"
01
b10011 #
b10011 6
0+
1*
#69125
0'
1&
b101 2
1+
#69250
0+
#69375
b110 2
1+
#69500
0+
#69625
b111 2
1+
#69750
0+
#69875
b0 2
1+
#70000
0+
0*
b10111 7
0-
1,
#70125
14
05
b1 2
1+
#70250
0+
#70375
b10 2
1+
#70500
0+
#70625
b11 2
1+
#70750
0+
#70875
b100 2
1+
#71000
b10100 #
b10100 6
0!
00
1"
11
0+
1*
#71125
1'
0&
b101 2
1+
#71250
0+
#71375
b110 2
1+
#71500
0+
#71625
b111 2
1+
#71750
0+
#71875
b0 2
1+
#72000
0+
0*
b11000 7
1-
0,
#72125
04
15
b1 2
1+
#72250
0+
#72375
b10 2
1+
#72500
0+
#72625
b11 2
1+
#72750
0+
#72875
b100 2
1+
#73000
1!
10
0"
01
b10101 #
b10101 6
0+
1*
#73125
0'
1&
b101 2
1+
#73250
0+
#73375
b110 2
1+
#73500
0+
#73625
b111 2
1+
#73750
0+
#73875
b0 2
1+
#74000
0+
0*
b11001 7
0-
1,
#74125
14
05
b1 2
1+
#74250
0+
#74375
b10 2
1+
#74500
0+
#74625
b11 2
1+
#74750
0+
#74875
b100 2
1+
#75000
b10110 #
b10110 6
0!
00
1"
11
0+
1*
#75125
1'
0&
b101 2
1+
#75250
0+
#75375
b110 2
1+
#75500
0+
#75625
b111 2
1+
#75750
0+
#75875
b0 2
1+
#76000
0+
0*
b11010 7
1-
0,
#76125
04
15
b1 2
1+
#76250
0+
#76375
b10 2
1+
#76500
0+
#76625
b11 2
1+
#76750
0+
#76875
b100 2
1+
#77000
1!
10
0"
01
b10111 #
b10111 6
0+
1*
#77125
0'
1&
b101 2
1+
#77250
0+
#77375
b110 2
1+
#77500
0+
#77625
b111 2
1+
#77750
0+
#77875
b0 2
1+
#78000
0+
0*
b11011 7
0-
1,
#78125
14
05
b1 2
1+
#78250
0+
#78375
b10 2
1+
#78500
0+
#78625
b11 2
1+
#78750
0+
#78875
b100 2
1+
#79000
b11000 #
b11000 6
0!
00
1"
11
0+
1*
#79125
1'
0&
b101 2
1+
#79250
0+
#79375
b110 2
1+
#79500
0+
#79625
b111 2
1+
#79750
0+
#79875
b0 2
1+
#80000
0+
0*
b11100 7
1-
0,
#80125
04
15
b1 2
1+
#80250
0+
#80375
b10 2
1+
#80500
0+
#80625
b11 2
1+
#80750
0+
#80875
b100 2
1+
#81000
1!
10
0"
01
b11001 #
b11001 6
0+
1*
#81125
0'
1&
b101 2
1+
#81250
0+
#81375
b110 2
1+
#81500
0+
#81625
b111 2
1+
#81750
0+
#81875
b0 2
1+
#82000
0+
0*
b11101 7
0-
1,
#82125
14
05
b1 2
1+
#82250
0+
#82375
b10 2
1+
#82500
0+
#82625
b11 2
1+
#82750
0+
#82875
b100 2
1+
#83000
b11010 #
b11010 6
0!
00
1"
11
0+
1*
#83125
1'
0&
b101 2
1+
#83250
0+
#83375
b110 2
1+
#83500
0+
#83625
b111 2
1+
#83750
0+
#83875
b0 2
1+
#84000
0+
0*
b11110 7
1-
0,
#84125
04
15
b1 2
1+
#84250
0+
#84375
b10 2
1+
#84500
0+
#84625
b11 2
1+
#84750
0+
#84875
b100 2
1+
#85000
1!
10
0"
01
b11011 #
b11011 6
0+
1*
#85125
0'
1&
b101 2
1+
#85250
0+
#85375
b110 2
1+
#85500
0+
#85625
b111 2
1+
#85750
0+
#85875
b0 2
1+
#86000
0+
0*
b11111 7
0-
1,
#86125
14
05
b1 2
1+
#86250
0+
#86375
b10 2
1+
#86500
0+
#86625
b11 2
1+
#86750
0+
#86875
b100 2
1+
#87000
b11100 #
b11100 6
0!
00
1"
11
0+
1*
#87125
1'
0&
b101 2
1+
#87250
0+
#87375
b110 2
1+
#87500
0+
#87625
b111 2
1+
#87750
0+
#87875
b0 2
1+
#88000
0+
0*
#88125
b1 2
1+
#88250
0+
#88375
b10 2
1+
#88500
0+
#88625
b11 2
1+
#88750
0+
#88875
b100 2
1+
#89000
1!
10
0"
01
b11101 #
b11101 6
0+
1*
#89125
b101 2
1+
#89250
0+
#89375
b110 2
1+
#89500
0+
#89625
b111 2
1+
#89750
0+
#89875
b0 2
1+
#90000
0+
0*
#90125
b1 2
1+
#90250
0+
#90375
b10 2
1+
#90500
0+
#90625
b11 2
1+
#90750
0+
#90875
b100 2
1+
#91000
b11110 #
b11110 6
1(
0+
1*
#91125
b101 2
1+
#91250
0+
#91375
b110 2
1+
#91500
0+
#91625
b111 2
1+
#91750
0+
#91875
b0 2
1+
#92000
0+
0*
#92125
b1 2
1+
#92250
0+
#92375
b10 2
1+
#92500
0+
#92625
b11 2
1+
#92750
0+
#92875
b100 2
1+
#93000
b1 /
1)
b11111 #
b11111 6
0+
1*
#93125
b101 2
1+
#93250
0+
#93375
b110 2
1+
#93500
0+
#93625
b111 2
1+
#93750
0+
#93875
b0 2
1+
#94000
0+
0*
#94125
b1 2
1+
#94250
0+
#94375
b10 2
1+
#94500
0+
#94625
b11 2
1+
#94750
0+
#94875
b100 2
1+
#95000
b0 #
b0 6
1%
b10 /
0+
1*
#95125
b101 2
1+
#95250
0+
#95375
b110 2
1+
#95500
0+
#95625
b111 2
1+
#95750
0+
#95875
b0 2
1+
#96000
0+
0*
#96125
b1 2
1+
#96250
0+
#96375
b10 2
1+
#96500
0+
#96625
b11 2
1+
#96750
0+
#96875
b100 2
1+
#97000
b11 /
0%
0+
1*
#97125
b101 2
1+
#97250
0+
#97375
b110 2
1+
#97500
0+
#97625
b111 2
1+
#97750
0+
#97875
b0 2
1+
