USB_PHY/sync_detector.v
module sync_detector(
	input wire [1:0]sd_sbus_i,
	input wire sd_clk_i,
	input wire sd_reset,
	output reg sd_sync_o
);
	
	localparam IDLE=2'b00;
	localparam ACQUIRING=2'b01;

	reg [1:0]STATE;
	reg [3:0]sd_count;
	reg [1:0]sd_prev;

	always@(posedge sd_clk_i or posedge sd_reset)begin
		if(sd_reset)begin
			sd_sync_o<=1'b0;
			sd_prev<=2'b01;
			sd_count<={4{1'b0}};
			STATE<=IDLE;
		end
		else begin
			sd_prev<=sd_sbus_i;
			case(STATE)
				IDLE : begin
					sd_sync_o<=1'b0;
					sd_count<={4{1'b0}};
					if((sd_sbus_i==2'b10) && (sd_prev==2'b01))begin
						STATE<=ACQUIRING;
						sd_count<=sd_count+1;
					end
				end
				ACQUIRING : begin
					if(sd_count<4'd14)begin
						if((sd_prev==2'b01 && sd_sbus_i==2'b10) || (sd_prev==2'b10 && sd_sbus_i==2'b01))begin
							sd_count<=sd_count+1;
						end
						else begin
							STATE<=IDLE;
							sd_count<={4{1'b0}};
						end
					end
					else if(({sd_sbus_i,sd_prev}==4'b1010)) begin
						sd_count<=4'b0;
						sd_sync_o<=1'b1;
						STATE<=IDLE;
					end
				end
				default :begin
				    STATE<=IDLE;
				    sd_sync_o<=1'b0;
					sd_count<={4{1'b0}};
				end
			endcase
		end
	end
endmodule

TB/PHY/sync_detector_tb.v
`timescale 1 ns / 1 ns;
module sync_detector_tb;
    reg [1:0]sd_sbus_i;
	reg sd_clk_i;
	reg sd_reset;
	 reg [8*9:1]s;
    wire sd_sync_o;
    
    sync_detector sd_1(
        .sd_sbus_i(sd_sbus_i),
	    .sd_clk_i(sd_clk_i),
	    .sd_reset(sd_reset),
	    .sd_sync_o(sd_sync_o)
    );

    initial begin
	    $dumpfile("TB/sync_detector.vcd");
	    $dumpvars(0,sync_detector_tb);
	    $display(" Time | clk | reset |  state  |count| prev | Dp,Dm | sync |");
    end                               

    always@(posedge sd_clk_i) begin
        $display(" %3t  |  %b  |   %b   |%s|%d|  %2b  |   %2b  |   %b  |",$time,sd_clk_i,sd_reset,s,sd_1.sd_count,sd_1.sd_prev,sd_sbus_i,sd_sync_o);
         case (sd_1.STATE)
            2'b00: s = "IDLE";
            2'b01: s = "ACQUIRING";
            default: s = "IDLE";
        endcase
    end
    
    initial begin
        sd_sbus_i=2'b01;
        sd_clk_i=1;
        sd_reset=1;
    end

    always begin
        #1 sd_clk_i=~sd_clk_i;
    end

    initial begin
        #2 sd_reset=1'b0;
        #2 sd_sbus_i=2'b01;
        #2 sd_sbus_i=2'b01;
        #2 sd_sbus_i=2'b01;
        #2 sd_sbus_i=2'b01;
        for(integer i = 0;i<7;i++)begin
            #2 sd_sbus_i=2'b10;
            #2 sd_sbus_i=2'b01;
        end
        #2 sd_sbus_i=2'b10;
        #2 sd_sbus_i=2'b10;
        #2 sd_sbus_i=2'b01;
        #13 $finish;
    end

endmodule

TB/PHY/DUMP/sync_detector.vcd
$date
	Wed Jun  3 19:40:34 2026
$end
$version
	Icarus Verilog
$end
$timescale
	1ns
$end
$scope module sync_detector_tb $end
$var wire 1 ! sd_sync_o $end
$var reg 72 " s [72:1] $end
$var reg 1 # sd_clk_i $end
$var reg 1 $ sd_reset $end
$var reg 2 % sd_sbus_i [1:0] $end
$scope module sd_1 $end
$var wire 1 # sd_clk_i $end
$var wire 1 $ sd_reset $end
$var wire 2 & sd_sbus_i [1:0] $end
$var parameter 2 ' ACQUIRING $end
$var parameter 2 ( IDLE $end
$var reg 2 ) STATE [1:0] $end
$var reg 4 * sd_count [3:0] $end
$var reg 2 + sd_prev [1:0] $end
$var reg 1 ! sd_sync_o $end
$upscope $end
$scope begin $ivl_for_loop0 $end
$var integer 32 , i [31:0] $end
$upscope $end
$upscope $end
$enddefinitions $end
$comment Show the parameter values. $end
$dumpall
b0 (
b1 '
$end
#0
$dumpvars
bx ,
b1 +
b0 *
b0 )
b1 &
b1 %
1$
1#
b1001001010001000100110001000101 "
0!
$end
#1
0#
#2
1#
0$
#3
0#
#4
1#
#5
0#
#6
1#
#7
0#
#8
1#
#9
0#
#10
1#
b0 ,
#11
0#
#12
b1 )
b10 +
1#
b10 %
b10 &
#13
0#
#14
b1 *
b1 +
b10000010100001101010001010101010100100101010010010010010100111001000111 "
1#
b1 ,
b1 %
b1 &
#15
0#
#16
b10 *
b10 +
1#
b10 %
b10 &
#17
0#
#18
b11 *
b1 +
1#
b10 ,
b1 %
b1 &
#19
0#
#20
b100 *
b10 +
1#
b10 %
b10 &
#21
0#
#22
b101 *
b1 +
1#
b11 ,
b1 %
b1 &
#23
0#
#24
b110 *
b10 +
1#
b10 %
b10 &
#25
0#
#26
b111 *
b1 +
1#
b100 ,
b1 %
b1 &
#27
0#
#28
b1000 *
b10 +
1#
b10 %
b10 &
#29
0#
#30
b1001 *
b1 +
1#
b101 ,
b1 %
b1 &
#31
0#
#32
b1010 *
b10 +
1#
b10 %
b10 &
#33
0#
#34
b1011 *
b1 +
1#
b110 ,
b1 %
b1 &
#35
0#
#36
b1100 *
b10 +
1#
b10 %
b10 &
#37
0#
#38
b1101 *
b1 +
1#
b111 ,
b1 %
b1 &
#39
0#
#40
b1110 *
b10 +
1#
b10 %
b10 &
#41
0#
#42
b0 )
b0 *
1!
1#
#43
0#
#44
0!
b1 +
b1001001010001000100110001000101 "
1#
b1 %
b1 &
