SIE/crc16_checker.v
module crc16_checker(
    input wire cc16_clk_i,
    input wire cc16_reset,
    input wire cc16_sbit_i,
    input wire cc16_sync_i,
    output reg [15:0]cc16_reg
);
    
    reg cc16_on;
    
    always@(posedge cc16_clk_i or posedge cc16_reset)begin
        if(cc16_reset)begin
            cc16_on<=1'b0;
            cc16_reg<=16'b0;
        end
        else begin
            if(cc16_sync_i | cc16_on)begin
                cc16_on<=1'b1;
                cc16_reg[15]<=cc16_reg[14];
                cc16_reg[14]<=cc16_reg[13]^cc16_reg[15];
                cc16_reg[13]<=cc16_reg[12];
                cc16_reg[12]<=cc16_reg[11];
                cc16_reg[11]<=cc16_reg[10];
                cc16_reg[10]<=cc16_reg[9];
                cc16_reg[9]<=cc16_reg[8];
                cc16_reg[8]<=cc16_reg[7];
                cc16_reg[7]<=cc16_reg[6];
                cc16_reg[6]<=cc16_reg[5];
                cc16_reg[5]<=cc16_reg[4];
                cc16_reg[4]<=cc16_reg[3];
                cc16_reg[3]<=cc16_reg[2];
                cc16_reg[2]<=cc16_reg[1];
                cc16_reg[1]<=cc16_reg[0]^cc16_reg[15];
                cc16_reg[0]<=cc16_reg[15]^cc16_sbit_i;
            end
                            
                
        end
    end
endmodule

TB/SIE/crc16_checker_tb.v
`timescale 1 ns / 1 ns;
module crc16_checker_tb;
    
    reg cc16_clk_i;
    reg cc16_reset;
    reg cc16_sbit_i;
    reg cc16_sync_i;
    wire [15:0]cc16_reg;

    crc16_checker cc16_1(
        .cc16_clk_i(cc16_clk_i),
        .cc16_reset(cc16_reset),
        .cc16_sbit_i(cc16_sbit_i),
        .cc16_sync_i(cc16_sync_i),
        .cc16_reg(cc16_reg)
    );

    initial begin
        $dumpfile("TB/SIE/DUMP/crc16_checker.vcd");
        $dumpvars(0,crc16_checker_tb);
        $display("|Time|Clk|Reset|Sync|Reg_on|Bit|CRC register|");
    end

    always@(posedge cc16_clk_i)begin
        $display("|%4t| %b |  %b  | %b  |  %b   | %b |   %16b    |",$time,cc16_clk_i,cc16_reset,cc16_sync_i,cc16_1.cc16_on,cc16_sbit_i,cc16_reg);
    end

    initial begin
        cc16_clk_i=1'b1;
        cc16_reset=1'b1;
        cc16_sbit_i=1'b0;
        cc16_sync_i=1'b0;
    end

    always begin
        #1 cc16_clk_i =~cc16_clk_i;
    end

    initial begin
        #2 cc16_reset=1'b0;
        #4 cc16_sync_i=1'b1;  
        #2 cc16_sync_i=1'b0; 
            //PID be DATA0 - 1100_0011 and crc16 - 1101_0111,1010_0111.
        
    //Order of appearance for DATA0 - 1100_0011
    //Order of appearance for crc16 - 1110_0101,1110_1011.
        
            // payload byte1 is 0101_1010, byte0 is 1100_0011.
    
    //Order of appearance for payload is 1100_0011,0101_1010
    
    //therefore, the bits 1100_0011,1100_0011,0101_1010,1110_0101,1110_1011 in order of appearance 
        #2 cc16_sbit_i=1'b1; 
        #2 cc16_sbit_i=1'b1;
        #2 cc16_sbit_i=1'b0;
        #2 cc16_sbit_i=1'b0;
        
        #2 cc16_sbit_i=1'b0;
        #2 cc16_sbit_i=1'b0;
        #2 cc16_sbit_i=1'b1;
        #2 cc16_sbit_i=1'b1;
        
        #2 cc16_sbit_i=1'b1;
        #2 cc16_sbit_i=1'b1;
        #2 cc16_sbit_i=1'b0;
        #2 cc16_sbit_i=1'b0;
        
        #2 cc16_sbit_i=1'b0;
        #2 cc16_sbit_i=1'b0;
        #2 cc16_sbit_i=1'b1;
        #2 cc16_sbit_i=1'b1;

        #2 cc16_sbit_i=1'b0;
        #2 cc16_sbit_i=1'b1;
        #2 cc16_sbit_i=1'b0;
        #2 cc16_sbit_i=1'b1;

        #2 cc16_sbit_i=1'b1;
        #2 cc16_sbit_i=1'b0;
        #2 cc16_sbit_i=1'b1;
        #2 cc16_sbit_i=1'b0;

        #2 cc16_sbit_i=1'b1;
        #2 cc16_sbit_i=1'b1;
        #2 cc16_sbit_i=1'b1;
        #2 cc16_sbit_i=1'b0;

        #2 cc16_sbit_i=1'b0;
        #2 cc16_sbit_i=1'b1;
        #2 cc16_sbit_i=1'b0;
        #2 cc16_sbit_i=1'b1;

        #2 cc16_sbit_i=1'b1;
        #2 cc16_sbit_i=1'b1;
        #2 cc16_sbit_i=1'b1;
        #2 cc16_sbit_i=1'b0;

        #2 cc16_sbit_i=1'b1;
        #2 cc16_sbit_i=1'b0;
        #2 cc16_sbit_i=1'b1;
        #2 cc16_sbit_i=1'b1;
        #2 cc16_reset=1'b1;
           cc16_sbit_i=1'b0;
        #2 cc16_reset=1'b0;

        #3 $finish;
    end 

endmodule

TB/SIE/DUMP/crc16_checker.vcd
$date
	Sun Jun 21 18:50:42 2026
$end
$version
	Icarus Verilog
$end
$timescale
	1ns
$end
$scope module crc16_checker_tb $end
$var wire 16 ! cc16_reg [15:0] $end
$var reg 1 " cc16_clk_i $end
$var reg 1 # cc16_reset $end
$var reg 1 $ cc16_sbit_i $end
$var reg 1 % cc16_sync_i $end
$scope module cc16_1 $end
$var wire 1 " cc16_clk_i $end
$var wire 1 # cc16_reset $end
$var wire 1 $ cc16_sbit_i $end
$var wire 1 % cc16_sync_i $end
$var reg 1 & cc16_on $end
$var reg 16 ' cc16_reg [15:0] $end
$upscope $end
$upscope $end
$enddefinitions $end
$comment Show the parameter values. $end
$dumpall
$end
#0
$dumpvars
b0 '
0&
0%
0$
1#
1"
b0 !
$end
#1
0"
#2
1"
0#
#3
0"
#4
1"
#5
0"
#6
1&
1"
1%
#7
0"
#8
1"
0%
#9
0"
#10
b1 !
b1 '
1"
1$
#11
0"
#12
b11 !
b11 '
1"
#13
0"
#14
b110 !
b110 '
1"
0$
#15
0"
#16
b1100 !
b1100 '
1"
#17
0"
#18
b11000 !
b11000 '
1"
#19
0"
#20
b110000 !
b110000 '
1"
#21
0"
#22
b1100001 !
b1100001 '
1"
1$
#23
0"
#24
b11000011 !
b11000011 '
1"
#25
0"
#26
b110000111 !
b110000111 '
1"
#27
0"
#28
b1100001111 !
b1100001111 '
1"
#29
0"
#30
b11000011110 !
b11000011110 '
1"
0$
#31
0"
#32
b110000111100 !
b110000111100 '
1"
#33
0"
#34
b1100001111000 !
b1100001111000 '
1"
#35
0"
#36
b11000011110000 !
b11000011110000 '
1"
#37
0"
#38
b110000111100001 !
b110000111100001 '
1"
1$
#39
0"
#40
b1100001111000011 !
b1100001111000011 '
1"
#41
0"
#42
b1100011110000101 !
b1100011110000101 '
1"
0$
#43
0"
#44
b1100111100001000 !
b1100111100001000 '
1"
1$
#45
0"
#46
b1101111000010011 !
b1101111000010011 '
1"
0$
#47
0"
#48
b1111110000100100 !
b1111110000100100 '
1"
1$
#49
0"
#50
b1011100001001010 !
b1011100001001010 '
1"
#51
0"
#52
b11000010010111 !
b11000010010111 '
1"
0$
#53
0"
#54
b110000100101111 !
b110000100101111 '
1"
1$
#55
0"
#56
b1100001001011110 !
b1100001001011110 '
1"
0$
#57
0"
#58
b1100010010111110 !
b1100010010111110 '
1"
1$
#59
0"
#60
b1100100101111110 !
b1100100101111110 '
1"
#61
0"
#62
b1101001011111110 !
b1101001011111110 '
1"
#63
0"
#64
b1110010111111111 !
b1110010111111111 '
1"
0$
#65
0"
#66
b1000101111111101 !
b1000101111111101 '
1"
#67
0"
#68
b101011111111000 !
b101011111111000 '
1"
1$
#69
0"
#70
b1010111111110000 !
b1010111111110000 '
1"
0$
#71
0"
#72
b1111111100010 !
b1111111100010 '
1"
1$
#73
0"
#74
b11111111000101 !
b11111111000101 '
1"
#75
0"
#76
b111111110001011 !
b111111110001011 '
1"
#77
0"
#78
b1111111100010111 !
b1111111100010111 '
1"
#79
0"
#80
b1011111000101101 !
b1011111000101101 '
1"
0$
#81
0"
#82
b11110001011000 !
b11110001011000 '
1"
1$
#83
0"
#84
b111100010110000 !
b111100010110000 '
1"
0$
#85
0"
#86
b1111000101100001 !
b1111000101100001 '
1"
1$
#87
0"
#88
b1010001011000000 !
b1010001011000000 '
1"
#89
0"
#90
b0 !
b0 '
0&
1"
0$
1#
#91
0"
#92
1"
0#
