SIE/crc5_checker.v
module crc5_checker(
    input wire cc_clk_i,
    input wire cc_reset,
    input wire cc_sbit_i,
    input wire cc_sync_i,
    output reg [4:0]cc_reg
);
    
    reg cc_on;
    
    always@(posedge cc_clk_i or posedge cc_reset)begin
        if(cc_reset)begin
            cc_on<=1'b0;
            cc_reg<=5'b0;
        end
        else begin
            if(cc_sync_i | cc_on)begin
                cc_on<=1'b1;
                cc_reg[4]<=cc_reg[3];
                cc_reg[3]<=cc_reg[4]^cc_reg[2];           
                cc_reg[2]<=cc_reg[1];
                cc_reg[1]<=cc_reg[0];
                cc_reg[0]<=cc_reg[4]^cc_sbit_i;
            end
                            
                
        end
    end
endmodule

TB/SIE/crc5_checker_tb.v
`timescale 1 ns / 1 ns;
module crc5_checker_tb;
    
    reg cc_clk_i;
    reg cc_reset;
    reg cc_sbit_i;
    reg cc_sync_i;
    wire [4:0]cc_reg;

    crc5_checker cc_1(
        .cc_clk_i(cc_clk_i),
        .cc_reset(cc_reset),
        .cc_sbit_i(cc_sbit_i),
        .cc_sync_i(cc_sync_i),
        .cc_reg(cc_reg)
    );

    initial begin
        $dumpfile("TB/SIE/DUMP/crc5_checker.vcd");
        $dumpvars(0,crc5_checker_tb);
        $display("|Time|Clk|Reset|Sync|Reg_on|Bit|CRC register|");
    end

    always@(posedge cc_clk_i)begin
        $display("|%4t| %b |  %b  | %b  |  %b   | %b |   %5b    |",$time,cc_clk_i,cc_reset,cc_sync_i,cc_1.cc_on,cc_sbit_i,cc_reg);
    end

    initial begin
        cc_clk_i=1'b1;
        cc_reset=1'b1;
        cc_sbit_i=1'b0;
        cc_sync_i=1'b0;
    end

    always begin
        #1 cc_clk_i =~cc_clk_i;
    end

    initial begin
        #2 cc_reset=1'b0;
        #4 cc_sync_i=1'b1; // message is 0000_1111_0000_0001 but USB transmits lsb first.
        #2 cc_sync_i=1'b0;
        
        #2 cc_sbit_i=1'b1; //therefore, the bits 1000_0000_1111_0000 in order of appearance
        #2 cc_sbit_i=1'b0;
        #2 cc_sbit_i=1'b0;
        #2 cc_sbit_i=1'b0;
        
        #2 cc_sbit_i=1'b0;
        #2 cc_sbit_i=1'b0;
        #2 cc_sbit_i=1'b0;
        #2 cc_sbit_i=1'b0;
        
        #2 cc_sbit_i=1'b1;
        #2 cc_sbit_i=1'b1;
        #2 cc_sbit_i=1'b1;
        #2 cc_sbit_i=1'b1;
        
        #2 cc_sbit_i=1'b0;
        #2 cc_sbit_i=1'b0;
        #2 cc_sbit_i=1'b0;
        #2 cc_sbit_i=1'b0;
        #2 cc_reset=1'b1;
        #2 cc_sbit_i=1'b1;
        #2 cc_sbit_i=1'b0;
        #3 $finish;
    end 

endmodule

TB/SIE/DUMP/crc5_checker.vcd
$date
	Thu Jun 18 19:07:19 2026
$end
$version
	Icarus Verilog
$end
$timescale
	1ns
$end
$scope module crc5_checker_tb $end
$var wire 5 ! cc_reg [4:0] $end
$var reg 1 " cc_clk_i $end
$var reg 1 # cc_reset $end
$var reg 1 $ cc_sbit_i $end
$var reg 1 % cc_sync_i $end
$scope module cc_1 $end
$var wire 1 " cc_clk_i $end
$var wire 1 # cc_reset $end
$var wire 1 $ cc_sbit_i $end
$var wire 1 % cc_sync_i $end
$var reg 1 & cc_on $end
$var reg 5 ' cc_reg [4:0] $end
$upscope $end
$upscope $end
$enddefinitions $end
$comment Show the parameter values. $end
$dumpall
$end
#0
$dumpvars
b0 '
0&
0%
0$
1#
1"
b0 !
$end
#1
0"
#2
1"
0#
#3
0"
#4
1"
#5
0"
#6
1&
1"
1%
#7
0"
#8
1"
0%
#9
0"
#10
b1 !
b1 '
1"
1$
#11
0"
#12
b10 !
b10 '
1"
0$
#13
0"
#14
b100 !
b100 '
1"
#15
0"
#16
b1000 !
b1000 '
1"
#17
0"
#18
b10000 !
b10000 '
1"
#19
0"
#20
b1001 !
b1001 '
1"
#21
0"
#22
b10010 !
b10010 '
1"
#23
0"
#24
b1101 !
b1101 '
1"
#25
0"
#26
b11011 !
b11011 '
1"
1$
#27
0"
#28
b11110 !
b11110 '
1"
#29
0"
#30
b10100 !
b10100 '
1"
#31
0"
#32
b0 !
b0 '
1"
#33
0"
#34
1"
0$
#35
0"
#36
1"
#37
0"
#38
1"
#39
0"
#40
1"
#41
0"
#42
0&
1"
1#
#43
0"
#44
1"
1$
#45
0"
#46
1"
0$
