HEADERS/PID.vh
`ifndef PID_VH
`define PID_VH

//PID TYPEs
`define PID_SPECIAL 2'b00
`define PID_TOKEN 2'b01
`define PID_HANDSHAKE 2'b10
`define PID_DATA 2'b11

//TOKEN PIDs
`define PID_OUT 8'b1110_0001
`define PID_SOF 8'b1010_0101
`define PID_IN 8'b0110_1001
`define PID_SETUP 8'b0010_1101

//DATA PIDs
`define PID_DATA0 8'b1100_0011
`define PID_DATA2 8'b1000_0111
`define PID_DATA1 8'b0100_1011
`define PID_MDATA 8'b0000_1111

//HANDSHAKE PIDs
`define PID_ACK 8'b1101_0010
`define PID_NYET 8'b1001_0110
`define PID_NAK 8'b0101_1010
`define PID_STALL 8'b0001_1110

//SPECIAL
`define PID_PING 8'b1011_0100
`define PID_SPLIT 8'b0111_1000
`define PID_PRE 8'b0011_1100

`define PID_INVALID 8'b0000_0000

`endif

SIE/handshake_decoder.v
`include "PID.vh" 
module handshake_decoder(
    input wire hd_clk_i,
    input wire hd_reset,

    input wire [3:0]hd_pid_i,
    input wire hd_pid_valid_i,

    output reg hd_ack_o,
    output reg hd_nyet_o,
    output reg hd_nak_o,
    output reg hd_stall_o
);

    always@(posedge hd_clk_i or posedge hd_reset)begin
        if(hd_reset)begin
            hd_ack_o<=1'b0;
            hd_nyet_o<=1'b0;
            hd_nak_o<=1'b0;
            hd_stall_o<=1'b0;
        end
        else begin
            hd_ack_o<=1'b0;
            hd_nyet_o<=1'b0;
            hd_nak_o<=1'b0;
            hd_stall_o<=1'b0;
            if(hd_pid_valid_i)begin
                case(hd_pid_i)
                    `PIDN_ACK : hd_ack_o<=1'b1;
                    `PIDN_NYET : hd_nyet_o<=1'b1;
                    `PIDN_NAK : hd_nak_o<=1'b1;
                    `PIDN_STALL : hd_stall_o<=1'b1;
                endcase
            end
        end
    end

endmodule

TB/SIE/handshake_decoder_tb.v
`timescale 1 ns / 1 ns;
module handshake_decoder_tb;
    reg hd_clk_i;
    reg hd_reset;
    reg [3:0]hd_pid_i;
    reg hd_pid_valid_i;
    wire hd_ack_o;
    wire hd_nyet_o;
    wire hd_nak_o;
    wire hd_stall_o;
    handshake_decoder hd_1(
        .hd_clk_i(hd_clk_i),
        .hd_reset(hd_reset),
        .hd_pid_i(hd_pid_i),
        .hd_pid_valid_i(hd_pid_valid_i),
        .hd_ack_o(hd_ack_o),
        .hd_nyet_o(hd_nyet_o),
        .hd_nak_o(hd_nak_o),
        .hd_stall_o(hd_stall_o)
    );
    initial begin
        $dumpfile("TB/SIE/DUMP/handshake_decoder.vcd");
        $dumpvars(0,handshake_decoder_tb);
        $display("|Time|Clk|Reset|PID_in|PID_valid|ACK|NYET|NAK|STALL|");
    end
    always@(posedge hd_clk_i)begin
        $display("|%4t| %b |  %b  | %4b |    %b    | %b | %b  | %b |  %b  |",$time,hd_clk_i,hd_reset,hd_pid_i,hd_pid_valid_i,hd_ack_o,hd_nyet_o,hd_nak_o,hd_stall_o);
    end

    initial begin
        hd_clk_i=1'b1;
        hd_reset=1'b1;
        hd_pid_i=4'b0;
        hd_pid_valid_i=1'b0; 
    end
    always begin
        #1 hd_clk_i=~hd_clk_i;
    end

    initial begin
        #2 hd_reset=1'b0;
        //ACK
        #2 hd_pid_i=4'b0010;
            hd_pid_valid_i=1'b1;
        #2 hd_pid_valid_i=1'b0;
        //NYET
        #4 hd_pid_i=4'b0110;
            hd_pid_valid_i=1'b1;
        #2 hd_pid_valid_i=1'b0;
        //NAK
        #4 hd_pid_i=4'b1010;
            hd_pid_valid_i=1'b1;
        #2 hd_pid_valid_i=1'b0;
        //STALL
        #4 hd_pid_i=4'b1110;
            hd_pid_valid_i=1'b1;
        #2 hd_pid_valid_i=1'b0;
        #5 $finish;
    end
endmodule

TB/SIE/DUMP/handshake_decoder.vcd
$date
	Thu Jul  2 19:44:05 2026
$end
$version
	Icarus Verilog
$end
$timescale
	1ns
$end
$scope module handshake_decoder_tb $end
$var wire 1 ! hd_stall_o $end
$var wire 1 " hd_nyet_o $end
$var wire 1 # hd_nak_o $end
$var wire 1 $ hd_ack_o $end
$var reg 1 % hd_clk_i $end
$var reg 4 & hd_pid_i [3:0] $end
$var reg 1 ' hd_pid_valid_i $end
$var reg 1 ( hd_reset $end
$scope module hd_1 $end
$var wire 1 % hd_clk_i $end
$var wire 4 ) hd_pid_i [3:0] $end
$var wire 1 ' hd_pid_valid_i $end
$var wire 1 ( hd_reset $end
$var reg 1 $ hd_ack_o $end
$var reg 1 # hd_nak_o $end
$var reg 1 " hd_nyet_o $end
$var reg 1 ! hd_stall_o $end
$upscope $end
$upscope $end
$enddefinitions $end
$comment Show the parameter values. $end
$dumpall
$end
#0
$dumpvars
b0 )
1(
0'
b0 &
1%
0$
0#
0"
0!
$end
#1
0%
#2
1%
0(
#3
0%
#4
1$
1%
1'
b10 &
b10 )
#5
0%
#6
0$
1%
0'
#7
0%
#8
1%
#9
0%
#10
1"
1%
1'
b110 &
b110 )
#11
0%
#12
0"
1%
0'
#13
0%
#14
1%
#15
0%
#16
1#
1%
1'
b1010 &
b1010 )
#17
0%
#18
0#
1%
0'
#19
0%
#20
1%
#21
0%
#22
1!
1%
1'
b1110 &
b1110 )
#23
0%
#24
0!
1%
0'
