SIE/rx_fifo.v
module rx_fifo(
     input wire rf_clk_i,
     input wire rf_reset,
     input wire [7:0]rf_byte_i,
     input wire rf_write_i,
     input wire rf_read_i,
     output reg [7:0]rf_byte_o,
     output reg rf_empty_o,
     output reg rf_full_o,
     output reg rf_underflow_o,
     output reg rf_overflow_o,
);
    reg [7:0] fifo_mem[63:0];
    reg [5:0]rd_ptr;
    reg [5:0]wr_ptr;
    reg [6:0]byte_count;

    always@(posedge rf_clk_i or posedge rf_reset)begin
        if(rf_reset)begin
            rf_empty_o<=1'b1;
            rf_underflow_o<=1'b0;
            rf_full_o<=1'b0;
            rf_overflow_o<=1'b0;
            rd_ptr<=6'b0;
            wr_ptr<=6'b0;
            byte_count<=7'b0;
        end
        else begin
            case({rf_write_i && (byte_count!=7'd64),rf_read_i && (byte_count!=7'd0)})
                2'b10 : begin
                    fifo_mem[wr_ptr]<=rf_byte_i;
                    wr_ptr<=wr_ptr+1;
                    byte_count<=byte_count+1;
                end
                2'b01 : begin
                    rf_byte_o<=fifo_mem[rd_ptr];
                    rd_ptr<=rd_ptr+1;
                    byte_count<=byte_count-1;
                end
                2'b11 : begin
                    fifo_mem[wr_ptr]<=rf_byte_i;
                    wr_ptr<=wr_ptr+1;
                    rf_byte_o<=fifo_mem[rd_ptr];
                    rd_ptr<=rd_ptr+1;
                end
                default : begin
                end
            endcase
            rf_empty_o<=(byte_count==7'b0);
            rf_underflow_o<=((byte_count==7'b0) && rf_read_i);
            rf_full_o<=(byte_count==7'd64);
            rf_overflow_o<=((byte_count==7'd64) && rf_write_i);
        end
    end

endmodule

TB/SIE/rx_fifo_tb.v
module rx_fifo_tb;
    reg rf_clk_i;
    reg rf_reset;
    reg [7:0]rf_byte_i;
    reg rf_write_i;
    reg rf_read_i;
    wire [7:0]rf_byte_o;
    wire rf_empty_o;
    wire rf_full_o;
    wire rf_underflow_o;
    wire rf_overflow_o;
    
    rx_fifo rf_1(
        .rf_clk_i(rf_clk_i),
        .rf_reset(rf_reset),
        .rf_byte_i(rf_byte_i),
        .rf_write_i(rf_write_i),
        .rf_read_i(rf_read_i),
        .rf_byte_o(rf_byte_o),
        .rf_empty_o(rf_empty_o),
        .rf_full_o(rf_full_o),
        .rf_underflow_o(rf_underflow_o),
        .rf_overflow_o(rf_overflow_o)
    );

    initial begin
        $dumpfile("TB/SIE/DUMP/rx_fifo.vcd");
        $dumpvars(0,rx_fifo_tb);
        $display("|Time|Clk|Reset|Write|wr_ptr|Byte__in|byte_count|Read|rd_ptr|Byte_out|Empty|Underflow|Full|Overflow|");
    end

    always@ (posedge rf_clk_i)begin
        $display("|%4t| %b |  %b  |  %b  |  %2d  |%8b|    %2d    | %b  |  %2d  |%8b|  %b  |    %b    | %b  |   %b    |",$time,rf_clk_i,rf_reset,rf_write_i,rf_1.wr_ptr,rf_byte_i,rf_1.byte_count,rf_read_i,rf_1.rd_ptr,rf_byte_o,rf_empty_o,rf_underflow_o,rf_full_o,rf_overflow_o);
    end

    initial begin
        rf_clk_i=1'b1;
        rf_reset=1'b1;
        rf_byte_i=8'b0;
        rf_write_i=1'b0;
        rf_read_i=1'b0; 
    end

    always begin
        #1 rf_clk_i=~rf_clk_i;
    end

    initial begin
        #2 rf_reset=1'b0;
        //write only
        #2 rf_byte_i=8'b1000_0000;
        #2 rf_byte_i=8'b0100_0000;
        #2 rf_byte_i=8'b0010_0000;
        #2 rf_byte_i=8'b0001_0000;
        #2 rf_byte_i=8'b0000_1000;
        #2 rf_byte_i=8'b0000_0100;
        #2 rf_byte_i=8'b0000_0010;
        #2 rf_byte_i=8'b0000_0001;
            rf_write_i=1'b1;
        #2 rf_write_i=1'b0;
        #2 rf_byte_i=8'b1000_0000;
        #2 rf_byte_i=8'b1100_0000;
        #2 rf_byte_i=8'b1110_0000;
        #2 rf_byte_i=8'b1111_0000;
        #2 rf_byte_i=8'b0111_1000;
        #2 rf_byte_i=8'b0011_1100;
        #2 rf_byte_i=8'b0001_1110;
        #2 rf_byte_i=8'b0000_1111;
            rf_write_i=1'b1;
        #2 rf_write_i=1'b0;
        #2 rf_byte_i=8'b1000_0000;
        #2 rf_byte_i=8'b0100_0000;
        #2 rf_byte_i=8'b1010_0000;
        #2 rf_byte_i=8'b0101_0000;
        #2 rf_byte_i=8'b1010_1000;
        #2 rf_byte_i=8'b0101_0100;
        #2 rf_byte_i=8'b1010_1010;
        #2 rf_byte_i=8'b0101_0101;
            rf_write_i=1'b1;
        #2 rf_write_i=1'b0;
        //read only
        #4 rf_read_i=1'b1;
        #6 rf_read_i=1'b0;
        //write and read at a time
        #2 rf_byte_i=8'b1000_0000;
        #2 rf_byte_i=8'b1100_0000;
        #2 rf_byte_i=8'b1110_0000;
        #2 rf_byte_i=8'b1111_0000;
        #2 rf_byte_i=8'b1111_1000;
        #2 rf_byte_i=8'b1111_1100;
        #2 rf_byte_i=8'b1111_1110;
        #2 rf_byte_i=8'b1111_1111;
            rf_write_i=1'b1;
            rf_read_i=1'b1;
        #2 rf_write_i=1'b0;
            rf_read_i=1'b0;
        //underflow
        #2 rf_read_i=1'b1;
        #2 rf_read_i=1'b0;
        //overflow
        for(integer i=0;i<64;i++)begin
            #2 rf_byte_i=8'b0000_1111;
                rf_write_i=1'b1;
        end
        #4 rf_write_i=1'b0;
        #11 $finish;
    end

endmodule

TB/SIE/DUMP/rx_fifo.vcd
$date
	Wed Jul 22 07:58:20 2026
$end
$version
	Icarus Verilog
$end
$timescale
	1ns
$end
$scope module rx_fifo_tb $end
$var wire 1 ! rf_underflow_o $end
$var wire 1 " rf_overflow_o $end
$var wire 1 # rf_full_o $end
$var wire 1 $ rf_empty_o $end
$var wire 8 % rf_byte_o [7:0] $end
$var reg 8 & rf_byte_i [7:0] $end
$var reg 1 ' rf_clk_i $end
$var reg 1 ( rf_read_i $end
$var reg 1 ) rf_reset $end
$var reg 1 * rf_write_i $end
$scope module rf_1 $end
$var wire 8 + rf_byte_i [7:0] $end
$var wire 1 ' rf_clk_i $end
$var wire 1 ( rf_read_i $end
$var wire 1 ) rf_reset $end
$var wire 1 * rf_write_i $end
$var reg 7 , byte_count [6:0] $end
$var reg 6 - rd_ptr [5:0] $end
$var reg 8 . rf_byte_o [7:0] $end
$var reg 1 $ rf_empty_o $end
$var reg 1 # rf_full_o $end
$var reg 1 " rf_overflow_o $end
$var reg 1 ! rf_underflow_o $end
$var reg 6 / wr_ptr [5:0] $end
$upscope $end
$scope begin $ivl_for_loop0 $end
$var integer 32 0 i [31:0] $end
$upscope $end
$upscope $end
$enddefinitions $end
$comment Show the parameter values. $end
$dumpall
$end
#0
$dumpvars
bx 0
b0 /
bx .
b0 -
b0 ,
b0 +
0*
1)
0(
1'
b0 &
bx %
1$
0#
0"
0!
$end
#1
0'
#2
1'
0)
#3
0'
#4
b1 ,
b1 /
0$
1'
1*
b1 &
b1 +
#5
0'
#6
1'
0*
#7
0'
#8
b10 ,
b10 /
1'
1*
b1111 &
b1111 +
#9
0'
#10
1'
0*
#11
0'
#12
b11 ,
b11 /
1'
1*
b1010101 &
b1010101 +
#13
0'
#14
1'
0*
#15
0'
#16
1'
#17
0'
#18
b1 -
b10 ,
b1 %
b1 .
1'
1(
#19
0'
#20
bx %
bx .
1'
0(
#21
0'
#22
b10 -
b1111 %
b1111 .
b100 /
1'
1(
1*
b11111111 &
b11111111 +
#23
0'
#24
b11 -
b1 ,
b1010101 %
b1010101 .
1'
0*
#25
0'
#26
bx %
bx .
1'
0(
#27
0'
#28
b100 -
b0 ,
b11111111 %
b11111111 .
1'
1(
#29
0'
#30
bx %
bx .
1$
1'
b0 0
0(
#31
0'
#32
b1 ,
b101 /
0$
1'
b1 0
1*
b1111 &
b1111 +
#33
0'
#34
b10 ,
b110 /
1'
b10 0
#35
0'
#36
b11 ,
b111 /
1'
b11 0
#37
0'
#38
b100 ,
b1000 /
1'
b100 0
#39
0'
#40
b101 ,
b1001 /
1'
b101 0
#41
0'
#42
b110 ,
b1010 /
1'
b110 0
#43
0'
#44
b111 ,
b1011 /
1'
b111 0
#45
0'
#46
b1000 ,
b1100 /
1'
b1000 0
#47
0'
#48
b1001 ,
b1101 /
1'
b1001 0
#49
0'
#50
b1010 ,
b1110 /
1'
b1010 0
#51
0'
#52
b1011 ,
b1111 /
1'
b1011 0
#53
0'
#54
b1100 ,
b10000 /
1'
b1100 0
#55
0'
#56
b1101 ,
b10001 /
1'
b1101 0
#57
0'
#58
b1110 ,
b10010 /
1'
b1110 0
#59
0'
#60
b1111 ,
b10011 /
1'
b1111 0
#61
0'
#62
b10000 ,
b10100 /
1'
b10000 0
#63
0'
#64
b10001 ,
b10101 /
1'
b10001 0
#65
0'
#66
b10010 ,
b10110 /
1'
b10010 0
#67
0'
#68
b10011 ,
b10111 /
1'
b10011 0
#69
0'
#70
b10100 ,
b11000 /
1'
b10100 0
#71
0'
#72
b10101 ,
b11001 /
1'
b10101 0
#73
0'
#74
b10110 ,
b11010 /
1'
b10110 0
#75
0'
#76
b10111 ,
b11011 /
1'
b10111 0
#77
0'
#78
b11000 ,
b11100 /
1'
b11000 0
#79
0'
#80
b11001 ,
b11101 /
1'
b11001 0
#81
0'
#82
b11010 ,
b11110 /
1'
b11010 0
#83
0'
#84
b11011 ,
b11111 /
1'
b11011 0
#85
0'
#86
b11100 ,
b100000 /
1'
b11100 0
#87
0'
#88
b11101 ,
b100001 /
1'
b11101 0
#89
0'
#90
b11110 ,
b100010 /
1'
b11110 0
#91
0'
#92
b11111 ,
b100011 /
1'
b11111 0
#93
0'
#94
b100000 ,
b100100 /
1'
b100000 0
#95
0'
#96
b100001 ,
b100101 /
1'
b100001 0
#97
0'
#98
b100010 ,
b100110 /
1'
b100010 0
#99
0'
#100
b100011 ,
b100111 /
1'
b100011 0
#101
0'
#102
b100100 ,
b101000 /
1'
b100100 0
#103
0'
#104
b100101 ,
b101001 /
1'
b100101 0
#105
0'
#106
b100110 ,
b101010 /
1'
b100110 0
#107
0'
#108
b100111 ,
b101011 /
1'
b100111 0
#109
0'
#110
b101000 ,
b101100 /
1'
b101000 0
#111
0'
#112
b101001 ,
b101101 /
1'
b101001 0
#113
0'
#114
b101010 ,
b101110 /
1'
b101010 0
#115
0'
#116
b101011 ,
b101111 /
1'
b101011 0
#117
0'
#118
b101100 ,
b110000 /
1'
b101100 0
#119
0'
#120
b101101 ,
b110001 /
1'
b101101 0
#121
0'
#122
b101110 ,
b110010 /
1'
b101110 0
#123
0'
#124
b101111 ,
b110011 /
1'
b101111 0
#125
0'
#126
b110000 ,
b110100 /
1'
b110000 0
#127
0'
#128
b110001 ,
b110101 /
1'
b110001 0
#129
0'
#130
b110010 ,
b110110 /
1'
b110010 0
#131
0'
#132
b110011 ,
b110111 /
1'
b110011 0
#133
0'
#134
b110100 ,
b111000 /
1'
b110100 0
#135
0'
#136
b110101 ,
b111001 /
1'
b110101 0
#137
0'
#138
b110110 ,
b111010 /
1'
b110110 0
#139
0'
#140
b110111 ,
b111011 /
1'
b110111 0
#141
0'
#142
b111000 ,
b111100 /
1'
b111000 0
#143
0'
#144
b111001 ,
b111101 /
1'
b111001 0
#145
0'
#146
b111010 ,
b111110 /
1'
b111010 0
#147
0'
#148
b111011 ,
b111111 /
1'
b111011 0
#149
0'
#150
b111100 ,
b0 /
1'
b111100 0
#151
0'
#152
b111101 ,
b1 /
1'
b111101 0
#153
0'
#154
b111110 ,
b10 /
1'
b111110 0
#155
0'
#156
b111111 ,
b11 /
1'
b111111 0
#157
0'
#158
b1000000 ,
b100 /
1'
b1000000 0
#159
0'
#160
1"
1#
1'
#161
0'
#162
0"
1'
0*
#163
0'
#164
b0 ,
b0 /
b0 -
0#
1$
1'
1)
#165
0'
#166
1'
b0 &
b0 +
0)
#167
0'
#168
1'
#169
0'
#170
1'
#171
0'
#172
b1 ,
b1 /
0$
1'
1*
b11110000 &
b11110000 +
#173
0'
#174
b10 ,
b10 /
1'
b1111 &
b1111 +
#175
0'
#176
b11 ,
b11 /
1'
b11110000 &
b11110000 +
#177
0'
#178
b100 ,
b100 /
1'
b1111 &
b1111 +
#179
0'
#180
b101 ,
b101 /
1'
b11110000 &
b11110000 +
#181
0'
#182
b110 ,
b110 /
1'
b1111 &
b1111 +
#183
0'
#184
b1 -
b11110000 %
b11110000 .
b111 /
1'
1(
b11110000 &
b11110000 +
#185
0'
#186
b10 -
b1111 %
b1111 .
b1000 /
1'
b1111 &
b1111 +
#187
0'
#188
b11 -
b101 ,
b11110000 %
b11110000 .
1'
b0 &
b0 +
0*
#189
0'
#190
b100 -
b100 ,
b1111 %
b1111 .
1'
#191
0'
#192
b101 -
b11 ,
b11110000 %
b11110000 .
1'
#193
0'
#194
b110 -
b10 ,
b1111 %
b1111 .
1'
#195
0'
#196
b111 -
b1 ,
b11110000 %
b11110000 .
1'
#197
0'
#198
b1000 -
b0 ,
b1111 %
b1111 .
1'
#199
0'
#200
bx %
bx .
1$
1'
0(
