SIE/token_handler.v
module token_handler(
    input wire th_clk_i,
    input wire th_reset,
    input wire th_trigger,
    input wire th_eop_i,
    input wire th_sync_i,
    input wire [10:0]th_bytes_i,  //only the 11 bits : 7 addr + 4 endp
    input wire [1:0]th_byte_ready_i, // byte 2 and 3 only as 1st one is pid.
    input wire [4:0]th_crc5_i,
    output reg th_crc_reset_o,
    output reg th_token_valid_o,
    output reg th_crc_fail_o,
    output reg th_packet_error_o,
    output reg [6:0]th_addr_o,
    output reg [3:0]th_endp_o
);

    localparam IDLE = 2'b00;
    localparam ACTIVE = 2'b01;

    reg [1:0]STATE;
    reg th_byte1;
    
    always@(posedge th_clk_i or posedge th_reset)begin
        if(th_reset)begin
            th_crc_reset_o<=1'b0;
            th_token_valid_o<=1'b0;
            th_crc_fail_o<=1'b0;
            th_addr_o<=7'b0;
            th_endp_o<=4'b0;
            th_packet_error_o<=1'b0;
            STATE<=2'b0;
        end
        else begin
            th_token_valid_o<=1'b0;
            th_crc_fail_o<=1'b0;
            th_crc_reset_o<=1'b0;
            th_packet_error_o<=1'b0;
            case(STATE)
                IDLE : begin
                    if(th_trigger)begin
                        th_addr_o<=7'b0;
                        th_endp_o<=4'b0;
                        STATE<=ACTIVE;
                    end
                end
                ACTIVE : begin
                    if(th_byte_ready_i[0]==1'b1)begin
                        th_byte1<=th_bytes_i[7];
                        th_addr_o<=th_bytes_i[6:0];
                    end
                    if(th_byte_ready_i[1]==1'b1)begin
                        th_endp_o<={th_bytes_i[10:8],th_byte1};
                        if(th_crc5_i==5'b0)begin
                            th_token_valid_o<=1'b1;
                            th_crc_reset_o<=1'b1;
                            STATE<=IDLE;
                        end
                        else begin
                            th_crc_fail_o<=1'b1;
                            th_crc_reset_o<=1'b1;
                            STATE<=IDLE;
                        end   
                    end
                end
                default :  STATE<=IDLE;
            endcase
            if(STATE==ACTIVE) begin
                if(th_eop_i | th_sync_i)begin
                    th_packet_error_o<=1'b1;
                    th_crc_reset_o<=1'b1;
                    STATE<=IDLE;
                end
            end
        end
    end

endmodule

TB/SIE/token_handler_tb.v
module token_handler_tb;
    reg th_clk_i;
    reg th_reset;
    reg th_trigger;
    reg th_eop_i;
    reg th_sync_i;
    reg [10:0]th_bytes_i;
    reg [1:0]th_byte_ready_i;
    reg [4:0]th_crc5_i;
    wire th_crc_reset_o;
    wire th_token_valid_o;
    wire th_crc_fail_o;
    wire th_packet_error_o;
    wire [6:0]th_addr_o;
    wire [3:0]th_endp_o;

    reg [8*6:1]s;

    token_handler th_1(
        .th_clk_i(th_clk_i),
        .th_reset(th_reset),
        .th_trigger(th_trigger),
        .th_eop_i(th_eop_i),
        .th_sync_i(th_sync_i),
        .th_bytes_i(th_bytes_i),
        .th_byte_ready_i(th_byte_ready_i),
        .th_crc5_i(th_crc5_i),
        .th_crc_reset_o(th_crc_reset_o),
        .th_token_valid_o(th_token_valid_o),
        .th_crc_fail_o(th_crc_fail_o),
        .th_packet_error_o(th_packet_error_o),
        .th_addr_o(th_addr_o),
        .th_endp_o(th_endp_o)
    );

    initial begin
        $dumpfile("TB/SIE/DUMP/token_handler.vcd");
        $dumpvars(0,token_handler_tb);
        $display("|Time|Clk|Reset|En|Sync|EOP|Bytes(11-bits)|Byte_ready|State |CRC5 |Token_valid| Addr  |Endp|CRC_reset|CRC_fail|Pack_err|");
    end

    always@(posedge th_clk_i)begin
        $display("|%4t| %b |  %b  |%b | %b  | %b | %11b  |    %2b    |%s|%5b|     %b     |%7b|%4b|    %b    |   %b    |   %b    |",$time,th_clk_i,th_reset,th_trigger,th_sync_i,th_eop_i,th_bytes_i,th_byte_ready_i,s,th_crc5_i,th_token_valid_o,th_addr_o,th_endp_o,th_crc_reset_o,th_crc_fail_o,th_packet_error_o);
        case(th_1.STATE)
            2'b00 : s="IDLE";
            2'b01 : s="ACTIVE";
            default : s="IDLE";
        endcase
    end

    initial begin
        th_clk_i=1'b1;
        th_reset=1'b1;
        th_trigger=1'b0;
        th_eop_i=1'b0;
        th_sync_i=1'b0;
        th_bytes_i=11'b0;
        th_byte_ready_i=2'b0;
        th_crc5_i=5'b0;
    end

    always begin
        #1 th_clk_i=~th_clk_i;
    end

    initial begin
        #2 th_reset=1'b0;
        #2 th_sync_i=1'b1;
        #2 th_sync_i=1'b0;
        #10 th_trigger=1'b1;
        #2 th_trigger=1'b0;
        #14 th_byte_ready_i[0]=1'b1;
            th_bytes_i[7:0]=8'b0000_1111;  // 0000_1111_0000_0001
        #2 th_byte_ready_i[0]=1'b0;
        #14 th_byte_ready_i[1]=1'b1;
            th_bytes_i[10:8]=3'b000;
            th_crc5_i=5'b0;
        #2 th_byte_ready_i[1]=1'b0;
        #7 $finish;
    end

endmodule

TB/SIE/DUMP/token_handler.vcd
$date
	Sat Jun 20 19:37:17 2026
$end
$version
	Icarus Verilog
$end
$timescale
	1s
$end
$scope module token_handler_tb $end
$var wire 1 ! th_token_valid_o $end
$var wire 1 " th_packet_error_o $end
$var wire 4 # th_endp_o [3:0] $end
$var wire 1 $ th_crc_reset_o $end
$var wire 1 % th_crc_fail_o $end
$var wire 7 & th_addr_o [6:0] $end
$var reg 48 ' s [48:1] $end
$var reg 2 ( th_byte_ready_i [1:0] $end
$var reg 11 ) th_bytes_i [10:0] $end
$var reg 1 * th_clk_i $end
$var reg 5 + th_crc5_i [4:0] $end
$var reg 1 , th_eop_i $end
$var reg 1 - th_reset $end
$var reg 1 . th_sync_i $end
$var reg 1 / th_trigger $end
$scope module th_1 $end
$var wire 2 0 th_byte_ready_i [1:0] $end
$var wire 11 1 th_bytes_i [10:0] $end
$var wire 1 * th_clk_i $end
$var wire 5 2 th_crc5_i [4:0] $end
$var wire 1 , th_eop_i $end
$var wire 1 - th_reset $end
$var wire 1 . th_sync_i $end
$var wire 1 / th_trigger $end
$var parameter 2 3 ACTIVE $end
$var parameter 2 4 IDLE $end
$var reg 2 5 STATE [1:0] $end
$var reg 7 6 th_addr_o [6:0] $end
$var reg 1 7 th_byte1 $end
$var reg 1 % th_crc_fail_o $end
$var reg 1 $ th_crc_reset_o $end
$var reg 4 8 th_endp_o [3:0] $end
$var reg 1 " th_packet_error_o $end
$var reg 1 ! th_token_valid_o $end
$upscope $end
$upscope $end
$enddefinitions $end
$comment Show the parameter values. $end
$dumpall
b0 4
b1 3
$end
#0
$dumpvars
b0 8
x7
b0 6
b0 5
b0 2
b0 1
b0 0
0/
0.
1-
0,
b0 +
1*
b0 )
b0 (
b1001001010001000100110001000101 '
b0 &
0%
0$
b0 #
0"
0!
$end
#1
0*
#2
1*
0-
#3
0*
#4
1*
1.
#5
0*
#6
1*
0.
#7
0*
#8
1*
#9
0*
#10
1*
#11
0*
#12
1*
#13
0*
#14
1*
#15
0*
#16
b1 5
1*
1/
#17
0*
#18
b10000010100001101010100010010010101011001000101 '
1*
0/
#19
0*
#20
1*
#21
0*
#22
1*
#23
0*
#24
1*
#25
0*
#26
1*
#27
0*
#28
1*
#29
0*
#30
1*
#31
0*
#32
b1111 &
b1111 6
07
1*
b1111 )
b1111 1
b1 (
b1 0
#33
0*
#34
1*
b0 (
b0 0
#35
0*
#36
1*
#37
0*
#38
1*
#39
0*
#40
1*
#41
0*
#42
1*
#43
0*
#44
1*
#45
0*
#46
1*
#47
0*
#48
b0 5
1$
1!
1*
b10 (
b10 0
#49
0*
#50
0$
0!
b1001001010001000100110001000101 '
1*
b0 (
b0 0
