HEADERS/PID.vh
`ifndef PID_VH
`define PID_VH

//PID TYPEs
`define PID_SPECIAL 2'b00
`define PID_TOKEN 2'b01
`define PID_HANDSHAKE 2'b10
`define PID_DATA 2'b11

//TOKEN PIDs
`define PID_OUT 8'b1110_0001
`define PID_SOF 8'b1010_0101
`define PID_IN 8'b0110_1001
`define PID_SETUP 8'b0010_1101

//DATA PIDs
`define PID_DATA0 8'b1100_0011
`define PID_DATA2 8'b1000_0111
`define PID_DATA1 8'b0100_1011
`define PID_MDATA 8'b0000_1111

//HANDSHAKE PIDs
`define PID_ACK 8'b1101_0010
`define PID_NYET 8'b1001_0110
`define PID_NAK 8'b0101_1010
`define PID_STALL 8'b0001_1110

//SPECIAL
`define PID_PING 8'b1011_0100
`define PID_SPLIT 8'b0111_1000
`define PID_PRE 8'b0011_1100

`define PID_INVALID 8'b0000_0000

`endif

SIE/transaction_engine.v
`include "PID.vh"
module transaction_engine#(
    parameter RESPONSE_TIMEOUT=10'd816;
)(
    input wire te_clk_i,
    input wire te_reset,
    input wire te_sync_i,
    input wire te_eop_i,

    input wire [3:0]te_pid_nibble_i,
    input wire te_pid_valid_i,

    input wire te_token_trigger_i, //token handler net
    input wire te_token_valid_i,
    input wire te_token_pac_err_i,
    input wire te_crc5_fail_i,
    input wire [6:0]te_addr_i,
    input wire [3:0]te_endp_i,

    input wire te_data_trigger_i, //data handler net
    input wire te_data_valid_i,
    input wire te_data_pac_err_i,
    input wire te_crc16_fail_i,

    input wire te_handshake_trigger_i, //handshake handler net
    input wire te_ack_i,
    input wire te_stall_i,
    input wire te_nak_i,

    input wire te_timeout_i,

    input wire te_endp_data_toggle_i,
    input wire te_endp_data_fail_i,
    input wire te_endp_empty_i,
    input wire te_endp_tx_done_i,
    input wire te_endp_stalled_i,
    input wire te_endp_ready_i,  //flag

    output reg te_send_ack_o,
    output reg te_send_nak_o,
    output reg te_send_stall_o,
    output reg te_send_data_o,
    output reg te_data_toggle_o,
    output reg te_clear_endp_buff_o,
    output reg te_setup_done_o,

    output reg te_protocol_err_o
);
    //For both STATE and SUB_STATE
    localparam IDLE=3'd0; 
    //For STATE
    localparam OUT_TR=3'd1; 
    localparam IN_TR=3'd2;
    localparam SETUP_TR=3'd3;
    //For SUB_STATE
    localparam OUT=3'd1;  
    localparam IN=3'd1;
    localparam CONFIRM=3'd1;
    localparam DATA=3'd2;
    localparam RESPONSE=3'd3;

    reg [2:0]STATE;
    reg [2:0]SUB_STATE;

    reg[9:0]te_timer;
    reg te_timer_en;

    reg te_ignore; //just for 
    reg te_abort;  //testing

    always@(posedge te_clk_i or posedge te_reset)begin
        if(te_reset)begin
            te_send_ack_o<=1'b0;
            te_send_nak_o<=1'b0;
            te_send_data_o<=1'b0;
            te_send_stall_o<=1'b0;
            te_data_toggle_o<=1'b0;
            te_clear_endp_buff_o<=1'b0;
            te_protocol_err_o<=1'b0;
            te_ignore<=1'b0;
            te_abort<=1'b0;
            STATE<=3'b0;
            SUB_STATE<=3'b0;
            te_timer<=10'b0;
            te_timer_en<=1'b0;
            te_setup_done_o<=1'b0;
        end
        else begin
            te_ignore<=1'b0;
            te_abort<=1'b0;
            te_protocol_err_o<=1'b0;
            te_send_ack_o<=1'b0;
            te_send_nak_o<=1'b0;
            te_send_stall_o<=1'b0;
            te_send_data_o<=1'b0;
            te_data_toggle_o<=1'b0;
            te_clear_endp_buff_o<=1'b0;
            te_setup_done_o<=1'b0;
            case(STATE)
                IDLE : begin
                    SUB_STATE<=IDLE;
                    te_timer_en<=1'b0;
                    if(te_token_trigger_i)begin
                        case(te_pid_nibble_i)
                            `PIDN_OUT : STATE<=OUT_TR;
                            `PIDN_IN : STATE<=IN_TR;
                            `PIDN_SETUP : STATE<=SETUP_TR;
                            default: STATE<=IDLE;
                        endcase
                    end
                    if(te_data_trigger_i || te_handshake_trigger_i)begin
                        te_protocol_err_o<=1'b1;
                    end
                end
                OUT_TR : begin
                    if(te_timeout_i)begin
                        te_abort<=1'b1;
                        SUB_STATE<=IDLE;
                        STATE<=IDLE;
                    end
                    else begin 
                        case(SUB_STATE)
                            IDLE : begin
                                if(te_token_pac_err_i || te_crc5_fail_i)begin
                                    te_ignore<=1'b1;
                                    STATE<=IDLE;
                                end
                                else if(te_token_valid_i)begin
                                    SUB_STATE<=OUT;
                                    te_timer_en<=1'b1;
                                    //note address and endpoint
                                end
                            end
                            OUT : begin
                                if(te_timer==RESPONSE_TIMEOUT-1)begin
                                    te_timer_en<=1'b0;
                                    SUB_STATE<=IDLE;
                                    STATE<=IDLE;
                                end
                                else if(te_handshake_trigger_i)begin
                                    te_protocol_err_o<=1'b1;
                                    SUB_STATE<=IDLE;
                                    STATE<=IDLE;
                                end
                                else if(te_token_trigger_i)begin
                                    te_abort<=1'b1;
                                    SUB_STATE<=IDLE;
                                    STATE<=IDLE;
                                end
                                else if(te_data_trigger_i)begin
                                    SUB_STATE<=DATA;
                                    te_timer_en<=1'b0;
                                end
                            end
                            DATA : begin
                                if(te_data_pac_err_i || te_crc16_fail_i)begin
                                    te_ignore<=1'b1;
                                    SUB_STATE<=IDLE;
                                    STATE<=IDLE;
                                end
                                else if(te_data_valid_i)begin
                                    te_send_ack_o<=1'b1;
                                    te_data_toggle_o<=1'b1;  //if ack is lost in the middle,
                                    SUB_STATE<=IDLE;        //host resends the same DATA packet
                                    STATE<=IDLE;            //device must detect it as a duplicate &
                                end                         //send ack again
                            end
                            default : SUB_STATE<=IDLE;
                        endcase
                    end
                end
                IN_TR : begin
                    if(te_timeout_i)begin
                        te_abort<=1'b1;
                        SUB_STATE<=IDLE;
                        STATE<=IDLE;
                    end
                    else begin 
                        case(SUB_STATE)
                            IDLE : begin
                                if(te_token_pac_err_i || te_crc5_fail_i)begin
                                    te_ignore<=1'b1;
                                    STATE<=IDLE;
                                    SUB_STATE<=IDLE;
                                end
                                else if(te_token_valid_i)begin
                                    SUB_STATE<=IN;
                                end 
                            end
                            IN : begin
                                if(te_endp_empty_i)begin
                                    te_send_nak_o<=1'b1;
                                    STATE<=IDLE;
                                    SUB_STATE<=IDLE;
                                end
                                else if(te_endp_stalled_i)begin
                                    te_send_stall_o<=1'b1;
                                    STATE<=IDLE;
                                    SUB_STATE<=IDLE;
                                end
                                else if(te_endp_ready_i)begin
                                    te_send_data_o<=1'b1;
                                    SUB_STATE<=DATA;
                                end
                            end
                            DATA : begin
                                if(te_endp_data_fail_i)begin
                                    STATE<=IDLE;
                                    SUB_STATE<=IDLE;
                                end
                                else if(te_endp_tx_done_i)begin
                                    SUB_STATE<=RESPONSE;
                                    te_timer_en<=1'b1;
                                end
                            end
                            RESPONSE : begin
                                if(te_timer==RESPONSE_TIMEOUT-1)begin
                                    te_timer<=10'b0;
                                    SUB_STATE<=IDLE;
                                    STATE<=IDLE;
                                end
                                else if(te_ack_i)begin
                                    te_clear_endp_buff_o<=1'b1;
                                    te_data_toggle_o<=1'b1;
                                    te_timer_en<=1'b0;
                                    SUB_STATE<=IDLE;
                                    STATE<=IDLE;
                                end
                                else if(te_stall_i || te_nak_i)begin
                                    te_protocol_err_o<=1'b1;
                                    te_timer_en<=1'b0;
                                    SUB_STATE<=IDLE;
                                    STATE<=IDLE;
                                end
                            end
                            default : SUB_STATE<=IDLE;
                        endcase
                    end
                end
                SETUP_TR : begin    //'Sending control request DATA'
                    if(te_timeout_i)begin
                        te_abort<=1'b1;
                        SUB_STATE<=IDLE;
                        STATE<=IDLE;
                    end
                    else begin
                        case(SUB_STATE)
                            IDLE : begin
                                if(te_token_pac_err_i || te_crc5_fail_i)begin
                                    te_ignore<=1'b1;
                                    STATE<=IDLE;
                                end
                                else if(te_token_valid_i)begin
                                    SUB_STATE<=CONFIRM;
                                    te_timer_en<=1'b1;
                                end
                            end
                            CONFIRM : begin
                                if(te_timer==RESPONSE_TIMEOUT-1)begin
                                    te_timer_en<=1'b0;
                                    SUB_STATE<=IDLE;
                                    STATE<=IDLE;
                                end
                                else if(te_data_trigger_i)begin
                                    te_timer_en<=1'b0;
                                    if(te_pid_nibble_i==`PIDN_DATA0)
                                        SUB_STATE<=DATA;
                                    else begin
                                        SUB_STATE<=IDLE;
                                        STATE<=IDLE;
                                    end        
                                end
                            end
                            DATA : begin //DATA0 only
                                if(te_data_pac_err_i || te_crc16_fail_i)begin
                                    te_ignore<=1'b1;
                                    SUB_STATE<=IDLE;
                                    STATE<=IDLE;
                                end
                                else if(te_data_valid_i)begin
                                    te_send_ack_o<=1'b1;
                                    te_data_toggle_o<=1'b1;  //if ack is lost in the middle,
                                    SUB_STATE<=IDLE;        //host resends the same DATA packet
                                    STATE<=IDLE;            //device must detect it as a duplicate &
                                    te_setup_done_o<=1'b1;  //send ack again
                                end                         
                            end
                            default : SUB_STATE<=IDLE;
                        endcase
                    end
                end
                default : STATE<=IDLE;
            endcase
            if(te_timer_en)begin
                te_timer<=te_timer+1;
            end
            else 
                te_timer<=10'b0;
        end
    end
endmodule

TB/SIE/transaction_engine_tb.v
module transaction_engine_tb;
    reg te_clk_i;
    reg te_reset;
    //reg te_sync_i;
    //reg te_eop_i;
    reg [3:0]te_pid_nibble_i;
    //reg te_pid_valid_i;
    //token handler net
    reg te_token_trigger_i; 
    reg te_token_valid_i;
    reg te_token_pac_err_i;
    reg te_crc5_fail_i;
    reg [6:0]te_addr_i;
    reg [3:0]te_endp_i;
    //data handler net
    reg te_data_trigger_i; 
    reg te_data_valid_i;
    reg te_data_pac_err_i;
    reg te_crc16_fail_i;
    //handshake handler net
    reg te_handshake_trigger_i; 
    reg te_ack_i;
    reg te_stall_i;
    reg te_nak_i;
    reg te_timeout_i;
    reg te_endp_data_toggle_i;
    reg te_endp_data_fail_i;
    reg te_endp_empty_i;
    reg te_endp_tx_done_i;
    reg te_endp_stalled_i;
    reg te_endp_ready_i;  //flag
    wire te_send_ack_o;
    wire te_send_nak_o;
    wire te_send_stall_o;
    wire te_send_data_o;
    wire te_data_toggle_o;
    wire te_clear_endp_buff_o;
    wire te_setup_done_o;
    wire te_protocol_err_o;
    
    transaction_engine te_1(
        .te_clk_i(te_clk_i),
        .te_reset(te_reset),
        //.te_sync_i(te_sync_i),
        //.te_eop_i(te_eop_i),
        .te_pid_nibble_i(te_pid_nibble_i),
        //.te_pid_valid_i(te_pid_valid_i),
        .te_token_trigger_i(te_token_trigger_i), 
        .te_token_valid_i(te_token_valid_i),
        .te_token_pac_err_i(te_token_pac_err_i),
        .te_crc5_fail_i(te_crc5_fail_i),
        .te_addr_i(te_addr_i),
        .te_endp_i(te_endp_i),
        .te_data_trigger_i(te_data_trigger_i), 
        .te_data_valid_i(te_data_valid_i),
        .te_data_pac_err_i(te_data_pac_err_i),
        .te_crc16_fail_i(te_crc16_fail_i),
        .te_handshake_trigger_i(te_handshake_trigger_i), 
        .te_ack_i(te_ack_i),
        .te_stall_i(te_stall_i),
        .te_nak_i(te_nak_i),
        .te_timeout_i(te_timeout_i),
        .te_endp_data_toggle_i(te_endp_data_toggle_i),
        .te_endp_data_fail_i(te_endp_data_fail_i),
        .te_endp_empty_i(te_endp_empty_i),
        .te_endp_tx_done_i(te_endp_tx_done_i),
        .te_endp_stalled_i(te_endp_stalled_i),
        .te_endp_ready_i(te_endp_ready_i),  //flag
        .te_send_ack_o(te_send_ack_o),
        .te_send_nak_o(te_send_nak_o),
        .te_send_stall_o(te_send_stall_o),
        .te_send_data_o(te_send_data_o),
        .te_data_toggle_o(te_data_toggle_o),
        .te_clear_endp_buff_o(te_clear_endp_buff_o),
        .te_setup_done_o(te_setup_done_o),
        .te_protocol_err_o(te_protocol_err_o)
    );

    initial begin
        $dumpfile("TB/SIE/DUMP/transaction_engine.vcd");
        $dumpvars(0,transaction_engine_tb);
        //OUT transaction
        $display("|Time|Clk|Rst|Timeout|PID_in|T_trigger|T_valid|T_err|T_crc5_fail|Timer|D_trigger|D_valid|D_err|D_crc16_fail|Abort|Ignore|Send_ACK|Data_toggle|");
    end
    always@(posedge te_clk_i)begin
        //OUT transaction
        $display("|%4t| %b | %b |   %b   | %4b |    %b    |   %b   |  %b  |     %b     | %4d|    %b    |   %b   |  %b  |     %b      |  %b  |  %b   |   %b    |     %b     |",$time,te_clk_i,te_reset,te_timeout_i,te_pid_nibble_i,te_token_trigger_i,te_token_valid_i,te_token_pac_err_i,te_crc5_fail_i,te_1.te_timer,te_data_trigger_i,te_data_valid_i,te_data_pac_err_i,te_crc16_fail_i,te_1.te_abort,te_1.te_ignore,te_send_ack_o,te_data_toggle_o);
    end

    initial begin
        te_clk_i=1'b1;
        te_reset=1'b1;
        //te_sync_i=1'b0;
        //te_eop_i=1'b0;
        te_pid_nibble_i=4'b0;
        //te_pid_valid_i=1'b0;
    //token handler net
        te_token_trigger_i=1'b0; 
        te_token_valid_i=1'b0;
        te_token_pac_err_i=1'b0;
        te_crc5_fail_i=1'b0;
        te_addr_i=7'b0;
        te_endp_i=4'b0;
    //data handler net
        te_data_trigger_i=1'b0; 
        te_data_valid_i=1'b0;
        te_data_pac_err_i=1'b0;
        te_crc16_fail_i=1'b0;
    //handshake net
        te_handshake_trigger_i=1'b0; 
        te_ack_i=1'b0;
        te_stall_i=1'b0;
        te_nak_i=1'b0;
        //packet timer
        te_timeout_i=1'b0;
        //endpoint
        te_endp_data_toggle_i=1'b0;
        te_endp_data_fail_i=1'b0;
        te_endp_empty_i=1'b0;
        te_endp_tx_done_i=1'b0;
        te_endp_stalled_i=1'b0;
        te_endp_ready_i=1'b0;  //flag
    end
    always begin
        #1 te_clk_i=~te_clk_i;
    end

    initial begin
        #2 te_reset=1'b0;
        //OUT transaction
        #2 
        #5 $finish;
    end
endmodule

TB/SIE/DUMP/transaction_engine.vcd
$date
	Sat Jul  4 20:13:36 2026
$end
$version
	Icarus Verilog
$end
$timescale
	1s
$end
$scope module transaction_engine_tb $end
$var wire 1 ! te_abort $end
$var wire 1 " te_ignore $end
$var wire 10 # te_timer [9:0] $end
$var wire 1 $ te_setup_done_o $end
$var wire 1 % te_send_stall_o $end
$var wire 1 & te_send_nak_o $end
$var wire 1 ' te_send_data_o $end
$var wire 1 ( te_send_ack_o $end
$var wire 1 ) te_protocol_err_o $end
$var wire 1 * te_data_toggle_o $end
$var wire 1 + te_clear_endp_buff_o $end
$var reg 1 , te_ack_i $end
$var reg 7 - te_addr_i [6:0] $end
$var reg 1 . te_clk_i $end
$var reg 1 / te_crc16_fail_i $end
$var reg 1 0 te_crc5_fail_i $end
$var reg 1 1 te_data_pac_err_i $end
$var reg 1 2 te_data_trigger_i $end
$var reg 1 3 te_data_valid_i $end
$var reg 1 4 te_endp_data_fail_i $end
$var reg 1 5 te_endp_data_toggle_i $end
$var reg 1 6 te_endp_empty_i $end
$var reg 4 7 te_endp_i [3:0] $end
$var reg 1 8 te_endp_ready_i $end
$var reg 1 9 te_endp_stalled_i $end
$var reg 1 : te_endp_tx_done_i $end
$var reg 1 ; te_handshake_trigger_i $end
$var reg 1 < te_nak_i $end
$var reg 4 = te_pid_nibble_i [3:0] $end
$var reg 1 > te_reset $end
$var reg 1 ? te_stall_i $end
$var reg 1 @ te_timeout_i $end
$var reg 1 A te_token_pac_err_i $end
$var reg 1 B te_token_trigger_i $end
$var reg 1 C te_token_valid_i $end
$scope module te_1 $end
$var wire 1 , te_ack_i $end
$var wire 7 D te_addr_i [6:0] $end
$var wire 1 . te_clk_i $end
$var wire 1 / te_crc16_fail_i $end
$var wire 1 0 te_crc5_fail_i $end
$var wire 1 1 te_data_pac_err_i $end
$var wire 1 2 te_data_trigger_i $end
$var wire 1 3 te_data_valid_i $end
$var wire 1 4 te_endp_data_fail_i $end
$var wire 1 5 te_endp_data_toggle_i $end
$var wire 1 6 te_endp_empty_i $end
$var wire 4 E te_endp_i [3:0] $end
$var wire 1 8 te_endp_ready_i $end
$var wire 1 9 te_endp_stalled_i $end
$var wire 1 : te_endp_tx_done_i $end
$var wire 1 ; te_handshake_trigger_i $end
$var wire 1 < te_nak_i $end
$var wire 4 F te_pid_nibble_i [3:0] $end
$var wire 1 > te_reset $end
$var wire 1 ? te_stall_i $end
$var wire 1 @ te_timeout_i $end
$var wire 1 A te_token_pac_err_i $end
$var wire 1 B te_token_trigger_i $end
$var wire 1 C te_token_valid_i $end
$var parameter 3 G CONFIRM $end
$var parameter 3 H DATA $end
$var parameter 3 I IDLE $end
$var parameter 3 J IN $end
$var parameter 3 K IN_TR $end
$var parameter 3 L OUT $end
$var parameter 3 M OUT_TR $end
$var parameter 3 N RESPONSE $end
$var parameter 10 O RESPONSE_TIMEOUT $end
$var parameter 3 P SETUP_TR $end
$var reg 3 Q STATE [2:0] $end
$var reg 3 R SUB_STATE [2:0] $end
$var reg 1 S te_abort $end
$var reg 1 + te_clear_endp_buff_o $end
$var reg 1 * te_data_toggle_o $end
$var reg 1 T te_ignore $end
$var reg 1 ) te_protocol_err_o $end
$var reg 1 ( te_send_ack_o $end
$var reg 1 ' te_send_data_o $end
$var reg 1 & te_send_nak_o $end
$var reg 1 % te_send_stall_o $end
$var reg 1 $ te_setup_done_o $end
$var reg 10 U te_timer [9:0] $end
$var reg 1 V te_timer_en $end
$upscope $end
$upscope $end
$enddefinitions $end
$comment Show the parameter values. $end
$dumpall
b11 P
b1100110000 O
b11 N
b1 M
b1 L
b10 K
b1 J
b0 I
b10 H
b1 G
$end
#0
$dumpvars
0V
b0 U
0T
0S
b0 R
b0 Q
b1 F
b0 E
b0 D
0C
0B
0A
0@
0?
1>
b1 =
0<
0;
0:
09
08
b0 7
06
05
04
03
02
01
00
0/
1.
b0 -
0,
0+
0*
0)
0(
0'
0&
0%
0$
b0 #
0"
0!
$end
#1
0.
#2
1.
0>
#3
0.
#4
1.
#5
0.
#6
1)
1.
12
#7
0.
#8
0)
1.
02
#9
0.
#10
1.
#11
0.
#12
1.
#13
0.
#14
1.
#15
0.
#16
1)
1.
1;
#17
0.
#18
0)
1.
0;
#19
0.
#20
b1 Q
1.
1B
#21
0.
#22
1.
0B
#23
0.
#24
1.
#25
0.
#26
b0 Q
1!
1S
1.
1@
#27
0.
#28
0!
0S
1.
0@
#29
0.
#30
1.
#31
0.
#32
b1 Q
1.
1B
#33
0.
#34
1.
0B
#35
0.
#36
1.
#37
0.
#38
b0 Q
1"
1T
1.
1A
#39
0.
#40
0"
0T
1.
0A
#41
0.
#42
1.
#43
0.
#44
b1 Q
1.
1B
#45
0.
#46
1.
0B
#47
0.
#48
1.
#49
0.
#50
b0 Q
1"
1T
1.
10
#51
0.
#52
0"
0T
1.
00
#53
0.
#54
1.
#55
0.
#56
b1 Q
1.
1B
#57
0.
#58
1.
0B
#59
0.
#60
1.
#61
0.
#62
1.
#63
0.
#64
1.
#65
0.
#66
1.
#67
0.
#68
1.
#69
0.
#70
1.
#71
0.
#72
1.
#73
0.
#74
1.
#75
0.
#76
1.
#77
0.
#78
1V
b1 R
1.
1C
#79
0.
#80
b1 #
b1 U
1.
0C
#81
0.
#82
b10 #
b10 U
1.
#83
0.
#84
b11 #
b11 U
b0 Q
b0 R
1!
1S
1.
1B
#85
0.
#86
b100 #
b100 U
0V
0!
0S
1.
0B
#87
0.
#88
b0 #
b0 U
1.
#89
0.
#90
b1 Q
1.
1B
#91
0.
#92
1.
0B
#93
0.
#94
1.
#95
0.
#96
1.
#97
0.
#98
1.
#99
0.
#100
1.
#101
0.
#102
1.
#103
0.
#104
1.
#105
0.
#106
1.
#107
0.
#108
1.
#109
0.
#110
1.
#111
0.
#112
1V
b1 R
1.
1C
#113
0.
#114
b1 #
b1 U
1.
0C
#115
0.
#116
b10 #
b10 U
1.
#117
0.
#118
b11 #
b11 U
b0 Q
b0 R
1)
1.
1;
#119
0.
#120
b100 #
b100 U
0V
0)
1.
0;
#121
0.
#122
b0 #
b0 U
b1 Q
1.
1B
#123
0.
#124
1.
0B
#125
0.
#126
1.
#127
0.
#128
1.
#129
0.
#130
1.
#131
0.
#132
1.
#133
0.
#134
1.
#135
0.
#136
1.
#137
0.
#138
1.
#139
0.
#140
1.
#141
0.
#142
1.
#143
0.
#144
1V
b1 R
1.
1C
#145
0.
#146
b1 #
b1 U
1.
0C
#147
0.
#148
b10 #
b10 U
1.
#149
0.
#150
b11 #
b11 U
1.
#151
0.
#152
b100 #
b100 U
1.
#153
0.
#154
b101 #
b101 U
1.
#155
0.
#156
b110 #
b110 U
0V
b10 R
1.
12
#157
0.
#158
b0 #
b0 U
1.
02
#159
0.
#160
1.
#161
0.
#162
1.
#163
0.
#164
b0 Q
b0 R
1"
1T
1.
11
#165
0.
#166
0"
0T
1.
01
#167
0.
#168
b1 Q
1.
1B
#169
0.
#170
1.
0B
#171
0.
#172
1.
#173
0.
#174
1.
#175
0.
#176
1.
#177
0.
#178
1.
#179
0.
#180
1.
#181
0.
#182
1.
#183
0.
#184
1.
#185
0.
#186
1.
#187
0.
#188
1.
#189
0.
#190
1V
b1 R
1.
1C
#191
0.
#192
b1 #
b1 U
1.
0C
#193
0.
#194
b10 #
b10 U
1.
#195
0.
#196
b11 #
b11 U
1.
#197
0.
#198
b100 #
b100 U
1.
#199
0.
#200
b101 #
b101 U
1.
#201
0.
#202
b110 #
b110 U
0V
b10 R
1.
12
#203
0.
#204
b0 #
b0 U
1.
02
#205
0.
#206
1.
#207
0.
#208
1.
#209
0.
#210
1.
#211
0.
#212
1.
#213
0.
#214
1.
#215
0.
#216
1.
#217
0.
#218
1.
#219
0.
#220
1.
#221
0.
#222
1.
#223
0.
#224
b0 Q
b0 R
1"
1T
1.
1/
#225
0.
#226
0"
0T
1.
0/
#227
0.
#228
b1 Q
1.
1B
#229
0.
#230
1.
0B
#231
0.
#232
1.
#233
0.
#234
1.
#235
0.
#236
1.
#237
0.
#238
1.
#239
0.
#240
1.
#241
0.
#242
1.
#243
0.
#244
1.
#245
0.
#246
1.
#247
0.
#248
1.
#249
0.
#250
1V
b1 R
1.
1C
#251
0.
#252
b1 #
b1 U
1.
0C
#253
0.
#254
b10 #
b10 U
1.
#255
0.
#256
b11 #
b11 U
1.
#257
0.
#258
b100 #
b100 U
1.
#259
0.
#260
b101 #
b101 U
1.
#261
0.
#262
b110 #
b110 U
0V
b10 R
1.
12
#263
0.
#264
b0 #
b0 U
1.
02
#265
0.
#266
1.
#267
0.
#268
1.
#269
0.
#270
1.
#271
0.
#272
1.
#273
0.
#274
1.
#275
0.
#276
1.
#277
0.
#278
1.
#279
0.
#280
1.
#281
0.
#282
1.
#283
0.
#284
b0 Q
b0 R
1*
1(
1.
13
#285
0.
#286
0*
0(
1.
03
