HEADERS/BASES.vh
`ifndef BASES_VH
`define BASES_VH
    `define DEVICE_BASE 8'h00;  //length = 8'h12
    `define CONFIGURATION_BASE 8'h12;  //length = 8'h09
    `define INTERFACE_BASE 8'h1B;  //length = 8'h09
    `define EP1OUT_BASE 8'h24;  //length = 8'h07
    `define EP1IN_BASE 8'h2B;  //length = 8'h07
    `define STRING0_BASE 8'h32;  //length = 8'h04
    `define STRING1_BASE 8'h36;  //length = 8'h10
    `define STRING2_BASE 8'h46;  //length = 8'h10
    `define STRING3_BASE 8'h56;  //length = 8'h0E
`endif

HEADERS/DESCRIPTOR_TYPES.vh
`ifndef DESCRIPTOR_VH
`define DESCRIPTOR_VH
    
    //DESCRIPTOR TYPES
    `define TYPE_DEVICE 8'h01
    `define TYPE_CONFIGURATION 8'h02
    `define TYPE_INTERFACE 8'h03
    `define TYPE_ENDPOINT 8'h04
    `define TYPE_STRING 8'h05
    `define TYPE_QUALIFIER 8'h06
    `define TYPE_OTHER_SPEED 8'h07
    `define TYPE_INTERFACE_POWER 8'h08

`endif

CONTROL/descriptor_manager.v
`include "DESCRIPTOR_TYPES.vh"
`include "BASES.vh"
module descriptor_manager(
    input wire dm_read_i,
    input wire [7:0]dm_type_i,
    input wire [7:0]dm_index_i,
    output reg [7:0]dm_addr_o,
    output reg [7:0]dm_length_o,
    output reg dm_valid_o
);

    localparam STRING0 = 8'h00;
    localparam STRING1 = 8'h01;
    localparam STRING2 = 8'h02;
    localparam STRING3 = 8'h03;

    always @(*)begin
            dm_addr_o=8'h00;
            dm_length_o=8'h00;
            dm_valid_o=1'b0;
            if(dm_read_i)begin
                case(dm_type_i)
                `TYPE_DEVICE : begin
                    if(dm_index_i==8'h00)begin
                        dm_addr_o=`DEVICE_BASE;
                        dm_length_o=`DEVICE_LENGTH;
                        dm_valid_o=1'b1;
                    end
                end
                `TYPE_CONFIGURATION : begin
                    if(dm_index_i==8'h00)begin
                        dm_addr_o=`CONFIGURATION_BASE;
                        dm_length_o=`CONFIGURATION_LENGTH;
                        dm_valid_o=1'b1;
                    end
                end
                `TYPE_STRING : begin
                    case(dm_index_i)
                        STRING0 : begin
                            dm_addr_o=`STRING0_BASE;
                            dm_length_o=`STRING0_LENGTH;
                            dm_valid_o=1'b1;
                        end
                        STRING1 : begin
                            dm_addr_o=`STRING1_BASE;
                            dm_length_o=`STRING1_LENGTH;
                            dm_valid_o=1'b1;
                        end
                        STRING2 : begin
                            dm_addr_o=`STRING2_BASE;
                            dm_length_o=`STRING2_LENGTH;
                            dm_valid_o=1'b1;
                        end
                        STRING3 : begin
                            dm_addr_o=`STRING3_BASE;
                            dm_length_o=`STRING3_LENGTH;
                            dm_valid_o=1'b1;
                        end
                    endcase 
                end
                endcase
            end
    end
endmodule

TB/CONTROL/descriptor_manager_tb.v
`timescale 1 ns / 1ns;
module descriptor_manager_tb;
    reg dm_read_i;
    reg [7:0]dm_type_i;
    reg [7:0]dm_index_i;
    wire [7:0]dm_addr_o;
    wire [7:0]dm_length_o;
    wire dm_valid_o;

    reg stop;

    descriptor_manager dm_1(
        .dm_read_i(dm_read_i),
        .dm_type_i(dm_type_i),
        .dm_index_i(dm_index_i),
        .dm_addr_o(dm_addr_o),
        .dm_length_o(dm_length_o),
        .dm_valid_o(dm_valid_o)
    );

    initial begin
        $dumpfile("TB/CONTROL/DUMP/descriptor_manager.vcd");
        $dumpvars(0,descriptor_manager_tb);
        $display("|Time|Read|Type|Index|Address_Out|Length_Out|Valid_Out|");
        //$monitor("|%4t| %b  | %2h | %2h  |    %2h     |    %2h    |    %b    |",$time,dm_read_i,dm_type_i,dm_index_i,dm_addr_o,dm_length_o,dm_valid_o);
    end

    always begin
        #1  $display("|%4t| %b  | %2h | %2h  |    %2h     |    %2h    |    %b    |",$time,dm_read_i,dm_type_i,dm_index_i,dm_addr_o,dm_length_o,dm_valid_o);
    end

    initial begin
        dm_read_i=1'b0;
        dm_type_i=8'h00;
        dm_index_i=8'h00;
    end

    initial begin
        #3 dm_read_i=1'b1;
        dm_type_i=8'h01;
        dm_index_i=8'h00;
        #1 dm_read_i=1'b0;

        #3 dm_read_i=1'b1;
        dm_type_i=8'h02;
        dm_index_i=8'h00;
        #1 dm_read_i=1'b0;

        #3 dm_read_i=1'b1;
        dm_type_i=8'h05;
        dm_index_i=8'h00;
        #1 dm_read_i=1'b0;

        #3 dm_read_i=1'b1;
        dm_type_i=8'h05;
        dm_index_i=8'h01;
        #1 dm_read_i=1'b0;
        
        #3 dm_read_i=1'b1;
        dm_type_i=8'h05;
        dm_index_i=8'h02;
        #1 dm_read_i=1'b0;
        
        #3 dm_read_i=1'b1;
        dm_type_i=8'h05;
        dm_index_i=8'h03;
        #1 dm_read_i=1'b0;
        
        #5 $finish;
    end

endmodule

TB/CONTROL/DUMP/descriptor_manager.vcd
$date
	Thu Jul 30 09:45:21 2026
$end
$version
	Icarus Verilog
$end
$timescale
	1ns
$end
$scope module descriptor_manager_tb $end
$var wire 1 ! dm_valid_o $end
$var wire 8 " dm_length_o [7:0] $end
$var wire 8 # dm_addr_o [7:0] $end
$var reg 8 $ dm_index_i [7:0] $end
$var reg 1 % dm_read_i $end
$var reg 8 & dm_type_i [7:0] $end
$scope module dm_1 $end
$var wire 8 ' dm_index_i [7:0] $end
$var wire 1 % dm_read_i $end
$var wire 8 ( dm_type_i [7:0] $end
$var parameter 8 ) STRING0 $end
$var parameter 8 * STRING1 $end
$var parameter 8 + STRING2 $end
$var parameter 8 , STRING3 $end
$var reg 8 - dm_addr_o [7:0] $end
$var reg 8 . dm_length_o [7:0] $end
$var reg 1 ! dm_valid_o $end
$upscope $end
$upscope $end
$enddefinitions $end
$comment Show the parameter values. $end
$dumpall
b11 ,
b10 +
b1 *
b0 )
$end
#0
$dumpvars
b0 .
b0 -
b0 (
b0 '
b0 &
0%
b0 $
b0 #
b0 "
0!
$end
#3
1!
b10010 "
b10010 .
b1 &
b1 (
1%
#4
0!
b0 "
b0 .
0%
#7
1!
b100000 "
b100000 .
b10010 #
b10010 -
b10 &
b10 (
1%
#8
0!
b0 "
b0 .
b0 #
b0 -
0%
#11
1!
b100 "
b100 .
b110010 #
b110010 -
b101 &
b101 (
1%
#12
0!
b0 "
b0 .
b0 #
b0 -
0%
#15
1!
b10000 "
b10000 .
b110110 #
b110110 -
b1 $
b1 '
1%
#16
0!
b0 "
b0 .
b0 #
b0 -
0%
#19
1!
b10000 "
b10000 .
b1000110 #
b1000110 -
b10 $
b10 '
1%
#20
0!
b0 "
b0 .
b0 #
b0 -
0%
#23
1!
b1110 "
b1110 .
b1010110 #
b1010110 -
b11 $
b11 '
1%
#24
0!
b0 "
b0 .
b0 #
b0 -
0%
