CONTROL/ep0_buffer.v
module ep0_buffer(
    input wire ep0b_clk_i,
    input wire ep0b_reset,
    input wire ep0b_clear,
    input wire ep0b_en,  //Enable for the EP0 buffer
    input wire ep0b_packet_commit_i,
    input wire [7:0]ep0b_wr_byte_i,
    input wire ep0b_wr_en_i,
    input wire ep0b_rd_en_i,
    input wire [7:0]ep0b_rd_addr_i,

    output reg [7:0]ep0b_rd_byte_o,
    output reg ep0b_empty_o,
    output reg ep0b_packet_valid_o,
    output reg [7:0]ep0b_packet_length_o
);
    reg [7:0] ep0_mem[63:0];
    reg [7:0]wr_ptr;
    always @(posedge ep0b_clk_i or posedge ep0b_reset)begin
        if(ep0b_reset)begin
            wr_ptr<=8'b0;
            ep0b_empty_o<=1'b1;
            ep0b_rd_byte_o<=8'bx;
            ep0b_packet_length_o<=8'b0;
            ep0b_packet_valid_o<=1'b0;
        end
        else if(ep0b_clear)begin
            wr_ptr<=8'b0;
            ep0b_empty_o<=1'b1;
            ep0b_rd_byte_o<=8'bx;
            ep0b_packet_length_o<=8'b0;
            ep0b_packet_valid_o<=1'b0;
        end
        else if(ep0b_en) begin
            if(ep0b_rd_en_i)begin  //Both conditions can never be satisfied simultaneously
                ep0b_rd_byte_o<=ep0_mem[ep0b_rd_addr_i];
            end
            if(ep0b_wr_en_i)begin  //So, just if statements are used.
                ep0_mem[wr_ptr]<=ep0b_wr_byte_i;
                wr_ptr<=wr_ptr+1;
                ep0b_empty_o<=1'b0;
            end
            if(ep0b_packet_commit_i)begin
                ep0b_packet_valid_o<=1'b1;
                ep0b_packet_length_o<=wr_ptr;
            end
        end
    end
endmodule

TB/CONTROL/ep0_buffer_tb.v
`timescale 1 ns / 1 ns;
module ep0_buffer_tb;
    reg ep0b_clk_i;
    reg ep0b_reset;
    reg ep0b_clear;
    reg ep0b_en;  //Enable for the EP0 buffer
    reg ep0b_packet_commit_i;
    reg [7:0]ep0b_wr_byte_i;
    reg ep0b_wr_en_i;
    reg ep0b_rd_en_i;
    reg [7:0]ep0b_rd_addr_i;
    wire [7:0]ep0b_rd_byte_o;
    wire ep0b_empty_o;
    wire ep0b_packet_valid_o;
    wire [7:0]ep0b_packet_length_o;
    
    ep0_buffer ep0b_1(
        .ep0b_clk_i(ep0b_clk_i),
        .ep0b_reset(ep0b_reset),
        .ep0b_clear(ep0b_clear),
        .ep0b_en(ep0b_en),  
        .ep0b_packet_commit_i(ep0b_packet_commit_i),
        .ep0b_wr_byte_i(ep0b_wr_byte_i),
        .ep0b_wr_en_i(ep0b_wr_en_i),
        .ep0b_rd_en_i(ep0b_rd_en_i),
        .ep0b_rd_addr_i(ep0b_rd_addr_i),
        .ep0b_rd_byte_o(ep0b_rd_byte_o),
        .ep0b_empty_o(ep0b_empty_o),
        .ep0b_packet_valid_o(ep0b_packet_valid_o),
        .ep0b_packet_length_o(ep0b_packet_length_o)
    );

    initial begin
        $dumpfile("TB/CONTROL/DUMP/ep0_buffer.vcd");
        $dumpvars(0,ep0_buffer_tb);
        $display("|Time|Clk|Reset|Clear|EP_en|Wr_en|Wr_ptr|Wr_Byte |Commit|Valid|Size|Empty|Rd_en|Rd_addr|Rd_Byte |");
    end

    always @(posedge ep0b_clk_i)begin
        $display("|%4t| %b |  %b  |  %b  |  %b  |  %b  |  %2d  |%8b|  %b   |  %b  | %2d |  %b  |  %b  |  %2d   |%8b|",$time,ep0b_clk_i,ep0b_reset,ep0b_clear,ep0b_en,ep0b_wr_en_i,ep0b_1.wr_ptr,ep0b_wr_byte_i,ep0b_packet_commit_i,ep0b_packet_valid_o,ep0b_packet_length_o,ep0b_empty_o,ep0b_rd_en_i,ep0b_rd_addr_i,ep0b_rd_byte_o);
    end

    initial begin
        ep0b_clk_i=1'b1;
        ep0b_reset=1'b1;
        ep0b_clear=1'b0;
        ep0b_en=1'b0;
        ep0b_packet_commit_i=1'b0;
        ep0b_wr_byte_i=8'bx;
        ep0b_wr_en_i=1'b0;
        ep0b_rd_en_i=1'b0;
        ep0b_rd_addr_i=8'bx;
    end

    always begin
        #1 ep0b_clk_i=~ep0b_clk_i;
    end

    initial begin
        #2 ep0b_reset=1'b0;
        #4 ep0b_en=1'b1; 
        
        #6 ep0b_wr_en_i=1'b1;  //Idle for few cycles after enabled
           ep0b_wr_byte_i=8'b0000_0001;  // Writing 8 bytes into the buffer
        #2 ep0b_wr_byte_i=8'b0000_0011;
        #2 ep0b_wr_byte_i=8'b0000_0111;
        #2 ep0b_wr_byte_i=8'b0000_1111;
        #2 ep0b_wr_byte_i=8'b0001_1111;
        #2 ep0b_wr_byte_i=8'b0011_1111;
        #2 ep0b_wr_byte_i=8'b0111_1111;
        #2 ep0b_wr_byte_i=8'b1111_1111;
        #2 ep0b_wr_en_i=1'b0;
           ep0b_wr_byte_i=8'bx; //waiting before getting commit signal
        
        #6 ep0b_packet_commit_i=1'b1; //commit
        #2 ep0b_packet_commit_i=1'b0;

        #6 ep0b_rd_en_i=1'b1;  //Read the 8 bytes from the buffer
            ep0b_rd_addr_i=8'd0;
        #2  ep0b_rd_addr_i=8'd1;
        #2  ep0b_rd_addr_i=8'd2;
        #2  ep0b_rd_addr_i=8'd3;
        #2  ep0b_rd_addr_i=8'd4;
        #2  ep0b_rd_addr_i=8'd5;
        #2  ep0b_rd_addr_i=8'd6;
        #2  ep0b_rd_addr_i=8'd7;
        #2  ep0b_rd_en_i=1'b0;
        ep0b_rd_addr_i=8'dx;  
                                //Waiting before clear arrives from the transaction engine
        #4 ep0b_clear=1'b1; //clear signal from transaction engine
        #2 ep0b_clear=1'b0;
                            //Waiting some time before finishing        
        #5 $finish;
    end
endmodule

TB/CONTROL/DUMP/ep0_buffer.vcd
$date
	Thu Jul 23 19:14:23 2026
$end
$version
	Icarus Verilog
$end
$timescale
	1ns
$end
$scope module ep0_buffer_tb $end
$var wire 8 ! ep0b_rd_byte_o [7:0] $end
$var wire 1 " ep0b_packet_valid_o $end
$var wire 8 # ep0b_packet_length_o [7:0] $end
$var wire 1 $ ep0b_empty_o $end
$var reg 1 % ep0b_clear $end
$var reg 1 & ep0b_clk_i $end
$var reg 1 ' ep0b_en $end
$var reg 1 ( ep0b_packet_commit_i $end
$var reg 8 ) ep0b_rd_addr_i [7:0] $end
$var reg 1 * ep0b_rd_en_i $end
$var reg 1 + ep0b_reset $end
$var reg 8 , ep0b_wr_byte_i [7:0] $end
$var reg 1 - ep0b_wr_en_i $end
$scope module ep0b_1 $end
$var wire 1 % ep0b_clear $end
$var wire 1 & ep0b_clk_i $end
$var wire 1 ' ep0b_en $end
$var wire 1 ( ep0b_packet_commit_i $end
$var wire 8 . ep0b_rd_addr_i [7:0] $end
$var wire 1 * ep0b_rd_en_i $end
$var wire 1 + ep0b_reset $end
$var wire 8 / ep0b_wr_byte_i [7:0] $end
$var wire 1 - ep0b_wr_en_i $end
$var reg 1 $ ep0b_empty_o $end
$var reg 8 0 ep0b_packet_length_o [7:0] $end
$var reg 1 " ep0b_packet_valid_o $end
$var reg 8 1 ep0b_rd_byte_o [7:0] $end
$var reg 8 2 wr_ptr [7:0] $end
$upscope $end
$upscope $end
$enddefinitions $end
$comment Show the parameter values. $end
$dumpall
$end
#0
$dumpvars
b0 2
bx 1
b0 0
bx /
bx .
0-
bx ,
1+
0*
bx )
0(
0'
1&
0%
1$
b0 #
0"
bx !
$end
#1
0&
#2
1&
0+
#3
0&
#4
1&
#5
0&
#6
1&
1'
#7
0&
#8
1&
#9
0&
#10
1&
#11
0&
#12
0$
b1 2
1&
b1 ,
b1 /
1-
#13
0&
#14
b10 2
1&
b11 ,
b11 /
#15
0&
#16
b11 2
1&
b111 ,
b111 /
#17
0&
#18
b100 2
1&
b1111 ,
b1111 /
#19
0&
#20
b101 2
1&
b11111 ,
b11111 /
#21
0&
#22
b110 2
1&
b111111 ,
b111111 /
#23
0&
#24
b111 2
1&
b1111111 ,
b1111111 /
#25
0&
#26
b1000 2
1&
b11111111 ,
b11111111 /
#27
0&
#28
1&
bx ,
bx /
0-
#29
0&
#30
1&
#31
0&
#32
1&
#33
0&
#34
b1000 #
b1000 0
1"
1&
1(
#35
0&
#36
1&
0(
#37
0&
#38
1&
#39
0&
#40
1&
#41
0&
#42
b1 !
b1 1
1&
b0 )
b0 .
1*
#43
0&
#44
b11 !
b11 1
1&
b1 )
b1 .
#45
0&
#46
b111 !
b111 1
1&
b10 )
b10 .
#47
0&
#48
b1111 !
b1111 1
1&
b11 )
b11 .
#49
0&
#50
b11111 !
b11111 1
1&
b100 )
b100 .
#51
0&
#52
b111111 !
b111111 1
1&
b101 )
b101 .
#53
0&
#54
b1111111 !
b1111111 1
1&
b110 )
b110 .
#55
0&
#56
b11111111 !
b11111111 1
1&
b111 )
b111 .
#57
0&
#58
1&
bx )
bx .
0*
#59
0&
#60
1&
#61
0&
#62
0"
b0 #
b0 0
bx !
bx 1
1$
b0 2
1&
1%
#63
0&
#64
1&
0%
