MEMORY/descriptor_rom.v
module descriptor_rom(
    input wire [7:0]dr_rd_addr_i,
    output wire [7:0]dr_rd_byte_o,
    output wire dr_byte_valid_o
);
    
    always @(*)begin
        case(dr_rd_addr_i)
            //Device Descriptor
            8'h00 : dr_rd_byte_o = 8'h12;  //bLength
            8'h01 : dr_rd_byte_o = 8'h01;  //bDescriptorType
            8'h02 : dr_rd_byte_o = 8'h00;  //bcdUSB
            8'h03 : dr_rd_byte_o = 8'h02;
            8'h04 : dr_rd_byte_o = 8'h00;  //bDeviceClass
            8'h05 : dr_rd_byte_o = 8'h00;  //bDeviceSubClass
            8'h06 : dr_rd_byte_o = 8'h00;  //bDeviceProtocol
            8'h07 : dr_rd_byte_o = 8'h04;  //bMaxPacketSize0
            8'h08 : dr_rd_byte_o = 8'h34;  //idVendor
            8'h09 : dr_rd_byte_o = 8'h12;
            8'h0A : dr_rd_byte_o = 8'h01;  //idProduct
            8'h0B : dr_rd_byte_o = 8'h00;
            8'h0C : dr_rd_byte_o = 8'h00;  //bcdDevice
            8'h0D : dr_rd_byte_o = 8'h01;
            8'h0E : dr_rd_byte_o = 8'h01;  //iManufacturer
            8'h0F : dr_rd_byte_o = 8'h02;  //iProduct
            8'h10 : dr_rd_byte_o = 8'h03;  //iSerialNumber
            8'h11 : dr_rd_byte_o = 8'h01;  //bNumConfigurations
            
            //Configuration Descriptor
            8'h12 : dr_rd_byte_o = 8'h09;   //bLength
            8'h13 : dr_rd_byte_o = 8'h02;   //bDescriptorType
            8'h14 : dr_rd_byte_o = 8'h20;   //wTotalLength
            8'h15 : dr_rd_byte_o = 8'h00;
            8'h16 : dr_rd_byte_o = 8'h01;   //bNumInterfaces
            8'h17 : dr_rd_byte_o = 8'h01;   //bConfigurationValue
            8'h18 : dr_rd_byte_o = 8'h00;   //iConfiguration
            8'h19 : dr_rd_byte_o = 8'h80;   //bmAttributes
            8'h1A : dr_rd_byte_o = 8'h32;   //bMaxPower

            //Interface Descriptor
            8'h1B : dr_rd_byte_o = 8'h09;   //bLength
            8'h1C : dr_rd_byte_o = 8'h04;   //bDescriptorType
            8'h1D : dr_rd_byte_o = 8'h00;   //bInterfaceNumber
            8'h1E : dr_rd_byte_o = 8'h00;   //bAlternateSetting
            8'h1F : dr_rd_byte_o = 8'h02;   //bNumEndpoints
            8'h20 : dr_rd_byte_o = 8'h03;   //bInterfaceClass
            8'h21 : dr_rd_byte_o = 8'h01;   //bInterfaceSubClass
            8'h22 : dr_rd_byte_o = 8'h01;   //bInterfaceProtocol
            8'h23 : dr_rd_byte_o = 8'h00;   //iInterface
            
            //Endpoint EP1 OUT Descriptor
            8'h24 : dr_rd_byte_o = 8'h07;  // bLength
            8'h25 : dr_rd_byte_o = 8'h05;  // bDescriptorType (Endpoint)
            8'h26 : dr_rd_byte_o = 8'h01;  // bEndpointAddress (EP1 OUT)
            8'h27 : dr_rd_byte_o = 8'h02;  // bmAttributes (Bulk)
            8'h28 : dr_rd_byte_o = 8'h00;  // wMaxPacketSize (LSB)
            8'h29 : dr_rd_byte_o = 8'h02;  // wMaxPacketSize (MSB) = 512 Bytes
            8'h2A : dr_rd_byte_o = 8'h00;  // bInterval

            //Endpoint EP1 IN Descriptor
            8'h2B : dr_rd_byte_o = 8'h07;  // bLength
            8'h2C : dr_rd_byte_o = 8'h05;  // bDescriptorType (Endpoint)
            8'h2D : dr_rd_byte_o = 8'h81;  // bEndpointAddress (EP1 IN)
            8'h2E : dr_rd_byte_o = 8'h02;  // bmAttributes (Bulk)
            8'h2F : dr_rd_byte_o = 8'h00;  // wMaxPacketSize (LSB)
            8'h30 : dr_rd_byte_o = 8'h02;  // wMaxPacketSize (MSB) = 512 Bytes
            8'h31 : dr_rd_byte_o = 8'h00;  // bInterval

            //String Descriptor 0 (Language ID)
            8'h32 : dr_rd_byte_o = 8'h04;  // bLength
            8'h33 : dr_rd_byte_o = 8'h03;  // bDescriptorType (String)
            8'h34 : dr_rd_byte_o = 8'h09;  // LANGID LSB
            8'h35 : dr_rd_byte_o = 8'h04;  // LANGID MSB (0x0409 = English-US)

                //For String Descriptors, these are the current values (dummy)
                //Manufacturer : "Brighty"
                //Product : "USB KSI"
                //Serial Number : "000001"
                
            // String Descriptor 1 ("Brighty")
            8'h36 : dr_rd_byte_o = 8'h10;   // bLength
            8'h37 : dr_rd_byte_o = 8'h03;   // bDescriptorType
            8'h38 : dr_rd_byte_o = 8'h42;   // B
            8'h39 : dr_rd_byte_o = 8'h00;
            8'h3A : dr_rd_byte_o = 8'h72;   // r
            8'h3B : dr_rd_byte_o = 8'h00;
            8'h3C : dr_rd_byte_o = 8'h69;   // i
            8'h3D : dr_rd_byte_o = 8'h00;
            8'h3E : dr_rd_byte_o = 8'h67;   // g
            8'h3F : dr_rd_byte_o = 8'h00;
            8'h40 : dr_rd_byte_o = 8'h68;   // h
            8'h41 : dr_rd_byte_o = 8'h00;
            8'h42 : dr_rd_byte_o = 8'h74;   // t
            8'h43 : dr_rd_byte_o = 8'h00;
            8'h44 : dr_rd_byte_o = 8'h79;   // y
            8'h45 : dr_rd_byte_o = 8'h00;

            // String Descriptor 2 ("USB KSI")
            8'h46 : dr_rd_byte_o = 8'h10;
            8'h47 : dr_rd_byte_o = 8'h03;
            8'h48 : dr_rd_byte_o = 8'h55;   // U
            8'h49 : dr_rd_byte_o = 8'h00;
            8'h4A : dr_rd_byte_o = 8'h53;   // S
            8'h4B : dr_rd_byte_o = 8'h00;
            8'h4C : dr_rd_byte_o = 8'h42;   // B
            8'h4D : dr_rd_byte_o = 8'h00;
            8'h4E : dr_rd_byte_o = 8'h20;   // Space
            8'h4F : dr_rd_byte_o = 8'h00;
            8'h50 : dr_rd_byte_o = 8'h4B;   // K
            8'h51 : dr_rd_byte_o = 8'h00;
            8'h52 : dr_rd_byte_o = 8'h53;   // S
            8'h53 : dr_rd_byte_o = 8'h00;
            8'h54 : dr_rd_byte_o = 8'h49;   // I
            8'h55 : dr_rd_byte_o = 8'h00;

            // String Descriptor 3 ("000001")
            8'h56 : dr_rd_byte_o = 8'h0E;
            8'h57 : dr_rd_byte_o = 8'h03;
            8'h58 : dr_rd_byte_o = 8'h30;   // 0
            8'h59 : dr_rd_byte_o = 8'h00;
            8'h5A : dr_rd_byte_o = 8'h30;   // 0
            8'h5B : dr_rd_byte_o = 8'h00;
            8'h5C : dr_rd_byte_o = 8'h30;   // 0
            8'h5D : dr_rd_byte_o = 8'h00;
            8'h5E : dr_rd_byte_o = 8'h30;   // 0
            8'h5F : dr_rd_byte_o = 8'h00;
            8'h60 : dr_rd_byte_o = 8'h30;   // 0
            8'h61 : dr_rd_byte_o = 8'h00;
            8'h62 : dr_rd_byte_o = 8'h31;   // 1
            8'h63 : dr_rd_byte_o = 8'h00;
        endcase
    end
endmodule

TB/MEMORY/descriptor_rom_tb.v
module descriptor_rom_tb;
    reg [7:0]dr_rd_addr_i;
    wire [7:0]dr_rd_byte_o;

    descriptor_rom dr_1(
        .dr_rd_addr_i(dr_rd_addr_i),
        .dr_rd_byte_o(dr_rd_byte_o)
    );

    initial begin
        $dumpfile("TB/MEMORY/DUMP/descriptor_rom.vcd");
        $dumpvars(0,descriptor_rom_tb);
        $display("|Time|Input_Address|MEMORY|");
        for(dr_rd_addr_i=8'h00;dr_rd_addr_i<=8'h63;dr_rd_addr_i=dr_rd_addr_i+1) begin
            #2 $display("|%4t|    %2s%2h     |  %2h  |",$time,"0x",dr_rd_addr_i,dr_rd_byte_o);
        end
        $finish;
    end
endmodule

TB/MEMORY/DUMP/descriptor_rom.vcd
$date
	Tue Jul 28 18:19:15 2026
$end
$version
	Icarus Verilog
$end
$timescale
	1s
$end
$scope module descriptor_rom_tb $end
$var wire 8 ! dr_rd_byte_o [7:0] $end
$var reg 8 " dr_rd_addr_i [7:0] $end
$scope module dr_1 $end
$var wire 8 # dr_rd_addr_i [7:0] $end
$var reg 8 $ dr_rd_byte_o [7:0] $end
$upscope $end
$upscope $end
$enddefinitions $end
$comment Show the parameter values. $end
$dumpall
$end
#0
$dumpvars
b10010 $
b0 #
b0 "
b10010 !
$end
#2
b1 !
b1 $
b1 "
b1 #
#4
b0 !
b0 $
b10 "
b10 #
#6
b10 !
b10 $
b11 "
b11 #
#8
b0 !
b0 $
b100 "
b100 #
#10
b101 "
b101 #
#12
b110 "
b110 #
#14
b100 !
b100 $
b111 "
b111 #
#16
b110100 !
b110100 $
b1000 "
b1000 #
#18
b10010 !
b10010 $
b1001 "
b1001 #
#20
b1 !
b1 $
b1010 "
b1010 #
#22
b0 !
b0 $
b1011 "
b1011 #
#24
b1100 "
b1100 #
#26
b1 !
b1 $
b1101 "
b1101 #
#28
b1110 "
b1110 #
#30
b10 !
b10 $
b1111 "
b1111 #
#32
b11 !
b11 $
b10000 "
b10000 #
#34
b1 !
b1 $
b10001 "
b10001 #
#36
b1001 !
b1001 $
b10010 "
b10010 #
#38
b10 !
b10 $
b10011 "
b10011 #
#40
b100000 !
b100000 $
b10100 "
b10100 #
#42
b0 !
b0 $
b10101 "
b10101 #
#44
b1 !
b1 $
b10110 "
b10110 #
#46
b10111 "
b10111 #
#48
b0 !
b0 $
b11000 "
b11000 #
#50
b10000000 !
b10000000 $
b11001 "
b11001 #
#52
b110010 !
b110010 $
b11010 "
b11010 #
#54
b1001 !
b1001 $
b11011 "
b11011 #
#56
b100 !
b100 $
b11100 "
b11100 #
#58
b0 !
b0 $
b11101 "
b11101 #
#60
b11110 "
b11110 #
#62
b10 !
b10 $
b11111 "
b11111 #
#64
b11 !
b11 $
b100000 "
b100000 #
#66
b1 !
b1 $
b100001 "
b100001 #
#68
b100010 "
b100010 #
#70
b0 !
b0 $
b100011 "
b100011 #
#72
b111 !
b111 $
b100100 "
b100100 #
#74
b101 !
b101 $
b100101 "
b100101 #
#76
b1 !
b1 $
b100110 "
b100110 #
#78
b10 !
b10 $
b100111 "
b100111 #
#80
b0 !
b0 $
b101000 "
b101000 #
#82
b10 !
b10 $
b101001 "
b101001 #
#84
b0 !
b0 $
b101010 "
b101010 #
#86
b111 !
b111 $
b101011 "
b101011 #
#88
b101 !
b101 $
b101100 "
b101100 #
#90
b10000001 !
b10000001 $
b101101 "
b101101 #
#92
b10 !
b10 $
b101110 "
b101110 #
#94
b0 !
b0 $
b101111 "
b101111 #
#96
b10 !
b10 $
b110000 "
b110000 #
#98
b0 !
b0 $
b110001 "
b110001 #
#100
b100 !
b100 $
b110010 "
b110010 #
#102
b11 !
b11 $
b110011 "
b110011 #
#104
b1001 !
b1001 $
b110100 "
b110100 #
#106
b100 !
b100 $
b110101 "
b110101 #
#108
b10000 !
b10000 $
b110110 "
b110110 #
#110
b11 !
b11 $
b110111 "
b110111 #
#112
b1000010 !
b1000010 $
b111000 "
b111000 #
#114
b0 !
b0 $
b111001 "
b111001 #
#116
b1110010 !
b1110010 $
b111010 "
b111010 #
#118
b0 !
b0 $
b111011 "
b111011 #
#120
b1101001 !
b1101001 $
b111100 "
b111100 #
#122
b0 !
b0 $
b111101 "
b111101 #
#124
b1100111 !
b1100111 $
b111110 "
b111110 #
#126
b0 !
b0 $
b111111 "
b111111 #
#128
b1101000 !
b1101000 $
b1000000 "
b1000000 #
#130
b0 !
b0 $
b1000001 "
b1000001 #
#132
b1110100 !
b1110100 $
b1000010 "
b1000010 #
#134
b0 !
b0 $
b1000011 "
b1000011 #
#136
b1111001 !
b1111001 $
b1000100 "
b1000100 #
#138
b0 !
b0 $
b1000101 "
b1000101 #
#140
b10000 !
b10000 $
b1000110 "
b1000110 #
#142
b11 !
b11 $
b1000111 "
b1000111 #
#144
b1010101 !
b1010101 $
b1001000 "
b1001000 #
#146
b0 !
b0 $
b1001001 "
b1001001 #
#148
b1010011 !
b1010011 $
b1001010 "
b1001010 #
#150
b0 !
b0 $
b1001011 "
b1001011 #
#152
b1000010 !
b1000010 $
b1001100 "
b1001100 #
#154
b0 !
b0 $
b1001101 "
b1001101 #
#156
b100000 !
b100000 $
b1001110 "
b1001110 #
#158
b0 !
b0 $
b1001111 "
b1001111 #
#160
b1001011 !
b1001011 $
b1010000 "
b1010000 #
#162
b0 !
b0 $
b1010001 "
b1010001 #
#164
b1010011 !
b1010011 $
b1010010 "
b1010010 #
#166
b0 !
b0 $
b1010011 "
b1010011 #
#168
b1001001 !
b1001001 $
b1010100 "
b1010100 #
#170
b0 !
b0 $
b1010101 "
b1010101 #
#172
b1110 !
b1110 $
b1010110 "
b1010110 #
#174
b11 !
b11 $
b1010111 "
b1010111 #
#176
b110000 !
b110000 $
b1011000 "
b1011000 #
#178
b0 !
b0 $
b1011001 "
b1011001 #
#180
b110000 !
b110000 $
b1011010 "
b1011010 #
#182
b0 !
b0 $
b1011011 "
b1011011 #
#184
b110000 !
b110000 $
b1011100 "
b1011100 #
#186
b0 !
b0 $
b1011101 "
b1011101 #
#188
b110000 !
b110000 $
b1011110 "
b1011110 #
#190
b0 !
b0 $
b1011111 "
b1011111 #
#192
b110000 !
b110000 $
b1100000 "
b1100000 #
#194
b0 !
b0 $
b1100001 "
b1100001 #
#196
b110001 !
b110001 $
b1100010 "
b1100010 #
#198
b0 !
b0 $
b1100011 "
b1100011 #
#200
b1100100 "
b1100100 #
