PHY_RX/bit_unstuffer.v
module bit_unstuffer(
	input wire bu_clk_i,
	input wire bu_reset,
	input wire bu_sbit_i,
	input wire bu_valid_bit_i, //input taken from the output of nrzi decoder -> nd_invalid_o
	output reg bu_unstuff_o,
	output reg bu_error_o
);
	
	reg [2:0]bu_count;
	
	always@(posedge bu_clk_i or posedge bu_reset) begin
		if(bu_reset) begin
			bu_unstuff_o <= 1'b0;
			bu_count <= 3'd0;
			bu_error_o<=1'b0;
		end
		else begin
			bu_unstuff_o<= 1'b0;
			bu_error_o<=1'b0;
			if(bu_valid_bit_i==1'b0) begin //input is negative logic so, valid is set to 0
				if(bu_sbit_i==1'b1) begin 
					if(bu_count<3'd6)begin
						bu_count <= bu_count+1;
					end
					else begin
						bu_error_o<=1'b1;
						bu_count<= 3'd0;
					end
				end
				else begin
					if(bu_count==3'd6)begin
						bu_unstuff_o<=1'b1;
					end
					bu_count<=3'b0;
				end
			end
			else begin
				bu_count<=3'b0;
			end	
		end
	end

endmodule

TB/bit_unstuffer_tb.v
module bit_unstuffer_tb;
    
    reg bu_clk_i;
    reg bu_reset;
    reg bu_sbit_i;
    reg bu_valid_bit_i;
    wire bu_unstuff_o;
    wire bu_error_o;

    bit_unstuffer bu_1(
        .bu_clk_i(bu_clk_i),
        .bu_reset(bu_reset),
        .bu_sbit_i(bu_sbit_i),
        .bu_valid_bit_i(bu_valid_bit_i), 
        .bu_unstuff_o(bu_unstuff_o),
        .bu_error_o(bu_error_o)
    );

    initial begin
        $dumpfile("TB/bit_unstuffer.vcd");
        $dumpvars(0,bit_unstuffer_tb);
        $display("|Time|Clk|Reset|Valid|Input|Count|Unstuff|Error|");
    end

    always@(posedge bu_clk_i)begin
        $display("|%3t | %b |  %b  |  %b  |  %b  |  %d  |   %b   |  %b  |",$time,bu_clk_i,bu_reset,~bu_valid_bit_i,bu_sbit_i,bu_1.bu_count,bu_unstuff_o,bu_error_o);
    end

    initial begin
        bu_clk_i=1'b1;
        bu_reset=1'b1;
        bu_sbit_i=1'b0;
        bu_valid_bit_i=1'b0;
    end

    always begin
        #1 bu_clk_i =~ bu_clk_i;
    end

    initial begin
        #2 bu_reset=1'b0;
           bu_sbit_i=1'b1;
        #12 bu_sbit_i=1'b0;
        bu_sbit_i=1'b1;
        #12 bu_sbit_i=1'b0;
        #4 bu_valid_bit_i=1'b1;
        #2 bu_valid_bit_i=1'b0;
        bu_sbit_i=1'b1;
        #12 bu_sbit_i=1'b0; 
        #9 $finish;
    end

endmodule

TB/bit_unstuffer.vcd
$date
	Thu Jun  4 11:35:55 2026
$end
$version
	Icarus Verilog
$end
$timescale
	1s
$end
$scope module bit_unstuffer_tb $end
$var wire 1 ! bu_unstuff_o $end
$var wire 1 " bu_error_o $end
$var reg 1 # bu_clk_i $end
$var reg 1 $ bu_reset $end
$var reg 1 % bu_sbit_i $end
$var reg 1 & bu_valid_bit_i $end
$scope module bu_1 $end
$var wire 1 # bu_clk_i $end
$var wire 1 $ bu_reset $end
$var wire 1 % bu_sbit_i $end
$var wire 1 & bu_valid_bit_i $end
$var reg 3 ' bu_count [2:0] $end
$var reg 1 " bu_error_o $end
$var reg 1 ! bu_unstuff_o $end
$upscope $end
$upscope $end
$enddefinitions $end
$comment Show the parameter values. $end
$dumpall
$end
#0
$dumpvars
b0 '
0&
0%
1$
1#
0"
0!
$end
#1
0#
#2
b1 '
1#
1%
0$
#3
0#
#4
b10 '
1#
#5
0#
#6
b11 '
1#
#7
0#
#8
b100 '
1#
#9
0#
#10
b101 '
1#
#11
0#
#12
b110 '
1#
#13
0#
#14
b0 '
1"
1#
1%
#15
0#
#16
b1 '
0"
1#
#17
0#
#18
b10 '
1#
#19
0#
#20
b11 '
1#
#21
0#
#22
b100 '
1#
#23
0#
#24
b101 '
1#
#25
0#
#26
b0 '
1#
0%
#27
0#
#28
1#
#29
0#
#30
1#
1&
#31
0#
#32
b1 '
1#
1%
0&
#33
0#
#34
b10 '
1#
#35
0#
#36
b11 '
1#
#37
0#
#38
b100 '
1#
#39
0#
#40
b101 '
1#
#41
0#
#42
b110 '
1#
#43
0#
#44
b0 '
1!
1#
0%
#45
0#
#46
0!
1#
