USB_PHY/nrzi_decoder.v
module nrzi_decoder(
	input wire nd_clk_i,
	input wire nd_dplus_i,
	input wire nd_dminus_i,
	input wire nd_reset,
	output reg nd_sbit_o,
	output reg nd_invalid_o
);
	reg [1:0]nd_prev; // [1:0] -> dp,dm
	
	always@(posedge nd_clk_i or posedge nd_reset)begin
		if(nd_reset) begin
			nd_prev <= 2'b0;
			nd_sbit_o <= 1'b0;
			nd_invalid_o<=1'b1;
		end
		else begin
			nd_prev<={nd_dplus_i,nd_dminus_i};
			if(((nd_dplus_i^nd_dminus_i)==1'b1) && ((nd_prev[1]^nd_prev[0])==1'b1)) begin
				nd_invalid_o<=1'b0;
				if({nd_dplus_i,nd_dminus_i}==nd_prev)begin
					nd_sbit_o<=1'b1;
				end
				else 
					nd_sbit_o<=1'b0;
			end
			else nd_invalid_o<=1'b1;
		end
	end
endmodule

TB/PHY/nrzi_decoder_tb.v
`timescale 1 ns / 1 ns;
module nrzi_decoder_tb;
    
    reg nd_clk_i;
    reg nd_dplus_i;
    reg nd_dminus_i;
    reg nd_reset;
    wire nd_sbit_o;
    wire nd_invalid_o;

    nrzi_decoder nd_1(
        .nd_clk_i(nd_clk_i),
        .nd_dplus_i(nd_dplus_i),
        .nd_dminus_i(nd_dminus_i),
        .nd_reset(nd_reset),
        .nd_sbit_o(nd_sbit_o),
        .nd_invalid_o(nd_invalid_o)
    );

    initial begin
     $dumpfile("TB/nrzi_decoder.vcd");
     $dumpvars(0,nrzi_decoder_tb);
     $display("|Time|Clock|reset|Previous|Dplus,Dminus|Bit|Invalid|");
    end
    always@(posedge nd_clk_i)begin
        $display("|%3t |  %b  |  %b  |   %2b   |     %2b     | %b |   %b   |",$time,nd_clk_i,nd_reset,nd_1.nd_prev,{nd_dplus_i,nd_dminus_i},nd_sbit_o,nd_invalid_o);
    end
    
    initial begin
        nd_clk_i=1'b1;
        nd_dplus_i=1'b0;
        nd_dminus_i=1'b0;
        nd_reset=1'b1;
    end
    always begin
        #1 nd_clk_i=~nd_clk_i;
    end

    initial begin
        #2 nd_reset=1'b0;
        #2 {nd_dplus_i,nd_dminus_i}=2'b00;
        #8 {nd_dplus_i,nd_dminus_i}=2'b01;
        #2 {nd_dplus_i,nd_dminus_i}=2'b10;
        #2 {nd_dplus_i,nd_dminus_i}=2'b01;
        #2 {nd_dplus_i,nd_dminus_i}=2'b10;
        #2 {nd_dplus_i,nd_dminus_i}=2'b01;
        #2 {nd_dplus_i,nd_dminus_i}=2'b10;
        #10 {nd_dplus_i,nd_dminus_i}=2'b00;
        #2 {nd_dplus_i,nd_dminus_i}=2'b10;
        #2 {nd_dplus_i,nd_dminus_i}=2'b01;
        #2 {nd_dplus_i,nd_dminus_i}=2'b10;
        #5 $finish;
    end

endmodule

TB/nrzi_decoder.vcd
$date
	Thu Jun  4 07:35:56 2026
$end
$version
	Icarus Verilog
$end
$timescale
	1ns
$end
$scope module nrzi_decoder_tb $end
$var wire 1 ! nd_sbit_o $end
$var wire 1 " nd_invalid_o $end
$var reg 1 # nd_clk_i $end
$var reg 1 $ nd_dminus_i $end
$var reg 1 % nd_dplus_i $end
$var reg 1 & nd_reset $end
$scope module nd_1 $end
$var wire 1 # nd_clk_i $end
$var wire 1 $ nd_dminus_i $end
$var wire 1 % nd_dplus_i $end
$var wire 1 & nd_reset $end
$var reg 1 " nd_invalid_o $end
$var reg 2 ' nd_prev [1:0] $end
$var reg 1 ! nd_sbit_o $end
$upscope $end
$upscope $end
$enddefinitions $end
$comment Show the parameter values. $end
$dumpall
$end
#0
$dumpvars
b0 '
1&
0%
0$
1#
1"
0!
$end
#1
0#
#2
1#
0&
#3
0#
#4
1#
#5
0#
#6
1#
#7
0#
#8
1#
#9
0#
#10
1#
#11
0#
#12
b1 '
1#
1$
#13
0#
#14
0"
b10 '
1#
1%
0$
#15
0#
#16
b1 '
1#
0%
1$
#17
0#
#18
b10 '
1#
1%
0$
#19
0#
#20
b1 '
1#
0%
1$
#21
0#
#22
b10 '
1#
1%
0$
#23
0#
#24
1!
1#
#25
0#
#26
1#
#27
0#
#28
1#
#29
0#
#30
1#
#31
0#
#32
1"
b0 '
1#
0%
#33
0#
#34
b10 '
1#
1%
#35
0#
#36
0!
0"
b1 '
1#
0%
1$
#37
0#
#38
b10 '
1#
1%
0$
#39
0#
#40
1!
1#
