USB_PHY/oversampler.v
module oversampler(
	input clk_8x_i,
	input dp_i,
	input dm_i,
	input reset,
	output reg dp_o,
	output reg dm_o
);
	/*reg [2:0]counter;
	reg counter_en;
	reg dp_pa,dm_pa;
	
	initial begin
		counter = 3'd0;
		counter_en = 1'b0;
		dp_o = 1'b0;
		dm_o = 1'b0;
	end*/
	
	always@(posedge clk_8x_i or posedge reset) begin
		if(reset) begin
			//counter<=3'd0;
			//counter_en <= 1'b0;
			dp_o <= 1'b0;
			dm_o <= 1'b0;
			//dp_pa <= 1'b0;
			//dm_pa <= 1'b0;
		end
		else begin
			/*if(dp_pa != dp_i || dm_pa != dm_i) begin
				counter_en <= 1'b1;
				counter <= 3'd1;
			end
		end
		dp_pa <= dp_i;
		dm_pa <= dm_i;
		if(counter_en) begin
			counter <= (counter==3'd7)?3'd0:counter+1;
			if(counter == 3'd4) begin
				dp_o <= dp_i;
				dm_o <= dm_i;
			end
		end*/
		dp_o<=dp_i;
		dm_o<=dm_i;
	end
endmodule

TB/oversampler_tb.v
`timescale 1ps / 1ps;
module oversampler_tb;
reg clk,clk_8x_i;
reg dp_i,dm_i;
reg reset;
wire dp_o,dm_o;

oversampler u_os(
	.clk_8x_i(clk_8x_i),
	.dp_i(dp_i),
	.dm_i(dm_i),
	.reset(reset),
	.dp_o(dp_o),
	.dm_o(dm_o)
);

initial begin
	$dumpfile("TB/oversampler.vcd");
	$dumpvars(0,oversampler_tb);
	$display("time | clk | clk_8x_i | dp_i | dm_i | dp_o | dm_o | reset |");
end

always@(posedge clk_8x_i) begin
	$display(" %3t | %3t |  %3t   |  %b  |  %b  |  %b  |  %b  |   %b  |",$time/125,clk,clk_8x_i,dp_i,dm_i,dp_o,dm_o,reset);
end

initial begin
	clk = 0;
	clk_8x_i = 0;
	reset = 0;
end

always begin
	# 125 clk_8x_i = ~clk_8x_i;
end

always begin
	#1000 clk = ~clk;
end

	initial begin
		#0    {dp_i,dm_i} = 2'b00;
		#200 {dp_i,dm_i} = 2'b10;
		#200 {dp_i,dm_i} = 2'b10;
		#200 {dp_i,dm_i} = 2'b10;
		#200 {dp_i,dm_i} = 2'b10;
		#200 {dp_i,dm_i} = 2'b10;
		#200 {dp_i,dm_i} = 2'b10;
		#200 {dp_i,dm_i} = 2'b10;
		#200 {dp_i,dm_i} = 2'b01;
		#200 {dp_i,dm_i} = 2'b01;
		#200 {dp_i,dm_i} = 2'b10;
		#200 {dp_i,dm_i} = 2'b10;
		#200 {dp_i,dm_i} = 2'b10;
		for(integer i = 0;i<31;i++) begin
			#200 {dp_i,dm_i} = {~dp_i,~dm_i};
		end
		#200  {dp_i,dm_i} = 2'b01;
		#200  {dp_i,dm_i} = 2'b01;
		 #200 $finish;
	end
endmodule

TB/oversampler.vcd
$date
	Sun May 31 17:56:10 2026
$end
$version
	Icarus Verilog
$end
$timescale
	1ps
$end
$scope module oversampler_tb $end
$var wire 1 ! dp_o $end
$var wire 1 " dm_o $end
$var reg 1 # clk $end
$var reg 1 $ clk_8x_i $end
$var reg 1 % dm_i $end
$var reg 1 & dp_i $end
$var reg 1 ' reset $end
$scope module u_os $end
$var wire 1 $ clk_8x_i $end
$var wire 1 % dm_i $end
$var wire 1 & dp_i $end
$var wire 1 ' reset $end
$var reg 1 " dm_o $end
$var reg 1 ! dp_o $end
$upscope $end
$scope begin $ivl_for_loop0 $end
$var integer 32 ( i [31:0] $end
$upscope $end
$upscope $end
$enddefinitions $end
$comment Show the parameter values. $end
$dumpall
$end
#0
$dumpvars
bx (
0'
0&
0%
0$
0#
x"
x!
$end
#125
0"
0!
1$
#200
1&
#250
0$
#375
1!
1$
#500
0$
#625
1$
#750
0$
#875
1$
#1000
0$
1#
#1125
1$
#1250
0$
#1375
1$
#1500
0$
#1600
0&
1%
#1625
1"
0!
1$
#1750
0$
#1875
1$
#2000
0$
1&
0%
0#
#2125
0"
1!
1$
#2250
0$
#2375
1$
#2400
b0 (
#2500
0$
#2600
b1 (
0&
1%
#2625
1"
0!
1$
#2750
0$
#2800
b10 (
1&
0%
#2875
0"
1!
1$
#3000
0$
b11 (
0&
1%
1#
#3125
1"
0!
1$
#3200
b100 (
1&
0%
#3250
0$
#3375
0"
1!
1$
#3400
b101 (
0&
1%
#3500
0$
#3600
b110 (
1&
0%
#3625
1$
#3750
0$
#3800
b111 (
0&
1%
#3875
1"
0!
1$
#4000
0$
b1000 (
1&
0%
0#
#4125
0"
1!
1$
#4200
b1001 (
0&
1%
#4250
0$
#4375
1"
0!
1$
#4400
b1010 (
1&
0%
#4500
0$
#4600
b1011 (
0&
1%
#4625
1$
#4750
0$
#4800
b1100 (
1&
0%
#4875
0"
1!
1$
#5000
0$
b1101 (
0&
1%
1#
#5125
1"
0!
1$
#5200
b1110 (
1&
0%
#5250
0$
#5375
0"
1!
1$
#5400
b1111 (
0&
1%
#5500
0$
#5600
b10000 (
1&
0%
#5625
1$
#5750
0$
#5800
b10001 (
0&
1%
#5875
1"
0!
1$
#6000
0$
b10010 (
1&
0%
0#
#6125
0"
1!
1$
#6200
b10011 (
0&
1%
#6250
0$
#6375
1"
0!
1$
#6400
b10100 (
1&
0%
#6500
0$
#6600
b10101 (
0&
1%
#6625
1$
#6750
0$
#6800
b10110 (
1&
0%
#6875
0"
1!
1$
#7000
0$
b10111 (
0&
1%
1#
#7125
1"
0!
1$
#7200
b11000 (
1&
0%
#7250
0$
#7375
0"
1!
1$
#7400
b11001 (
0&
1%
#7500
0$
#7600
b11010 (
1&
0%
#7625
1$
#7750
0$
#7800
b11011 (
0&
1%
#7875
1"
0!
1$
#8000
0$
b11100 (
1&
0%
0#
#8125
0"
1!
1$
#8200
b11101 (
0&
1%
#8250
0$
#8375
1"
0!
1$
#8400
b11110 (
1&
0%
#8500
0$
#8600
b11111 (
0&
1%
