USB_PHY/resume_detector.v
module resume_detector(
    input wire rumed_ref_clk_i,
    input wire rumed_reset,
    input wire rumed_suspend_state_i,
    input wire rumed_dplus_i,
    input wire rumed_dminus_i,
    output reg rumed_resume_o
);

    localparam SUSPEND=2'b00;
    localparam RESUMING=2'b01;
    
    reg [9:0]rumed_count;
    reg [1:0]STATE;

    always@(posedge rumed_ref_clk_i or posedge rumed_reset)begin
        if(rumed_reset)begin
            rumed_resume_o<=1'b0;
            rumed_count<=10'b0;
            STATE<=SUSPEND;
        end
        else begin
            case(STATE)
                
                SUSPEND : begin
                    rumed_count<=10'b0;
                    rumed_resume_o<=1'b0;
                    if(rumed_suspend_state_i)
                        STATE<=RESUMING;
                end

                RESUMING : begin
                    if({rumed_dplus_i,rumed_dminus_i}==2'b10)begin
                        if(rumed_count==10'd960)begin
                            rumed_resume_o<=1'b1;
                            STATE<=SUSPEND;
                        end
                        else
                            rumed_count<=rumed_count+1;
                    end
                    else
                        rumed_count<=10'b0;
                end
                default : STATE<=SUSPEND;
            endcase
        end
    end

endmodule

TB/PHY/resume_detector_tb.v
`timescale 10 ns / 100 fs;
module resume_detector_tb;
   
    reg rumed_ref_clk_i;
    reg rumed_reset;
    reg rumed_suspend_state_i;
    reg rumed_dplus_i;
    reg rumed_dminus_i;
    wire rumed_resume_o;

    resume_detector rumed_1(
        .rumed_ref_clk_i(rumed_ref_clk_i),
        .rumed_reset(rumed_reset),
        .rumed_suspend_state_i(rumed_suspend_state_i),
        .rumed_dplus_i(rumed_dplus_i),
        .rumed_dminus_i(rumed_dminus_i),
        .rumed_resume_o(rumed_resume_o)
    );

    initial begin
        $dumpfile("TB/resume_detector.vcd");
        $dumpvars(0,resume_detector_tb);
        $display("|   Time  |Clk|Reset|Suspend_State|Dplus,Dminus|Resume|Count|");
    end

    always@(posedge rumed_ref_clk_i) begin
        if(({rumed_dplus_i,rumed_dminus_i}!=2'b10)||((rumed_resume_o)||(rumed_1.rumed_count==10'd960)))
            $display("|%9t| %b |  %b  |      %b      |     %2b     |   %b  |%d |",$time,rumed_ref_clk_i,rumed_reset,rumed_suspend_state_i,{rumed_dplus_i,rumed_dminus_i},rumed_resume_o,rumed_1.rumed_count);
    end

    initial begin
        rumed_ref_clk_i=1'b1;
        rumed_reset=1'b1;
        rumed_suspend_state_i=1'b0;
        {rumed_dplus_i,rumed_dminus_i}=2'b01;
    end

    always begin
        #1.0415 rumed_ref_clk_i=~rumed_ref_clk_i;
    end

    initial begin
        #2 rumed_reset=1'b0;
        #8 rumed_suspend_state_i=1'b1;
        #10 rumed_suspend_state_i=1'b0;
            {rumed_dplus_i,rumed_dminus_i}=2'b10;
        #2002 {rumed_dplus_i,rumed_dminus_i}=2'b01;
        #5 $finish;
    end

endmodule

TB/resume_detector.vcd
$date
	Tue Jun  9 20:11:19 2026
$end
$version
	Icarus Verilog
$end
$timescale
	100fs
$end
$scope module resume_detector_tb $end
$var wire 1 ! rumed_resume_o $end
$var reg 1 " rumed_dminus_i $end
$var reg 1 # rumed_dplus_i $end
$var reg 1 $ rumed_ref_clk_i $end
$var reg 1 % rumed_reset $end
$var reg 1 & rumed_suspend_state_i $end
$scope module rumed_1 $end
$var wire 1 " rumed_dminus_i $end
$var wire 1 # rumed_dplus_i $end
$var wire 1 $ rumed_ref_clk_i $end
$var wire 1 % rumed_reset $end
$var wire 1 & rumed_suspend_state_i $end
$var parameter 2 ' RESUMING $end
$var parameter 2 ( SUSPEND $end
$var reg 2 ) STATE [1:0] $end
$var reg 10 * rumed_count [9:0] $end
$var reg 1 ! rumed_resume_o $end
$upscope $end
$upscope $end
$enddefinitions $end
$comment Show the parameter values. $end
$dumpall
b0 (
b1 '
$end
#0
$dumpvars
b0 *
b0 )
0&
1%
1$
0#
1"
0!
$end
#104150
0$
#200000
0%
#208300
1$
#312450
0$
#416600
1$
#520750
0$
#624900
1$
#729050
0$
#833200
1$
#937350
0$
#1000000
1&
#1041500
b1 )
1$
#1145650
0$
#1249800
1$
#1353950
0$
#1458100
1$
#1562250
0$
#1666400
1$
#1770550
0$
#1874700
1$
#1978850
0$
#2000000
1#
0"
0&
#2083000
b1 *
1$
#2187150
0$
#2291300
b10 *
1$
#2395450
0$
#2499600
b11 *
1$
#2603750
0$
#2707900
b100 *
1$
#2812050
0$
#2916200
b101 *
1$
#3020350
0$
#3124500
b110 *
1$
#3228650
0$
#3332800
b111 *
1$
#3436950
0$
#3541100
b1000 *
1$
#3645250
0$
#3749400
b1001 *
1$
#3853550
0$
#3957700
b1010 *
1$
#4061850
0$
#4166000
b1011 *
1$
#4270150
0$
#4374300
b1100 *
1$
#4478450
0$
#4582600
b1101 *
1$
#4686750
0$
#4790900
b1110 *
1$
#4895050
0$
#4999200
b1111 *
1$
#5103350
0$
#5207500
b10000 *
1$
#5311650
0$
#5415800
b10001 *
1$
#5519950
0$
#5624100
b10010 *
1$
#5728250
0$
#5832400
b10011 *
1$
#5936550
0$
#6040700
b10100 *
1$
#6144850
0$
#6249000
b10101 *
1$
#6353150
0$
#6457300
b10110 *
1$
#6561450
0$
#6665600
b10111 *
1$
#6769750
0$
#6873900
b11000 *
1$
#6978050
0$
#7082200
b11001 *
1$
#7186350
0$
#7290500
b11010 *
1$
#7394650
0$
#7498800
b11011 *
1$
#7602950
0$
#7707100
b11100 *
1$
#7811250
0$
#7915400
b11101 *
1$
#8019550
0$
#8123700
b11110 *
1$
#8227850
0$
#8332000
b11111 *
1$
#8436150
0$
#8540300
b100000 *
1$
#8644450
0$
#8748600
b100001 *
1$
#8852750
0$
#8956900
b100010 *
1$
#9061050
0$
#9165200
b100011 *
1$
#9269350
0$
#9373500
b100100 *
1$
#9477650
0$
#9581800
b100101 *
1$
#9685950
0$
#9790100
b100110 *
1$
#9894250
0$
#9998400
b100111 *
1$
#10102550
0$
#10206700
b101000 *
1$
#10310850
0$
#10415000
b101001 *
1$
#10519150
0$
#10623300
b101010 *
1$
#10727450
0$
#10831600
b101011 *
1$
#10935750
0$
#11039900
b101100 *
1$
#11144050
0$
#11248200
b101101 *
1$
#11352350
0$
#11456500
b101110 *
1$
#11560650
0$
#11664800
b101111 *
1$
#11768950
0$
#11873100
b110000 *
1$
#11977250
0$
#12081400
b110001 *
1$
#12185550
0$
#12289700
b110010 *
1$
#12393850
0$
#12498000
b110011 *
1$
#12602150
0$
#12706300
b110100 *
1$
#12810450
0$
#12914600
b110101 *
1$
#13018750
0$
#13122900
b110110 *
1$
#13227050
0$
#13331200
b110111 *
1$
#13435350
0$
#13539500
b111000 *
1$
#13643650
0$
#13747800
b111001 *
1$
#13851950
0$
#13956100
b111010 *
1$
#14060250
0$
#14164400
b111011 *
1$
#14268550
0$
#14372700
b111100 *
1$
#14476850
0$
#14581000
b111101 *
1$
#14685150
0$
#14789300
b111110 *
1$
#14893450
0$
#14997600
b111111 *
1$
#15101750
0$
#15205900
b1000000 *
1$
#15310050
0$
#15414200
b1000001 *
1$
#15518350
0$
#15622500
b1000010 *
1$
#15726650
0$
#15830800
b1000011 *
1$
#15934950
0$
#16039100
b1000100 *
1$
#16143250
0$
#16247400
b1000101 *
1$
#16351550
0$
#16455700
b1000110 *
1$
#16559850
0$
#16664000
b1000111 *
1$
#16768150
0$
#16872300
b1001000 *
1$
#16976450
0$
#17080600
b1001001 *
1$
#17184750
0$
#17288900
b1001010 *
1$
#17393050
0$
#17497200
b1001011 *
1$
#17601350
0$
#17705500
b1001100 *
1$
#17809650
0$
#17913800
b1001101 *
1$
#18017950
0$
#18122100
b1001110 *
1$
#18226250
0$
#18330400
b1001111 *
1$
#18434550
0$
#18538700
b1010000 *
1$
#18642850
0$
#18747000
b1010001 *
1$
#18851150
0$
#18955300
b1010010 *
1$
#19059450
0$
#19163600
b1010011 *
1$
#19267750
0$
#19371900
b1010100 *
1$
#19476050
0$
#19580200
b1010101 *
1$
#19684350
0$
#19788500
b1010110 *
1$
#19892650
0$
#19996800
b1010111 *
1$
#20100950
0$
#20205100
b1011000 *
1$
#20309250
0$
#20413400
b1011001 *
1$
#20517550
0$
#20621700
b1011010 *
1$
#20725850
0$
#20830000
b1011011 *
1$
#20934150
0$
#21038300
b1011100 *
1$
#21142450
0$
#21246600
b1011101 *
1$
#21350750
0$
#21454900
b1011110 *
1$
#21559050
0$
#21663200
b1011111 *
1$
#21767350
0$
#21871500
b1100000 *
1$
#21975650
0$
#22079800
b1100001 *
1$
#22183950
0$
#22288100
b1100010 *
1$
#22392250
0$
#22496400
b1100011 *
1$
#22600550
0$
#22704700
b1100100 *
1$
#22808850
0$
#22913000
b1100101 *
1$
#23017150
0$
#23121300
b1100110 *
1$
#23225450
0$
#23329600
b1100111 *
1$
#23433750
0$
#23537900
b1101000 *
1$
#23642050
0$
#23746200
b1101001 *
1$
#23850350
0$
#23954500
b1101010 *
1$
#24058650
0$
#24162800
b1101011 *
1$
#24266950
0$
#24371100
b1101100 *
1$
#24475250
0$
#24579400
b1101101 *
1$
#24683550
0$
#24787700
b1101110 *
1$
#24891850
0$
#24996000
b1101111 *
1$
#25100150
0$
#25204300
b1110000 *
1$
#25308450
0$
#25412600
b1110001 *
1$
#25516750
0$
#25620900
b1110010 *
1$
#25725050
0$
#25829200
b1110011 *
1$
#25933350
0$
#26037500
b1110100 *
1$
#26141650
0$
#26245800
b1110101 *
1$
#26349950
0$
#26454100
b1110110 *
1$
#26558250
0$
#26662400
b1110111 *
1$
#26766550
0$
#26870700
b1111000 *
1$
#26974850
0$
#27079000
b1111001 *
1$
#27183150
0$
#27287300
b1111010 *
1$
#27391450
0$
#27495600
b1111011 *
1$
#27599750
0$
#27703900
b1111100 *
1$
#27808050
0$
#27912200
b1111101 *
1$
#28016350
0$
#28120500
b1111110 *
1$
#28224650
0$
#28328800
b1111111 *
1$
#28432950
0$
#28537100
b10000000 *
1$
#28641250
0$
#28745400
b10000001 *
1$
#28849550
0$
#28953700
b10000010 *
1$
#29057850
0$
#29162000
b10000011 *
1$
#29266150
0$
#29370300
b10000100 *
1$
#29474450
0$
#29578600
b10000101 *
1$
#29682750
0$
#29786900
b10000110 *
1$
#29891050
0$
#29995200
b10000111 *
1$
#30099350
0$
#30203500
b10001000 *
1$
#30307650
0$
#30411800
b10001001 *
1$
#30515950
0$
#30620100
b10001010 *
1$
#30724250
0$
#30828400
b10001011 *
1$
#30932550
0$
#31036700
b10001100 *
1$
#31140850
0$
#31245000
b10001101 *
1$
#31349150
0$
#31453300
b10001110 *
1$
#31557450
0$
#31661600
b10001111 *
1$
#31765750
0$
#31869900
b10010000 *
1$
#31974050
0$
#32078200
b10010001 *
1$
#32182350
0$
#32286500
b10010010 *
1$
#32390650
0$
#32494800
b10010011 *
1$
#32598950
0$
#32703100
b10010100 *
1$
#32807250
0$
#32911400
b10010101 *
1$
#33015550
0$
#33119700
b10010110 *
1$
#33223850
0$
#33328000
b10010111 *
1$
#33432150
0$
#33536300
b10011000 *
1$
#33640450
0$
#33744600
b10011001 *
1$
#33848750
0$
#33952900
b10011010 *
1$
#34057050
0$
#34161200
b10011011 *
1$
#34265350
0$
#34369500
b10011100 *
1$
#34473650
0$
#34577800
b10011101 *
1$
#34681950
0$
#34786100
b10011110 *
1$
#34890250
0$
#34994400
b10011111 *
1$
#35098550
0$
#35202700
b10100000 *
1$
#35306850
0$
#35411000
b10100001 *
1$
#35515150
0$
#35619300
b10100010 *
1$
#35723450
0$
#35827600
b10100011 *
1$
#35931750
0$
#36035900
b10100100 *
1$
#36140050
0$
#36244200
b10100101 *
1$
#36348350
0$
#36452500
b10100110 *
1$
#36556650
0$
#36660800
b10100111 *
1$
#36764950
0$
#36869100
b10101000 *
1$
#36973250
0$
#37077400
b10101001 *
1$
#37181550
0$
#37285700
b10101010 *
1$
#37389850
0$
#37494000
b10101011 *
1$
#37598150
0$
#37702300
b10101100 *
1$
#37806450
0$
#37910600
b10101101 *
1$
#38014750
0$
#38118900
b10101110 *
1$
#38223050
0$
#38327200
b10101111 *
1$
#38431350
0$
#38535500
b10110000 *
1$
#38639650
0$
#38743800
b10110001 *
1$
#38847950
0$
#38952100
b10110010 *
1$
#39056250
0$
#39160400
b10110011 *
1$
#39264550
0$
#39368700
b10110100 *
1$
#39472850
0$
#39577000
b10110101 *
1$
#39681150
0$
#39785300
b10110110 *
1$
#39889450
0$
#39993600
b10110111 *
1$
#40097750
0$
#40201900
b10111000 *
1$
#40306050
0$
#40410200
b10111001 *
1$
#40514350
0$
#40618500
b10111010 *
1$
#40722650
0$
#40826800
b10111011 *
1$
#40930950
0$
#41035100
b10111100 *
1$
#41139250
0$
#41243400
b10111101 *
1$
#41347550
0$
#41451700
b10111110 *
1$
#41555850
0$
#41660000
b10111111 *
1$
#41764150
0$
#41868300
b11000000 *
1$
#41972450
0$
#42076600
b11000001 *
1$
#42180750
0$
#42284900
b11000010 *
1$
#42389050
0$
#42493200
b11000011 *
1$
#42597350
0$
#42701500
b11000100 *
1$
#42805650
0$
#42909800
b11000101 *
1$
#43013950
0$
#43118100
b11000110 *
1$
#43222250
0$
#43326400
b11000111 *
1$
#43430550
0$
#43534700
b11001000 *
1$
#43638850
0$
#43743000
b11001001 *
1$
#43847150
0$
#43951300
b11001010 *
1$
#44055450
0$
#44159600
b11001011 *
1$
#44263750
0$
#44367900
b11001100 *
1$
#44472050
0$
#44576200
b11001101 *
1$
#44680350
0$
#44784500
b11001110 *
1$
#44888650
0$
#44992800
b11001111 *
1$
#45096950
0$
#45201100
b11010000 *
1$
#45305250
0$
#45409400
b11010001 *
1$
#45513550
0$
#45617700
b11010010 *
1$
#45721850
0$
#45826000
b11010011 *
1$
#45930150
0$
#46034300
b11010100 *
1$
#46138450
0$
#46242600
b11010101 *
1$
#46346750
0$
#46450900
b11010110 *
1$
#46555050
0$
#46659200
b11010111 *
1$
#46763350
0$
#46867500
b11011000 *
1$
#46971650
0$
#47075800
b11011001 *
1$
#47179950
0$
#47284100
b11011010 *
1$
#47388250
0$
#47492400
b11011011 *
1$
#47596550
0$
#47700700
b11011100 *
1$
#47804850
0$
#47909000
b11011101 *
1$
#48013150
0$
#48117300
b11011110 *
1$
#48221450
0$
#48325600
b11011111 *
1$
#48429750
0$
#48533900
b11100000 *
1$
#48638050
0$
#48742200
b11100001 *
1$
#48846350
0$
#48950500
b11100010 *
1$
#49054650
0$
#49158800
b11100011 *
1$
#49262950
0$
#49367100
b11100100 *
1$
#49471250
0$
#49575400
b11100101 *
1$
#49679550
0$
#49783700
b11100110 *
1$
#49887850
0$
#49992000
b11100111 *
1$
#50096150
0$
#50200300
b11101000 *
1$
#50304450
0$
#50408600
b11101001 *
1$
#50512750
0$
#50616900
b11101010 *
1$
#50721050
0$
#50825200
b11101011 *
1$
#50929350
0$
#51033500
b11101100 *
1$
#51137650
0$
#51241800
b11101101 *
1$
#51345950
0$
#51450100
b11101110 *
1$
#51554250
0$
#51658400
b11101111 *
1$
#51762550
0$
#51866700
b11110000 *
1$
#51970850
0$
#52075000
b11110001 *
1$
#52179150
0$
#52283300
b11110010 *
1$
#52387450
0$
#52491600
b11110011 *
1$
#52595750
0$
#52699900
b11110100 *
1$
#52804050
0$
#52908200
b11110101 *
1$
#53012350
0$
#53116500
b11110110 *
1$
#53220650
0$
#53324800
b11110111 *
1$
#53428950
0$
#53533100
b11111000 *
1$
#53637250
0$
#53741400
b11111001 *
1$
#53845550
0$
#53949700
b11111010 *
1$
#54053850
0$
#54158000
b11111011 *
1$
#54262150
0$
#54366300
b11111100 *
1$
#54470450
0$
#54574600
b11111101 *
1$
#54678750
0$
#54782900
b11111110 *
1$
#54887050
0$
#54991200
b11111111 *
1$
#55095350
0$
#55199500
b100000000 *
1$
#55303650
0$
#55407800
b100000001 *
1$
#55511950
0$
#55616100
b100000010 *
1$
#55720250
0$
#55824400
b100000011 *
1$
#55928550
0$
#56032700
b100000100 *
1$
#56136850
0$
#56241000
b100000101 *
1$
#56345150
0$
#56449300
b100000110 *
1$
#56553450
0$
#56657600
b100000111 *
1$
#56761750
0$
#56865900
b100001000 *
1$
#56970050
0$
#57074200
b100001001 *
1$
#57178350
0$
#57282500
b100001010 *
1$
#57386650
0$
#57490800
b100001011 *
1$
#57594950
0$
#57699100
b100001100 *
1$
#57803250
0$
#57907400
b100001101 *
1$
#58011550
0$
#58115700
b100001110 *
1$
#58219850
0$
#58324000
b100001111 *
1$
#58428150
0$
#58532300
b100010000 *
1$
#58636450
0$
#58740600
b100010001 *
1$
#58844750
0$
#58948900
b100010010 *
1$
#59053050
0$
#59157200
b100010011 *
1$
#59261350
0$
#59365500
b100010100 *
1$
#59469650
0$
#59573800
b100010101 *
1$
#59677950
0$
#59782100
b100010110 *
1$
#59886250
0$
#59990400
b100010111 *
1$
#60094550
0$
#60198700
b100011000 *
1$
#60302850
0$
#60407000
b100011001 *
1$
#60511150
0$
#60615300
b100011010 *
1$
#60719450
0$
#60823600
b100011011 *
1$
#60927750
0$
#61031900
b100011100 *
1$
#61136050
0$
#61240200
b100011101 *
1$
#61344350
0$
#61448500
b100011110 *
1$
#61552650
0$
#61656800
b100011111 *
1$
#61760950
0$
#61865100
b100100000 *
1$
#61969250
0$
#62073400
b100100001 *
1$
#62177550
0$
#62281700
b100100010 *
1$
#62385850
0$
#62490000
b100100011 *
1$
#62594150
0$
#62698300
b100100100 *
1$
#62802450
0$
#62906600
b100100101 *
1$
#63010750
0$
#63114900
b100100110 *
1$
#63219050
0$
#63323200
b100100111 *
1$
#63427350
0$
#63531500
b100101000 *
1$
#63635650
0$
#63739800
b100101001 *
1$
#63843950
0$
#63948100
b100101010 *
1$
#64052250
0$
#64156400
b100101011 *
1$
#64260550
0$
#64364700
b100101100 *
1$
#64468850
0$
#64573000
b100101101 *
1$
#64677150
0$
#64781300
b100101110 *
1$
#64885450
0$
#64989600
b100101111 *
1$
#65093750
0$
#65197900
b100110000 *
1$
#65302050
0$
#65406200
b100110001 *
1$
#65510350
0$
#65614500
b100110010 *
1$
#65718650
0$
#65822800
b100110011 *
1$
#65926950
0$
#66031100
b100110100 *
1$
#66135250
0$
#66239400
b100110101 *
1$
#66343550
0$
#66447700
b100110110 *
1$
#66551850
0$
#66656000
b100110111 *
1$
#66760150
0$
#66864300
b100111000 *
1$
#66968450
0$
#67072600
b100111001 *
1$
#67176750
0$
#67280900
b100111010 *
1$
#67385050
0$
#67489200
b100111011 *
1$
#67593350
0$
#67697500
b100111100 *
1$
#67801650
0$
#67905800
b100111101 *
1$
#68009950
0$
#68114100
b100111110 *
1$
#68218250
0$
#68322400
b100111111 *
1$
#68426550
0$
#68530700
b101000000 *
1$
#68634850
0$
#68739000
b101000001 *
1$
#68843150
0$
#68947300
b101000010 *
1$
#69051450
0$
#69155600
b101000011 *
1$
#69259750
0$
#69363900
b101000100 *
1$
#69468050
0$
#69572200
b101000101 *
1$
#69676350
0$
#69780500
b101000110 *
1$
#69884650
0$
#69988800
b101000111 *
1$
#70092950
0$
#70197100
b101001000 *
1$
#70301250
0$
#70405400
b101001001 *
1$
#70509550
0$
#70613700
b101001010 *
1$
#70717850
0$
#70822000
b101001011 *
1$
#70926150
0$
#71030300
b101001100 *
1$
#71134450
0$
#71238600
b101001101 *
1$
#71342750
0$
#71446900
b101001110 *
1$
#71551050
0$
#71655200
b101001111 *
1$
#71759350
0$
#71863500
b101010000 *
1$
#71967650
0$
#72071800
b101010001 *
1$
#72175950
0$
#72280100
b101010010 *
1$
#72384250
0$
#72488400
b101010011 *
1$
#72592550
0$
#72696700
b101010100 *
1$
#72800850
0$
#72905000
b101010101 *
1$
#73009150
0$
#73113300
b101010110 *
1$
#73217450
0$
#73321600
b101010111 *
1$
#73425750
0$
#73529900
b101011000 *
1$
#73634050
0$
#73738200
b101011001 *
1$
#73842350
0$
#73946500
b101011010 *
1$
#74050650
0$
#74154800
b101011011 *
1$
#74258950
0$
#74363100
b101011100 *
1$
#74467250
0$
#74571400
b101011101 *
1$
#74675550
0$
#74779700
b101011110 *
1$
#74883850
0$
#74988000
b101011111 *
1$
#75092150
0$
#75196300
b101100000 *
1$
#75300450
0$
#75404600
b101100001 *
1$
#75508750
0$
#75612900
b101100010 *
1$
#75717050
0$
#75821200
b101100011 *
1$
#75925350
0$
#76029500
b101100100 *
1$
#76133650
0$
#76237800
b101100101 *
1$
#76341950
0$
#76446100
b101100110 *
1$
#76550250
0$
#76654400
b101100111 *
1$
#76758550
0$
#76862700
b101101000 *
1$
#76966850
0$
#77071000
b101101001 *
1$
#77175150
0$
#77279300
b101101010 *
1$
#77383450
0$
#77487600
b101101011 *
1$
#77591750
0$
#77695900
b101101100 *
1$
#77800050
0$
#77904200
b101101101 *
1$
#78008350
0$
#78112500
b101101110 *
1$
#78216650
0$
#78320800
b101101111 *
1$
#78424950
0$
#78529100
b101110000 *
1$
#78633250
0$
#78737400
b101110001 *
1$
#78841550
0$
#78945700
b101110010 *
1$
#79049850
0$
#79154000
b101110011 *
1$
#79258150
0$
#79362300
b101110100 *
1$
#79466450
0$
#79570600
b101110101 *
1$
#79674750
0$
#79778900
b101110110 *
1$
#79883050
0$
#79987200
b101110111 *
1$
#80091350
0$
#80195500
b101111000 *
1$
#80299650
0$
#80403800
b101111001 *
1$
#80507950
0$
#80612100
b101111010 *
1$
#80716250
0$
#80820400
b101111011 *
1$
#80924550
0$
#81028700
b101111100 *
1$
#81132850
0$
#81237000
b101111101 *
1$
#81341150
0$
#81445300
b101111110 *
1$
#81549450
0$
#81653600
b101111111 *
1$
#81757750
0$
#81861900
b110000000 *
1$
#81966050
0$
#82070200
b110000001 *
1$
#82174350
0$
#82278500
b110000010 *
1$
#82382650
0$
#82486800
b110000011 *
1$
#82590950
0$
#82695100
b110000100 *
1$
#82799250
0$
#82903400
b110000101 *
1$
#83007550
0$
#83111700
b110000110 *
1$
#83215850
0$
#83320000
b110000111 *
1$
#83424150
0$
#83528300
b110001000 *
1$
#83632450
0$
#83736600
b110001001 *
1$
#83840750
0$
#83944900
b110001010 *
1$
#84049050
0$
#84153200
b110001011 *
1$
#84257350
0$
#84361500
b110001100 *
1$
#84465650
0$
#84569800
b110001101 *
1$
#84673950
0$
#84778100
b110001110 *
1$
#84882250
0$
#84986400
b110001111 *
1$
#85090550
0$
#85194700
b110010000 *
1$
#85298850
0$
#85403000
b110010001 *
1$
#85507150
0$
#85611300
b110010010 *
1$
#85715450
0$
#85819600
b110010011 *
1$
#85923750
0$
#86027900
b110010100 *
1$
#86132050
0$
#86236200
b110010101 *
1$
#86340350
0$
#86444500
b110010110 *
1$
#86548650
0$
#86652800
b110010111 *
1$
#86756950
0$
#86861100
b110011000 *
1$
#86965250
0$
#87069400
b110011001 *
1$
#87173550
0$
#87277700
b110011010 *
1$
#87381850
0$
#87486000
b110011011 *
1$
#87590150
0$
#87694300
b110011100 *
1$
#87798450
0$
#87902600
b110011101 *
1$
#88006750
0$
#88110900
b110011110 *
1$
#88215050
0$
#88319200
b110011111 *
1$
#88423350
0$
#88527500
b110100000 *
1$
#88631650
0$
#88735800
b110100001 *
1$
#88839950
0$
#88944100
b110100010 *
1$
#89048250
0$
#89152400
b110100011 *
1$
#89256550
0$
#89360700
b110100100 *
1$
#89464850
0$
#89569000
b110100101 *
1$
#89673150
0$
#89777300
b110100110 *
1$
#89881450
0$
#89985600
b110100111 *
1$
#90089750
0$
#90193900
b110101000 *
1$
#90298050
0$
#90402200
b110101001 *
1$
#90506350
0$
#90610500
b110101010 *
1$
#90714650
0$
#90818800
b110101011 *
1$
#90922950
0$
#91027100
b110101100 *
1$
#91131250
0$
#91235400
b110101101 *
1$
#91339550
0$
#91443700
b110101110 *
1$
#91547850
0$
#91652000
b110101111 *
1$
#91756150
0$
#91860300
b110110000 *
1$
#91964450
0$
#92068600
b110110001 *
1$
#92172750
0$
#92276900
b110110010 *
1$
#92381050
0$
#92485200
b110110011 *
1$
#92589350
0$
#92693500
b110110100 *
1$
#92797650
0$
#92901800
b110110101 *
1$
#93005950
0$
#93110100
b110110110 *
1$
#93214250
0$
#93318400
b110110111 *
1$
#93422550
0$
#93526700
b110111000 *
1$
#93630850
0$
#93735000
b110111001 *
1$
#93839150
0$
#93943300
b110111010 *
1$
#94047450
0$
#94151600
b110111011 *
1$
#94255750
0$
#94359900
b110111100 *
1$
#94464050
0$
#94568200
b110111101 *
1$
#94672350
0$
#94776500
b110111110 *
1$
#94880650
0$
#94984800
b110111111 *
1$
#95088950
0$
#95193100
b111000000 *
1$
#95297250
0$
#95401400
b111000001 *
1$
#95505550
0$
#95609700
b111000010 *
1$
#95713850
0$
#95818000
b111000011 *
1$
#95922150
0$
#96026300
b111000100 *
1$
#96130450
0$
#96234600
b111000101 *
1$
#96338750
0$
#96442900
b111000110 *
1$
#96547050
0$
#96651200
b111000111 *
1$
#96755350
0$
#96859500
b111001000 *
1$
#96963650
0$
#97067800
b111001001 *
1$
#97171950
0$
#97276100
b111001010 *
1$
#97380250
0$
#97484400
b111001011 *
1$
#97588550
0$
#97692700
b111001100 *
1$
#97796850
0$
#97901000
b111001101 *
1$
#98005150
0$
#98109300
b111001110 *
1$
#98213450
0$
#98317600
b111001111 *
1$
#98421750
0$
#98525900
b111010000 *
1$
#98630050
0$
#98734200
b111010001 *
1$
#98838350
0$
#98942500
b111010010 *
1$
#99046650
0$
#99150800
b111010011 *
1$
#99254950
0$
#99359100
b111010100 *
1$
#99463250
0$
#99567400
b111010101 *
1$
#99671550
0$
#99775700
b111010110 *
1$
#99879850
0$
#99984000
b111010111 *
1$
#100088150
0$
#100192300
b111011000 *
1$
#100296450
0$
#100400600
b111011001 *
1$
#100504750
0$
#100608900
b111011010 *
1$
#100713050
0$
#100817200
b111011011 *
1$
#100921350
0$
#101025500
b111011100 *
1$
#101129650
0$
#101233800
b111011101 *
1$
#101337950
0$
#101442100
b111011110 *
1$
#101546250
0$
#101650400
b111011111 *
1$
#101754550
0$
#101858700
b111100000 *
1$
#101962850
0$
#102067000
b111100001 *
1$
#102171150
0$
#102275300
b111100010 *
1$
#102379450
0$
#102483600
b111100011 *
1$
#102587750
0$
#102691900
b111100100 *
1$
#102796050
0$
#102900200
b111100101 *
1$
#103004350
0$
#103108500
b111100110 *
1$
#103212650
0$
#103316800
b111100111 *
1$
#103420950
0$
#103525100
b111101000 *
1$
#103629250
0$
#103733400
b111101001 *
1$
#103837550
0$
#103941700
b111101010 *
1$
#104045850
0$
#104150000
b111101011 *
1$
#104254150
0$
#104358300
b111101100 *
1$
#104462450
0$
#104566600
b111101101 *
1$
#104670750
0$
#104774900
b111101110 *
1$
#104879050
0$
#104983200
b111101111 *
1$
#105087350
0$
#105191500
b111110000 *
1$
#105295650
0$
#105399800
b111110001 *
1$
#105503950
0$
#105608100
b111110010 *
1$
#105712250
0$
#105816400
b111110011 *
1$
#105920550
0$
#106024700
b111110100 *
1$
#106128850
0$
#106233000
b111110101 *
1$
#106337150
0$
#106441300
b111110110 *
1$
#106545450
0$
#106649600
b111110111 *
1$
#106753750
0$
#106857900
b111111000 *
1$
#106962050
0$
#107066200
b111111001 *
1$
#107170350
0$
#107274500
b111111010 *
1$
#107378650
0$
#107482800
b111111011 *
1$
#107586950
0$
#107691100
b111111100 *
1$
#107795250
0$
#107899400
b111111101 *
1$
#108003550
0$
#108107700
b111111110 *
1$
#108211850
0$
#108316000
b111111111 *
1$
#108420150
0$
#108524300
b1000000000 *
1$
#108628450
0$
#108732600
b1000000001 *
1$
#108836750
0$
#108940900
b1000000010 *
1$
#109045050
0$
#109149200
b1000000011 *
1$
#109253350
0$
#109357500
b1000000100 *
1$
#109461650
0$
#109565800
b1000000101 *
1$
#109669950
0$
#109774100
b1000000110 *
1$
#109878250
0$
#109982400
b1000000111 *
1$
#110086550
0$
#110190700
b1000001000 *
1$
#110294850
0$
#110399000
b1000001001 *
1$
#110503150
0$
#110607300
b1000001010 *
1$
#110711450
0$
#110815600
b1000001011 *
1$
#110919750
0$
#111023900
b1000001100 *
1$
#111128050
0$
#111232200
b1000001101 *
1$
#111336350
0$
#111440500
b1000001110 *
1$
#111544650
0$
#111648800
b1000001111 *
1$
#111752950
0$
#111857100
b1000010000 *
1$
#111961250
0$
#112065400
b1000010001 *
1$
#112169550
0$
#112273700
b1000010010 *
1$
#112377850
0$
#112482000
b1000010011 *
1$
#112586150
0$
#112690300
b1000010100 *
1$
#112794450
0$
#112898600
b1000010101 *
1$
#113002750
0$
#113106900
b1000010110 *
1$
#113211050
0$
#113315200
b1000010111 *
1$
#113419350
0$
#113523500
b1000011000 *
1$
#113627650
0$
#113731800
b1000011001 *
1$
#113835950
0$
#113940100
b1000011010 *
1$
#114044250
0$
#114148400
b1000011011 *
1$
#114252550
0$
#114356700
b1000011100 *
1$
#114460850
0$
#114565000
b1000011101 *
1$
#114669150
0$
#114773300
b1000011110 *
1$
#114877450
0$
#114981600
b1000011111 *
1$
#115085750
0$
#115189900
b1000100000 *
1$
#115294050
0$
#115398200
b1000100001 *
1$
#115502350
0$
#115606500
b1000100010 *
1$
#115710650
0$
#115814800
b1000100011 *
1$
#115918950
0$
#116023100
b1000100100 *
1$
#116127250
0$
#116231400
b1000100101 *
1$
#116335550
0$
#116439700
b1000100110 *
1$
#116543850
0$
#116648000
b1000100111 *
1$
#116752150
0$
#116856300
b1000101000 *
1$
#116960450
0$
#117064600
b1000101001 *
1$
#117168750
0$
#117272900
b1000101010 *
1$
#117377050
0$
#117481200
b1000101011 *
1$
#117585350
0$
#117689500
b1000101100 *
1$
#117793650
0$
#117897800
b1000101101 *
1$
#118001950
0$
#118106100
b1000101110 *
1$
#118210250
0$
#118314400
b1000101111 *
1$
#118418550
0$
#118522700
b1000110000 *
1$
#118626850
0$
#118731000
b1000110001 *
1$
#118835150
0$
#118939300
b1000110010 *
1$
#119043450
0$
